Compiled from "LambdaJ.java"
public class com.robertmayer.lambdaj.LambdaJ {
  public static final int EOF;

  public static final int TOKEN_MAX;

  public static final int TRC_NONE;

  public static final int TRC_EVAL;

  public static final int TRC_ENV;

  public static final int TRC_PRIM;

  public static final int TRC_PARSE;

  public static final int TRC_TOK;

  public static final int TRC_LEX;

  public int trace;

  private com.robertmayer.lambdaj.LambdaJ$Tracer tracer;

  private boolean HAVE_LABELS;

  private boolean HAVE_NIL;

  private boolean HAVE_T;

  private boolean HAVE_XTRA;

  private boolean HAVE_DOUBLE;

  private boolean HAVE_STRING;

  private boolean HAVE_IO;

  private boolean HAVE_UTIL;

  private boolean HAVE_APPLY;

  private boolean HAVE_CONS;

  private boolean HAVE_COND;

  private boolean HAVE_ATOM;

  private boolean HAVE_EQ;

  private boolean HAVE_QUOTE;

  private com.robertmayer.lambdaj.LambdaJ$SymbolTable symtab;

  private java.util.function.Supplier<java.lang.Object> sApply;

  private java.util.function.Supplier<java.lang.Object> sCond;

  private java.util.function.Supplier<java.lang.Object> sIf;

  private java.util.function.Supplier<java.lang.Object> sLabels;

  private java.util.function.Supplier<java.lang.Object> sLambda;

  private java.util.function.Supplier<java.lang.Object> sQuote;

  private java.util.function.Supplier<java.lang.Object> expTrue;

  private int maxEvalStack;

  private int maxEvalLevel;

  private static final java.util.regex.Pattern dQuotePattern;

  private static final java.util.regex.Pattern bSlashPattern;

  public com.robertmayer.lambdaj.LambdaJ();
    Code:
       0: aload_0
       1: invokespecial #13                 // Method java/lang/Object."<init>":()V
       4: aload_0
       5: iconst_0
       6: putfield      #15                 // Field trace:I
       9: aload_0
      10: getstatic     #16                 // Field java/lang/System.err:Ljava/io/PrintStream;
      13: dup
      14: invokevirtual #17                 // Method java/lang/Object.getClass:()Ljava/lang/Class;
      17: pop
      18: invokedynamic #18,  0             // InvokeDynamic #0:println:(Ljava/io/PrintStream;)Lcom/robertmayer/lambdaj/LambdaJ$Tracer;
      23: putfield      #6                  // Field tracer:Lcom/robertmayer/lambdaj/LambdaJ$Tracer;
      26: aload_0
      27: iconst_1
      28: putfield      #19                 // Field HAVE_LABELS:Z
      31: aload_0
      32: iconst_1
      33: putfield      #20                 // Field HAVE_NIL:Z
      36: aload_0
      37: iconst_1
      38: putfield      #21                 // Field HAVE_T:Z
      41: aload_0
      42: iconst_1
      43: putfield      #22                 // Field HAVE_XTRA:Z
      46: aload_0
      47: iconst_1
      48: putfield      #7                  // Field HAVE_DOUBLE:Z
      51: aload_0
      52: iconst_1
      53: putfield      #8                  // Field HAVE_STRING:Z
      56: aload_0
      57: iconst_1
      58: putfield      #23                 // Field HAVE_IO:Z
      61: aload_0
      62: iconst_1
      63: putfield      #24                 // Field HAVE_UTIL:Z
      66: aload_0
      67: iconst_1
      68: putfield      #25                 // Field HAVE_APPLY:Z
      71: aload_0
      72: iconst_1
      73: putfield      #26                 // Field HAVE_CONS:Z
      76: aload_0
      77: iconst_1
      78: putfield      #27                 // Field HAVE_COND:Z
      81: aload_0
      82: iconst_1
      83: putfield      #28                 // Field HAVE_ATOM:Z
      86: aload_0
      87: iconst_1
      88: putfield      #29                 // Field HAVE_EQ:Z
      91: aload_0
      92: iconst_1
      93: putfield      #2                  // Field HAVE_QUOTE:Z
      96: return

  public void haveMinPlus();
    Code:
       0: aload_0
       1: iconst_0
       2: putfield      #20                 // Field HAVE_NIL:Z
       5: aload_0
       6: iconst_0
       7: putfield      #21                 // Field HAVE_T:Z
      10: aload_0
      11: iconst_0
      12: putfield      #22                 // Field HAVE_XTRA:Z
      15: aload_0
      16: iconst_0
      17: putfield      #7                  // Field HAVE_DOUBLE:Z
      20: aload_0
      21: iconst_0
      22: putfield      #8                  // Field HAVE_STRING:Z
      25: aload_0
      26: iconst_0
      27: putfield      #23                 // Field HAVE_IO:Z
      30: aload_0
      31: iconst_0
      32: putfield      #24                 // Field HAVE_UTIL:Z
      35: return

  public void haveMin();
    Code:
       0: aload_0
       1: invokevirtual #30                 // Method haveMinPlus:()V
       4: aload_0
       5: iconst_0
       6: putfield      #25                 // Field HAVE_APPLY:Z
       9: aload_0
      10: iconst_0
      11: putfield      #19                 // Field HAVE_LABELS:Z
      14: return

  public void haveLambdaPlus();
    Code:
       0: aload_0
       1: invokevirtual #31                 // Method haveMin:()V
       4: aload_0
       5: iconst_0
       6: putfield      #26                 // Field HAVE_CONS:Z
       9: aload_0
      10: iconst_0
      11: putfield      #27                 // Field HAVE_COND:Z
      14: return

  public void haveLambda();
    Code:
       0: aload_0
       1: invokevirtual #32                 // Method haveLambdaPlus:()V
       4: aload_0
       5: iconst_0
       6: putfield      #28                 // Field HAVE_ATOM:Z
       9: aload_0
      10: iconst_0
      11: putfield      #29                 // Field HAVE_EQ:Z
      14: aload_0
      15: iconst_0
      16: putfield      #2                  // Field HAVE_QUOTE:Z
      19: return

  private static boolean isWhiteSpace(int);
    Code:
       0: iload_0
       1: bipush        32
       3: if_icmpeq     24
       6: iload_0
       7: bipush        9
       9: if_icmpeq     24
      12: iload_0
      13: bipush        10
      15: if_icmpeq     24
      18: iload_0
      19: bipush        13
      21: if_icmpne     28
      24: iconst_1
      25: goto          29
      28: iconst_0
      29: ireturn

  private static boolean isSExSyntaxChar(int);
    Code:
       0: iload_0
       1: bipush        40
       3: if_icmpeq     18
       6: iload_0
       7: bipush        41
       9: if_icmpeq     18
      12: iload_0
      13: bipush        39
      15: if_icmpne     22
      18: iconst_1
      19: goto          23
      22: iconst_0
      23: ireturn

  private static boolean containsSExSyntaxOrBlank(java.lang.String);
    Code:
       0: iconst_0
       1: istore_1
       2: iload_1
       3: aload_0
       4: invokevirtual #33                 // Method java/lang/String.length:()I
       7: if_icmpge     40
      10: aload_0
      11: iload_1
      12: invokevirtual #34                 // Method java/lang/String.charAt:(I)C
      15: dup
      16: istore_2
      17: invokestatic  #9                  // Method isSExSyntaxChar:(I)Z
      20: ifeq          25
      23: iconst_1
      24: ireturn
      25: iload_2
      26: invokestatic  #10                 // Method isWhiteSpace:(I)Z
      29: ifeq          34
      32: iconst_1
      33: ireturn
      34: iinc          1, 1
      37: goto          2
      40: iconst_0
      41: ireturn

  private void setSymtab(com.robertmayer.lambdaj.LambdaJ$SymbolTable);
    Code:
       0: aload_0
       1: aload_1
       2: putfield      #35                 // Field symtab:Lcom/robertmayer/lambdaj/LambdaJ$SymbolTable;
       5: aload_0
       6: aload_0
       7: aload_1
       8: invokedynamic #36,  0             // InvokeDynamic #1:get:(Lcom/robertmayer/lambdaj/LambdaJ;Lcom/robertmayer/lambdaj/LambdaJ$SymbolTable;)Ljava/util/function/Supplier;
      13: putfield      #37                 // Field sApply:Ljava/util/function/Supplier;
      16: aload_0
      17: aload_0
      18: aload_1
      19: invokedynamic #38,  0             // InvokeDynamic #2:get:(Lcom/robertmayer/lambdaj/LambdaJ;Lcom/robertmayer/lambdaj/LambdaJ$SymbolTable;)Ljava/util/function/Supplier;
      24: putfield      #39                 // Field sCond:Ljava/util/function/Supplier;
      27: aload_0
      28: aload_0
      29: aload_1
      30: invokedynamic #40,  0             // InvokeDynamic #3:get:(Lcom/robertmayer/lambdaj/LambdaJ;Lcom/robertmayer/lambdaj/LambdaJ$SymbolTable;)Ljava/util/function/Supplier;
      35: putfield      #41                 // Field sIf:Ljava/util/function/Supplier;
      38: aload_0
      39: aload_0
      40: aload_1
      41: invokedynamic #42,  0             // InvokeDynamic #4:get:(Lcom/robertmayer/lambdaj/LambdaJ;Lcom/robertmayer/lambdaj/LambdaJ$SymbolTable;)Ljava/util/function/Supplier;
      46: putfield      #43                 // Field sLabels:Ljava/util/function/Supplier;
      49: aload_0
      50: aload_0
      51: aload_1
      52: invokedynamic #44,  0             // InvokeDynamic #5:get:(Lcom/robertmayer/lambdaj/LambdaJ;Lcom/robertmayer/lambdaj/LambdaJ$SymbolTable;)Ljava/util/function/Supplier;
      57: putfield      #45                 // Field sLambda:Ljava/util/function/Supplier;
      60: aload_0
      61: aload_0
      62: aload_1
      63: invokedynamic #46,  0             // InvokeDynamic #6:get:(Lcom/robertmayer/lambdaj/LambdaJ;Lcom/robertmayer/lambdaj/LambdaJ$SymbolTable;)Ljava/util/function/Supplier;
      68: putfield      #47                 // Field sQuote:Ljava/util/function/Supplier;
      71: aload_0
      72: aload_0
      73: invokedynamic #48,  0             // InvokeDynamic #7:get:(Lcom/robertmayer/lambdaj/LambdaJ;)Ljava/util/function/Supplier;
      78: putfield      #49                 // Field expTrue:Ljava/util/function/Supplier;
      81: return

  private java.lang.Object makeExpTrue();
    Code:
       0: aload_0
       1: getfield      #21                 // Field HAVE_T:Z
       4: ifeq          19
       7: aload_0
       8: getfield      #35                 // Field symtab:Lcom/robertmayer/lambdaj/LambdaJ$SymbolTable;
      11: ldc           #50                 // String t
      13: invokeinterface #51,  2           // InterfaceMethod com/robertmayer/lambdaj/LambdaJ$SymbolTable.intern:(Ljava/lang/String;)Ljava/lang/Object;
      18: areturn
      19: aload_0
      20: getfield      #2                  // Field HAVE_QUOTE:Z
      23: ifeq          56
      26: aload_0
      27: getfield      #35                 // Field symtab:Lcom/robertmayer/lambdaj/LambdaJ$SymbolTable;
      30: ldc           #52                 // String quote
      32: invokeinterface #51,  2           // InterfaceMethod com/robertmayer/lambdaj/LambdaJ$SymbolTable.intern:(Ljava/lang/String;)Ljava/lang/Object;
      37: aload_0
      38: getfield      #35                 // Field symtab:Lcom/robertmayer/lambdaj/LambdaJ$SymbolTable;
      41: ldc           #50                 // String t
      43: invokeinterface #51,  2           // InterfaceMethod com/robertmayer/lambdaj/LambdaJ$SymbolTable.intern:(Ljava/lang/String;)Ljava/lang/Object;
      48: aconst_null
      49: invokestatic  #3                  // Method cons:(Ljava/lang/Object;Ljava/lang/Object;)Lcom/robertmayer/lambdaj/LambdaJ$ConsCell;
      52: invokestatic  #3                  // Method cons:(Ljava/lang/Object;Ljava/lang/Object;)Lcom/robertmayer/lambdaj/LambdaJ$ConsCell;
      55: areturn
      56: new           #53                 // class com/robertmayer/lambdaj/LambdaJ$LambdaJError
      59: dup
      60: ldc           #54                 // String truthiness needs support for 't' or 'quote'
      62: invokespecial #55                 // Method com/robertmayer/lambdaj/LambdaJ$LambdaJError."<init>":(Ljava/lang/String;)V
      65: athrow

  private java.lang.Object eval(java.lang.Object, com.robertmayer.lambdaj.LambdaJ$ConsCell, int, int);
    Code:
       0: iconst_0
       1: istore        5
       3: iinc          4, -1
       6: iinc          4, 1
       9: aload_0
      10: iload         5
      12: ifeq          20
      15: ldc           #56                 // String eval TC
      17: goto          22
      20: ldc           #57                 // String eval
      22: aload_1
      23: aload_2
      24: iload_3
      25: iload         4
      27: invokespecial #58                 // Method dbgEvalStart:(Ljava/lang/String;Ljava/lang/Object;Lcom/robertmayer/lambdaj/LambdaJ$ConsCell;II)V
      30: aload_1
      31: invokestatic  #1                  // Method symbolp:(Ljava/lang/Object;)Z
      34: ifeq          144
      37: aload_1
      38: ifnonnull     67
      41: aconst_null
      42: astore        6
      44: aload_0
      45: iload         5
      47: ifeq          55
      50: ldc           #56                 // String eval TC
      52: goto          57
      55: ldc           #57                 // String eval
      57: aload_1
      58: iload_3
      59: iload         4
      61: invokespecial #59                 // Method dbgEvalDone:(Ljava/lang/String;Ljava/lang/Object;II)V
      64: aload         6
      66: areturn
      67: aload_1
      68: aload_2
      69: invokestatic  #60                 // Method assoc:(Ljava/lang/Object;Ljava/lang/Object;)Ljava/lang/Object;
      72: astore        6
      74: aload         6
      76: ifnull        112
      79: aload         6
      81: invokestatic  #5                  // Method cdr:(Ljava/lang/Object;)Ljava/lang/Object;
      84: invokestatic  #4                  // Method car:(Ljava/lang/Object;)Ljava/lang/Object;
      87: astore        7
      89: aload_0
      90: iload         5
      92: ifeq          100
      95: ldc           #56                 // String eval TC
      97: goto          102
     100: ldc           #57                 // String eval
     102: aload_1
     103: iload_3
     104: iload         4
     106: invokespecial #59                 // Method dbgEvalDone:(Ljava/lang/String;Ljava/lang/Object;II)V
     109: aload         7
     111: areturn
     112: new           #53                 // class com/robertmayer/lambdaj/LambdaJ$LambdaJError
     115: dup
     116: new           #61                 // class java/lang/StringBuilder
     119: dup
     120: invokespecial #62                 // Method java/lang/StringBuilder."<init>":()V
     123: ldc           #63                 // String symbol |
     125: invokevirtual #64                 // Method java/lang/StringBuilder.append:(Ljava/lang/String;)Ljava/lang/StringBuilder;
     128: aload_1
     129: invokevirtual #65                 // Method java/lang/StringBuilder.append:(Ljava/lang/Object;)Ljava/lang/StringBuilder;
     132: ldc           #66                 // String | is undefined
     134: invokevirtual #64                 // Method java/lang/StringBuilder.append:(Ljava/lang/String;)Ljava/lang/StringBuilder;
     137: invokevirtual #67                 // Method java/lang/StringBuilder.toString:()Ljava/lang/String;
     140: invokespecial #55                 // Method com/robertmayer/lambdaj/LambdaJ$LambdaJError."<init>":(Ljava/lang/String;)V
     143: athrow
     144: aload_1
     145: invokestatic  #68                 // Method atom:(Ljava/lang/Object;)Z
     148: ifeq          177
     151: aload_1
     152: astore        6
     154: aload_0
     155: iload         5
     157: ifeq          165
     160: ldc           #56                 // String eval TC
     162: goto          167
     165: ldc           #57                 // String eval
     167: aload_1
     168: iload_3
     169: iload         4
     171: invokespecial #59                 // Method dbgEvalDone:(Ljava/lang/String;Ljava/lang/Object;II)V
     174: aload         6
     176: areturn
     177: aload_1
     178: invokestatic  #4                  // Method car:(Ljava/lang/Object;)Ljava/lang/Object;
     181: invokestatic  #1                  // Method symbolp:(Ljava/lang/Object;)Z
     184: ifeq          1047
     187: aload_0
     188: getfield      #2                  // Field HAVE_QUOTE:Z
     191: ifeq          251
     194: aload_1
     195: invokestatic  #4                  // Method car:(Ljava/lang/Object;)Ljava/lang/Object;
     198: aload_0
     199: getfield      #47                 // Field sQuote:Ljava/util/function/Supplier;
     202: invokeinterface #69,  1           // InterfaceMethod java/util/function/Supplier.get:()Ljava/lang/Object;
     207: if_acmpne     251
     210: ldc           #52                 // String quote
     212: aload_1
     213: invokestatic  #5                  // Method cdr:(Ljava/lang/Object;)Ljava/lang/Object;
     216: invokestatic  #70                 // Method oneArg:(Ljava/lang/String;Ljava/lang/Object;)V
     219: aload_1
     220: invokestatic  #5                  // Method cdr:(Ljava/lang/Object;)Ljava/lang/Object;
     223: invokestatic  #4                  // Method car:(Ljava/lang/Object;)Ljava/lang/Object;
     226: astore        6
     228: aload_0
     229: iload         5
     231: ifeq          239
     234: ldc           #56                 // String eval TC
     236: goto          241
     239: ldc           #57                 // String eval
     241: aload_1
     242: iload_3
     243: iload         4
     245: invokespecial #59                 // Method dbgEvalDone:(Ljava/lang/String;Ljava/lang/Object;II)V
     248: aload         6
     250: areturn
     251: aload_0
     252: getfield      #22                 // Field HAVE_XTRA:Z
     255: ifeq          384
     258: aload_1
     259: invokestatic  #4                  // Method car:(Ljava/lang/Object;)Ljava/lang/Object;
     262: aload_0
     263: getfield      #41                 // Field sIf:Ljava/util/function/Supplier;
     266: invokeinterface #69,  1           // InterfaceMethod java/util/function/Supplier.get:()Ljava/lang/Object;
     271: if_acmpne     384
     274: ldc           #71                 // String if
     276: aload_1
     277: invokestatic  #5                  // Method cdr:(Ljava/lang/Object;)Ljava/lang/Object;
     280: iconst_2
     281: iconst_3
     282: aload_1
     283: invokestatic  #72                 // Method nArgs:(Ljava/lang/String;Ljava/lang/Object;IILjava/lang/Object;)V
     286: aload_0
     287: aload_1
     288: invokestatic  #5                  // Method cdr:(Ljava/lang/Object;)Ljava/lang/Object;
     291: invokestatic  #4                  // Method car:(Ljava/lang/Object;)Ljava/lang/Object;
     294: aload_2
     295: iload_3
     296: iconst_1
     297: iadd
     298: iload         4
     300: iconst_1
     301: iadd
     302: invokespecial #73                 // Method eval:(Ljava/lang/Object;Lcom/robertmayer/lambdaj/LambdaJ$ConsCell;II)Ljava/lang/Object;
     305: ifnull        325
     308: aload_1
     309: invokestatic  #5                  // Method cdr:(Ljava/lang/Object;)Ljava/lang/Object;
     312: invokestatic  #5                  // Method cdr:(Ljava/lang/Object;)Ljava/lang/Object;
     315: invokestatic  #4                  // Method car:(Ljava/lang/Object;)Ljava/lang/Object;
     318: astore_1
     319: iconst_1
     320: istore        5
     322: goto          6
     325: aload_1
     326: invokestatic  #5                  // Method cdr:(Ljava/lang/Object;)Ljava/lang/Object;
     329: invokestatic  #5                  // Method cdr:(Ljava/lang/Object;)Ljava/lang/Object;
     332: invokestatic  #5                  // Method cdr:(Ljava/lang/Object;)Ljava/lang/Object;
     335: ifnull        358
     338: aload_1
     339: invokestatic  #5                  // Method cdr:(Ljava/lang/Object;)Ljava/lang/Object;
     342: invokestatic  #5                  // Method cdr:(Ljava/lang/Object;)Ljava/lang/Object;
     345: invokestatic  #5                  // Method cdr:(Ljava/lang/Object;)Ljava/lang/Object;
     348: invokestatic  #4                  // Method car:(Ljava/lang/Object;)Ljava/lang/Object;
     351: astore_1
     352: iconst_1
     353: istore        5
     355: goto          6
     358: aconst_null
     359: astore        6
     361: aload_0
     362: iload         5
     364: ifeq          372
     367: ldc           #56                 // String eval TC
     369: goto          374
     372: ldc           #57                 // String eval
     374: aload_1
     375: iload_3
     376: iload         4
     378: invokespecial #59                 // Method dbgEvalDone:(Ljava/lang/String;Ljava/lang/Object;II)V
     381: aload         6
     383: areturn
     384: aload_1
     385: invokestatic  #4                  // Method car:(Ljava/lang/Object;)Ljava/lang/Object;
     388: aload_0
     389: getfield      #45                 // Field sLambda:Ljava/util/function/Supplier;
     392: invokeinterface #69,  1           // InterfaceMethod java/util/function/Supplier.get:()Ljava/lang/Object;
     397: if_acmpne     437
     400: ldc           #74                 // String lambda
     402: aload_1
     403: invokestatic  #5                  // Method cdr:(Ljava/lang/Object;)Ljava/lang/Object;
     406: iconst_2
     407: aload_1
     408: invokestatic  #75                 // Method nArgs:(Ljava/lang/String;Ljava/lang/Object;ILjava/lang/Object;)V
     411: aload_1
     412: astore        6
     414: aload_0
     415: iload         5
     417: ifeq          425
     420: ldc           #56                 // String eval TC
     422: goto          427
     425: ldc           #57                 // String eval
     427: aload_1
     428: iload_3
     429: iload         4
     431: invokespecial #59                 // Method dbgEvalDone:(Ljava/lang/String;Ljava/lang/Object;II)V
     434: aload         6
     436: areturn
     437: aload_0
     438: getfield      #19                 // Field HAVE_LABELS:Z
     441: ifeq          536
     444: aload_1
     445: invokestatic  #4                  // Method car:(Ljava/lang/Object;)Ljava/lang/Object;
     448: aload_0
     449: getfield      #43                 // Field sLabels:Ljava/util/function/Supplier;
     452: invokeinterface #69,  1           // InterfaceMethod java/util/function/Supplier.get:()Ljava/lang/Object;
     457: if_acmpne     536
     460: ldc           #76                 // String labels
     462: aload_1
     463: invokestatic  #5                  // Method cdr:(Ljava/lang/Object;)Ljava/lang/Object;
     466: iconst_2
     467: aload_1
     468: invokestatic  #75                 // Method nArgs:(Ljava/lang/String;Ljava/lang/Object;ILjava/lang/Object;)V
     471: aload_1
     472: invokestatic  #5                  // Method cdr:(Ljava/lang/Object;)Ljava/lang/Object;
     475: invokestatic  #4                  // Method car:(Ljava/lang/Object;)Ljava/lang/Object;
     478: checkcast     #77                 // class com/robertmayer/lambdaj/LambdaJ$ConsCell
     481: astore        6
     483: aload_1
     484: invokestatic  #5                  // Method cdr:(Ljava/lang/Object;)Ljava/lang/Object;
     487: invokestatic  #5                  // Method cdr:(Ljava/lang/Object;)Ljava/lang/Object;
     490: checkcast     #77                 // class com/robertmayer/lambdaj/LambdaJ$ConsCell
     493: astore        7
     495: aload_0
     496: aload         6
     498: aload         7
     500: aload_2
     501: iload_3
     502: iconst_1
     503: iadd
     504: iload         4
     506: iconst_1
     507: iadd
     508: invokespecial #78                 // Method evlabels:(Lcom/robertmayer/lambdaj/LambdaJ$ConsCell;Lcom/robertmayer/lambdaj/LambdaJ$ConsCell;Lcom/robertmayer/lambdaj/LambdaJ$ConsCell;II)Ljava/lang/Object;
     511: astore        8
     513: aload_0
     514: iload         5
     516: ifeq          524
     519: ldc           #56                 // String eval TC
     521: goto          526
     524: ldc           #57                 // String eval
     526: aload_1
     527: iload_3
     528: iload         4
     530: invokespecial #59                 // Method dbgEvalDone:(Ljava/lang/String;Ljava/lang/Object;II)V
     533: aload         8
     535: areturn
     536: aload_0
     537: getfield      #27                 // Field HAVE_COND:Z
     540: ifeq          653
     543: aload_1
     544: invokestatic  #4                  // Method car:(Ljava/lang/Object;)Ljava/lang/Object;
     547: aload_0
     548: getfield      #39                 // Field sCond:Ljava/util/function/Supplier;
     551: invokeinterface #69,  1           // InterfaceMethod java/util/function/Supplier.get:()Ljava/lang/Object;
     556: if_acmpne     653
     559: aload_1
     560: invokestatic  #5                  // Method cdr:(Ljava/lang/Object;)Ljava/lang/Object;
     563: checkcast     #77                 // class com/robertmayer/lambdaj/LambdaJ$ConsCell
     566: astore        6
     568: aload         6
     570: ifnull        627
     573: aload_0
     574: aload         6
     576: invokestatic  #4                  // Method car:(Ljava/lang/Object;)Ljava/lang/Object;
     579: invokestatic  #4                  // Method car:(Ljava/lang/Object;)Ljava/lang/Object;
     582: aload_2
     583: iload_3
     584: iconst_1
     585: iadd
     586: iload         4
     588: iconst_1
     589: iadd
     590: invokespecial #73                 // Method eval:(Ljava/lang/Object;Lcom/robertmayer/lambdaj/LambdaJ$ConsCell;II)Ljava/lang/Object;
     593: ifnull        614
     596: aload         6
     598: invokestatic  #4                  // Method car:(Ljava/lang/Object;)Ljava/lang/Object;
     601: invokestatic  #5                  // Method cdr:(Ljava/lang/Object;)Ljava/lang/Object;
     604: invokestatic  #4                  // Method car:(Ljava/lang/Object;)Ljava/lang/Object;
     607: astore_1
     608: iconst_1
     609: istore        5
     611: goto          6
     614: aload         6
     616: invokestatic  #5                  // Method cdr:(Ljava/lang/Object;)Ljava/lang/Object;
     619: checkcast     #77                 // class com/robertmayer/lambdaj/LambdaJ$ConsCell
     622: astore        6
     624: goto          568
     627: aconst_null
     628: astore        7
     630: aload_0
     631: iload         5
     633: ifeq          641
     636: ldc           #56                 // String eval TC
     638: goto          643
     641: ldc           #57                 // String eval
     643: aload_1
     644: iload_3
     645: iload         4
     647: invokespecial #59                 // Method dbgEvalDone:(Ljava/lang/String;Ljava/lang/Object;II)V
     650: aload         7
     652: areturn
     653: aload_0
     654: getfield      #25                 // Field HAVE_APPLY:Z
     657: ifeq          905
     660: aload_1
     661: invokestatic  #4                  // Method car:(Ljava/lang/Object;)Ljava/lang/Object;
     664: aload_0
     665: getfield      #37                 // Field sApply:Ljava/util/function/Supplier;
     668: invokeinterface #69,  1           // InterfaceMethod java/util/function/Supplier.get:()Ljava/lang/Object;
     673: if_acmpne     905
     676: ldc           #79                 // String apply
     678: aload_1
     679: invokestatic  #5                  // Method cdr:(Ljava/lang/Object;)Ljava/lang/Object;
     682: aload_1
     683: invokestatic  #80                 // Method twoArgs:(Ljava/lang/String;Ljava/lang/Object;Ljava/lang/Object;)V
     686: aload_0
     687: aload_1
     688: invokestatic  #5                  // Method cdr:(Ljava/lang/Object;)Ljava/lang/Object;
     691: invokestatic  #4                  // Method car:(Ljava/lang/Object;)Ljava/lang/Object;
     694: aload_2
     695: iload_3
     696: iconst_1
     697: iadd
     698: iload         4
     700: iconst_1
     701: iadd
     702: invokespecial #73                 // Method eval:(Ljava/lang/Object;Lcom/robertmayer/lambdaj/LambdaJ$ConsCell;II)Ljava/lang/Object;
     705: astore        6
     707: aload         6
     709: ifnonnull     755
     712: new           #53                 // class com/robertmayer/lambdaj/LambdaJ$LambdaJError
     715: dup
     716: new           #61                 // class java/lang/StringBuilder
     719: dup
     720: invokespecial #62                 // Method java/lang/StringBuilder."<init>":()V
     723: ldc           #81                 // String apply: cannot apply function nil. nil was the result of evaluating the expression
     725: invokevirtual #64                 // Method java/lang/StringBuilder.append:(Ljava/lang/String;)Ljava/lang/StringBuilder;
     728: aload_1
     729: invokestatic  #5                  // Method cdr:(Ljava/lang/Object;)Ljava/lang/Object;
     732: invokestatic  #4                  // Method car:(Ljava/lang/Object;)Ljava/lang/Object;
     735: invokestatic  #11                 // Method printSEx:(Ljava/lang/Object;)Ljava/lang/String;
     738: invokevirtual #64                 // Method java/lang/StringBuilder.append:(Ljava/lang/String;)Ljava/lang/StringBuilder;
     741: aload_1
     742: invokestatic  #82                 // Method errorExp:(Ljava/lang/Object;)Ljava/lang/String;
     745: invokevirtual #64                 // Method java/lang/StringBuilder.append:(Ljava/lang/String;)Ljava/lang/StringBuilder;
     748: invokevirtual #67                 // Method java/lang/StringBuilder.toString:()Ljava/lang/String;
     751: invokespecial #55                 // Method com/robertmayer/lambdaj/LambdaJ$LambdaJError."<init>":(Ljava/lang/String;)V
     754: athrow
     755: aload_0
     756: aload_1
     757: invokestatic  #5                  // Method cdr:(Ljava/lang/Object;)Ljava/lang/Object;
     760: invokestatic  #5                  // Method cdr:(Ljava/lang/Object;)Ljava/lang/Object;
     763: invokestatic  #4                  // Method car:(Ljava/lang/Object;)Ljava/lang/Object;
     766: aload_2
     767: iload_3
     768: iconst_1
     769: iadd
     770: iload         4
     772: iconst_1
     773: iadd
     774: invokespecial #73                 // Method eval:(Ljava/lang/Object;Lcom/robertmayer/lambdaj/LambdaJ$ConsCell;II)Ljava/lang/Object;
     777: astore        7
     779: aload         6
     781: invokestatic  #83                 // Method consp:(Ljava/lang/Object;)Z
     784: ifeq          801
     787: aload         6
     789: aload         7
     791: invokestatic  #3                  // Method cons:(Ljava/lang/Object;Ljava/lang/Object;)Lcom/robertmayer/lambdaj/LambdaJ$ConsCell;
     794: astore_1
     795: iconst_1
     796: istore        5
     798: goto          6
     801: aload         6
     803: invokestatic  #84                 // Method isPrim:(Ljava/lang/Object;)Z
     806: ifeq          849
     809: aload_0
     810: aload         6
     812: checkcast     #85                 // class com/robertmayer/lambdaj/LambdaJ$Primitive
     815: aload         7
     817: checkcast     #77                 // class com/robertmayer/lambdaj/LambdaJ$ConsCell
     820: iload_3
     821: invokespecial #86                 // Method applyPrimitive:(Lcom/robertmayer/lambdaj/LambdaJ$Primitive;Lcom/robertmayer/lambdaj/LambdaJ$ConsCell;I)Ljava/lang/Object;
     824: astore        8
     826: aload_0
     827: iload         5
     829: ifeq          837
     832: ldc           #56                 // String eval TC
     834: goto          839
     837: ldc           #57                 // String eval
     839: aload_1
     840: iload_3
     841: iload         4
     843: invokespecial #59                 // Method dbgEvalDone:(Ljava/lang/String;Ljava/lang/Object;II)V
     846: aload         8
     848: areturn
     849: new           #53                 // class com/robertmayer/lambdaj/LambdaJ$LambdaJError
     852: dup
     853: new           #61                 // class java/lang/StringBuilder
     856: dup
     857: invokespecial #62                 // Method java/lang/StringBuilder."<init>":()V
     860: ldc           #87                 // String apply: not a symbol or lambda:
     862: invokevirtual #64                 // Method java/lang/StringBuilder.append:(Ljava/lang/String;)Ljava/lang/StringBuilder;
     865: aload         6
     867: invokestatic  #11                 // Method printSEx:(Ljava/lang/Object;)Ljava/lang/String;
     870: invokevirtual #64                 // Method java/lang/StringBuilder.append:(Ljava/lang/String;)Ljava/lang/StringBuilder;
     873: ldc           #88                 // String . this was the result of evaluating the expression
     875: invokevirtual #64                 // Method java/lang/StringBuilder.append:(Ljava/lang/String;)Ljava/lang/StringBuilder;
     878: aload_1
     879: invokestatic  #5                  // Method cdr:(Ljava/lang/Object;)Ljava/lang/Object;
     882: invokestatic  #4                  // Method car:(Ljava/lang/Object;)Ljava/lang/Object;
     885: invokestatic  #11                 // Method printSEx:(Ljava/lang/Object;)Ljava/lang/String;
     888: invokevirtual #64                 // Method java/lang/StringBuilder.append:(Ljava/lang/String;)Ljava/lang/StringBuilder;
     891: aload_1
     892: invokestatic  #82                 // Method errorExp:(Ljava/lang/Object;)Ljava/lang/String;
     895: invokevirtual #64                 // Method java/lang/StringBuilder.append:(Ljava/lang/String;)Ljava/lang/StringBuilder;
     898: invokevirtual #67                 // Method java/lang/StringBuilder.toString:()Ljava/lang/String;
     901: invokespecial #55                 // Method com/robertmayer/lambdaj/LambdaJ$LambdaJError."<init>":(Ljava/lang/String;)V
     904: athrow
     905: aload_0
     906: aload_1
     907: invokestatic  #4                  // Method car:(Ljava/lang/Object;)Ljava/lang/Object;
     910: aload_2
     911: iload_3
     912: iconst_1
     913: iadd
     914: iload         4
     916: iconst_1
     917: iadd
     918: invokespecial #73                 // Method eval:(Ljava/lang/Object;Lcom/robertmayer/lambdaj/LambdaJ$ConsCell;II)Ljava/lang/Object;
     921: astore        6
     923: aload         6
     925: invokestatic  #83                 // Method consp:(Ljava/lang/Object;)Z
     928: ifeq          947
     931: aload         6
     933: aload_1
     934: invokestatic  #5                  // Method cdr:(Ljava/lang/Object;)Ljava/lang/Object;
     937: invokestatic  #3                  // Method cons:(Ljava/lang/Object;Ljava/lang/Object;)Lcom/robertmayer/lambdaj/LambdaJ$ConsCell;
     940: astore_1
     941: iconst_1
     942: istore        5
     944: goto          6
     947: aload         6
     949: invokestatic  #84                 // Method isPrim:(Ljava/lang/Object;)Z
     952: ifeq          1009
     955: aload_0
     956: aload         6
     958: checkcast     #85                 // class com/robertmayer/lambdaj/LambdaJ$Primitive
     961: aload_0
     962: aload_1
     963: invokestatic  #5                  // Method cdr:(Ljava/lang/Object;)Ljava/lang/Object;
     966: checkcast     #77                 // class com/robertmayer/lambdaj/LambdaJ$ConsCell
     969: aload_2
     970: iload_3
     971: iconst_1
     972: iadd
     973: iload         4
     975: iconst_1
     976: iadd
     977: invokespecial #89                 // Method evlis:(Lcom/robertmayer/lambdaj/LambdaJ$ConsCell;Lcom/robertmayer/lambdaj/LambdaJ$ConsCell;II)Lcom/robertmayer/lambdaj/LambdaJ$ConsCell;
     980: iload_3
     981: invokespecial #86                 // Method applyPrimitive:(Lcom/robertmayer/lambdaj/LambdaJ$Primitive;Lcom/robertmayer/lambdaj/LambdaJ$ConsCell;I)Ljava/lang/Object;
     984: astore        7
     986: aload_0
     987: iload         5
     989: ifeq          997
     992: ldc           #56                 // String eval TC
     994: goto          999
     997: ldc           #57                 // String eval
     999: aload_1
    1000: iload_3
    1001: iload         4
    1003: invokespecial #59                 // Method dbgEvalDone:(Ljava/lang/String;Ljava/lang/Object;II)V
    1006: aload         7
    1008: areturn
    1009: new           #53                 // class com/robertmayer/lambdaj/LambdaJ$LambdaJError
    1012: dup
    1013: new           #61                 // class java/lang/StringBuilder
    1016: dup
    1017: invokespecial #62                 // Method java/lang/StringBuilder."<init>":()V
    1020: ldc           #90                 // String not a function:
    1022: invokevirtual #64                 // Method java/lang/StringBuilder.append:(Ljava/lang/String;)Ljava/lang/StringBuilder;
    1025: aload         6
    1027: invokestatic  #11                 // Method printSEx:(Ljava/lang/Object;)Ljava/lang/String;
    1030: invokevirtual #64                 // Method java/lang/StringBuilder.append:(Ljava/lang/String;)Ljava/lang/StringBuilder;
    1033: aload_1
    1034: invokestatic  #82                 // Method errorExp:(Ljava/lang/Object;)Ljava/lang/String;
    1037: invokevirtual #64                 // Method java/lang/StringBuilder.append:(Ljava/lang/String;)Ljava/lang/StringBuilder;
    1040: invokevirtual #67                 // Method java/lang/StringBuilder.toString:()Ljava/lang/String;
    1043: invokespecial #55                 // Method com/robertmayer/lambdaj/LambdaJ$LambdaJError."<init>":(Ljava/lang/String;)V
    1046: athrow
    1047: aload_1
    1048: invokestatic  #4                  // Method car:(Ljava/lang/Object;)Ljava/lang/Object;
    1051: invokestatic  #83                 // Method consp:(Ljava/lang/Object;)Z
    1054: ifeq          1349
    1057: aload_1
    1058: invokestatic  #4                  // Method car:(Ljava/lang/Object;)Ljava/lang/Object;
    1061: invokestatic  #4                  // Method car:(Ljava/lang/Object;)Ljava/lang/Object;
    1064: aload_0
    1065: getfield      #45                 // Field sLambda:Ljava/util/function/Supplier;
    1068: invokeinterface #69,  1           // InterfaceMethod java/util/function/Supplier.get:()Ljava/lang/Object;
    1073: if_acmpne     1349
    1076: aload_1
    1077: invokestatic  #4                  // Method car:(Ljava/lang/Object;)Ljava/lang/Object;
    1080: invokestatic  #5                  // Method cdr:(Ljava/lang/Object;)Ljava/lang/Object;
    1083: astore        6
    1085: ldc           #74                 // String lambda
    1087: aload         6
    1089: iconst_2
    1090: aload_1
    1091: invokestatic  #75                 // Method nArgs:(Ljava/lang/String;Ljava/lang/Object;ILjava/lang/Object;)V
    1094: aload_2
    1095: astore        7
    1097: aload         6
    1099: invokestatic  #4                  // Method car:(Ljava/lang/Object;)Ljava/lang/Object;
    1102: checkcast     #77                 // class com/robertmayer/lambdaj/LambdaJ$ConsCell
    1105: astore        8
    1107: aload_1
    1108: invokestatic  #5                  // Method cdr:(Ljava/lang/Object;)Ljava/lang/Object;
    1111: checkcast     #77                 // class com/robertmayer/lambdaj/LambdaJ$ConsCell
    1114: astore        9
    1116: aload         8
    1118: ifnull        1185
    1121: aload         9
    1123: ifnull        1185
    1126: aload         8
    1128: invokestatic  #4                  // Method car:(Ljava/lang/Object;)Ljava/lang/Object;
    1131: aload_0
    1132: aload         9
    1134: invokestatic  #4                  // Method car:(Ljava/lang/Object;)Ljava/lang/Object;
    1137: aload_2
    1138: iload_3
    1139: iconst_1
    1140: iadd
    1141: iload         4
    1143: iconst_1
    1144: iadd
    1145: invokespecial #73                 // Method eval:(Ljava/lang/Object;Lcom/robertmayer/lambdaj/LambdaJ$ConsCell;II)Ljava/lang/Object;
    1148: aconst_null
    1149: invokestatic  #3                  // Method cons:(Ljava/lang/Object;Ljava/lang/Object;)Lcom/robertmayer/lambdaj/LambdaJ$ConsCell;
    1152: invokestatic  #3                  // Method cons:(Ljava/lang/Object;Ljava/lang/Object;)Lcom/robertmayer/lambdaj/LambdaJ$ConsCell;
    1155: aload         7
    1157: invokestatic  #3                  // Method cons:(Ljava/lang/Object;Ljava/lang/Object;)Lcom/robertmayer/lambdaj/LambdaJ$ConsCell;
    1160: astore        7
    1162: aload         8
    1164: invokestatic  #5                  // Method cdr:(Ljava/lang/Object;)Ljava/lang/Object;
    1167: checkcast     #77                 // class com/robertmayer/lambdaj/LambdaJ$ConsCell
    1170: astore        8
    1172: aload         9
    1174: invokestatic  #5                  // Method cdr:(Ljava/lang/Object;)Ljava/lang/Object;
    1177: checkcast     #77                 // class com/robertmayer/lambdaj/LambdaJ$ConsCell
    1180: astore        9
    1182: goto          1116
    1185: aload         8
    1187: ifnull        1228
    1190: new           #53                 // class com/robertmayer/lambdaj/LambdaJ$LambdaJError
    1193: dup
    1194: new           #61                 // class java/lang/StringBuilder
    1197: dup
    1198: invokespecial #62                 // Method java/lang/StringBuilder."<init>":()V
    1201: ldc           #91                 // String lambda: not enough arguments. parameters w/o argument:
    1203: invokevirtual #64                 // Method java/lang/StringBuilder.append:(Ljava/lang/String;)Ljava/lang/StringBuilder;
    1206: aload         8
    1208: invokestatic  #11                 // Method printSEx:(Ljava/lang/Object;)Ljava/lang/String;
    1211: invokevirtual #64                 // Method java/lang/StringBuilder.append:(Ljava/lang/String;)Ljava/lang/StringBuilder;
    1214: aload_1
    1215: invokestatic  #82                 // Method errorExp:(Ljava/lang/Object;)Ljava/lang/String;
    1218: invokevirtual #64                 // Method java/lang/StringBuilder.append:(Ljava/lang/String;)Ljava/lang/StringBuilder;
    1221: invokevirtual #67                 // Method java/lang/StringBuilder.toString:()Ljava/lang/String;
    1224: invokespecial #55                 // Method com/robertmayer/lambdaj/LambdaJ$LambdaJError."<init>":(Ljava/lang/String;)V
    1227: athrow
    1228: aload         9
    1230: ifnull        1271
    1233: new           #53                 // class com/robertmayer/lambdaj/LambdaJ$LambdaJError
    1236: dup
    1237: new           #61                 // class java/lang/StringBuilder
    1240: dup
    1241: invokespecial #62                 // Method java/lang/StringBuilder."<init>":()V
    1244: ldc           #92                 // String lambda: too many arguments. remaining arguments:
    1246: invokevirtual #64                 // Method java/lang/StringBuilder.append:(Ljava/lang/String;)Ljava/lang/StringBuilder;
    1249: aload         9
    1251: invokestatic  #11                 // Method printSEx:(Ljava/lang/Object;)Ljava/lang/String;
    1254: invokevirtual #64                 // Method java/lang/StringBuilder.append:(Ljava/lang/String;)Ljava/lang/StringBuilder;
    1257: aload_1
    1258: invokestatic  #82                 // Method errorExp:(Ljava/lang/Object;)Ljava/lang/String;
    1261: invokevirtual #64                 // Method java/lang/StringBuilder.append:(Ljava/lang/String;)Ljava/lang/StringBuilder;
    1264: invokevirtual #67                 // Method java/lang/StringBuilder.toString:()Ljava/lang/String;
    1267: invokespecial #55                 // Method com/robertmayer/lambdaj/LambdaJ$LambdaJError."<init>":(Ljava/lang/String;)V
    1270: athrow
    1271: aload         6
    1273: invokestatic  #5                  // Method cdr:(Ljava/lang/Object;)Ljava/lang/Object;
    1276: checkcast     #77                 // class com/robertmayer/lambdaj/LambdaJ$ConsCell
    1279: astore        10
    1281: aload         10
    1283: ifnull        1326
    1286: aload         10
    1288: invokestatic  #5                  // Method cdr:(Ljava/lang/Object;)Ljava/lang/Object;
    1291: ifnull        1326
    1294: aload_0
    1295: aload         10
    1297: invokestatic  #4                  // Method car:(Ljava/lang/Object;)Ljava/lang/Object;
    1300: aload         7
    1302: iload_3
    1303: iconst_1
    1304: iadd
    1305: iload         4
    1307: iconst_1
    1308: iadd
    1309: invokespecial #73                 // Method eval:(Ljava/lang/Object;Lcom/robertmayer/lambdaj/LambdaJ$ConsCell;II)Ljava/lang/Object;
    1312: pop
    1313: aload         10
    1315: invokestatic  #5                  // Method cdr:(Ljava/lang/Object;)Ljava/lang/Object;
    1318: checkcast     #77                 // class com/robertmayer/lambdaj/LambdaJ$ConsCell
    1321: astore        10
    1323: goto          1281
    1326: aload         10
    1328: ifnull        1346
    1331: aload         10
    1333: invokestatic  #4                  // Method car:(Ljava/lang/Object;)Ljava/lang/Object;
    1336: astore_1
    1337: aload         7
    1339: astore_2
    1340: iconst_1
    1341: istore        5
    1343: goto          6
    1346: goto          1399
    1349: aload_1
    1350: invokestatic  #4                  // Method car:(Ljava/lang/Object;)Ljava/lang/Object;
    1353: invokestatic  #68                 // Method atom:(Ljava/lang/Object;)Z
    1356: ifeq          1399
    1359: new           #53                 // class com/robertmayer/lambdaj/LambdaJ$LambdaJError
    1362: dup
    1363: new           #61                 // class java/lang/StringBuilder
    1366: dup
    1367: invokespecial #62                 // Method java/lang/StringBuilder."<init>":()V
    1370: ldc           #90                 // String not a function:
    1372: invokevirtual #64                 // Method java/lang/StringBuilder.append:(Ljava/lang/String;)Ljava/lang/StringBuilder;
    1375: aload_1
    1376: invokestatic  #4                  // Method car:(Ljava/lang/Object;)Ljava/lang/Object;
    1379: invokestatic  #11                 // Method printSEx:(Ljava/lang/Object;)Ljava/lang/String;
    1382: invokevirtual #64                 // Method java/lang/StringBuilder.append:(Ljava/lang/String;)Ljava/lang/StringBuilder;
    1385: aload_1
    1386: invokestatic  #82                 // Method errorExp:(Ljava/lang/Object;)Ljava/lang/String;
    1389: invokevirtual #64                 // Method java/lang/StringBuilder.append:(Ljava/lang/String;)Ljava/lang/StringBuilder;
    1392: invokevirtual #67                 // Method java/lang/StringBuilder.toString:()Ljava/lang/String;
    1395: invokespecial #55                 // Method com/robertmayer/lambdaj/LambdaJ$LambdaJError."<init>":(Ljava/lang/String;)V
    1398: athrow
    1399: new           #53                 // class com/robertmayer/lambdaj/LambdaJ$LambdaJError
    1402: dup
    1403: new           #61                 // class java/lang/StringBuilder
    1406: dup
    1407: invokespecial #62                 // Method java/lang/StringBuilder."<init>":()V
    1410: ldc           #93                 // String cannot eval expression '
    1412: invokevirtual #64                 // Method java/lang/StringBuilder.append:(Ljava/lang/String;)Ljava/lang/StringBuilder;
    1415: aload_1
    1416: invokestatic  #11                 // Method printSEx:(Ljava/lang/Object;)Ljava/lang/String;
    1419: invokevirtual #64                 // Method java/lang/StringBuilder.append:(Ljava/lang/String;)Ljava/lang/StringBuilder;
    1422: bipush        39
    1424: invokevirtual #94                 // Method java/lang/StringBuilder.append:(C)Ljava/lang/StringBuilder;
    1427: invokevirtual #67                 // Method java/lang/StringBuilder.toString:()Ljava/lang/String;
    1430: invokespecial #55                 // Method com/robertmayer/lambdaj/LambdaJ$LambdaJError."<init>":(Ljava/lang/String;)V
    1433: athrow
    1434: astore        6
    1436: aload         6
    1438: athrow
    1439: astore        11
    1441: aload_0
    1442: iload         5
    1444: ifeq          1452
    1447: ldc           #56                 // String eval TC
    1449: goto          1454
    1452: ldc           #57                 // String eval
    1454: aload_1
    1455: iload_3
    1456: iload         4
    1458: invokespecial #59                 // Method dbgEvalDone:(Ljava/lang/String;Ljava/lang/Object;II)V
    1461: aload         11
    1463: athrow
    Exception table:
       from    to  target type
           3    44  1434   Class java/lang/Exception
          67    89  1434   Class java/lang/Exception
         112   154  1434   Class java/lang/Exception
         177   228  1434   Class java/lang/Exception
         251   361  1434   Class java/lang/Exception
         384   414  1434   Class java/lang/Exception
         437   513  1434   Class java/lang/Exception
         536   630  1434   Class java/lang/Exception
         653   826  1434   Class java/lang/Exception
         849   986  1434   Class java/lang/Exception
        1009  1434  1434   Class java/lang/Exception
           3    44  1439   any
          67    89  1439   any
         112   154  1439   any
         177   228  1439   any
         251   361  1439   any
         384   414  1439   any
         437   513  1439   any
         536   630  1439   any
         653   826  1439   any
         849   986  1439   any
        1009  1441  1439   any

  private com.robertmayer.lambdaj.LambdaJ$ConsCell evlis(com.robertmayer.lambdaj.LambdaJ$ConsCell, com.robertmayer.lambdaj.LambdaJ$ConsCell, int, int);
    Code:
       0: aload_0
       1: ldc           #96                 // String evlis
       3: aload_1
       4: aload_2
       5: iload_3
       6: iload         4
       8: invokespecial #58                 // Method dbgEvalStart:(Ljava/lang/String;Ljava/lang/Object;Lcom/robertmayer/lambdaj/LambdaJ$ConsCell;II)V
      11: aconst_null
      12: astore        5
      14: aconst_null
      15: astore        6
      17: aload_1
      18: astore        7
      20: aload         7
      22: ifnull        94
      25: aload_1
      26: aload         7
      28: invokestatic  #5                  // Method cdr:(Ljava/lang/Object;)Ljava/lang/Object;
      31: if_acmpeq     94
      34: aload_0
      35: aload         7
      37: invokestatic  #4                  // Method car:(Ljava/lang/Object;)Ljava/lang/Object;
      40: aload_2
      41: iload_3
      42: iconst_1
      43: iadd
      44: iload         4
      46: iconst_1
      47: iadd
      48: invokespecial #73                 // Method eval:(Ljava/lang/Object;Lcom/robertmayer/lambdaj/LambdaJ$ConsCell;II)Ljava/lang/Object;
      51: aconst_null
      52: invokestatic  #3                  // Method cons:(Ljava/lang/Object;Ljava/lang/Object;)Lcom/robertmayer/lambdaj/LambdaJ$ConsCell;
      55: astore        8
      57: aload         5
      59: ifnonnull     73
      62: aload         8
      64: astore        5
      66: aload         5
      68: astore        6
      70: goto          84
      73: aload         6
      75: aload         8
      77: putfield      #97                 // Field com/robertmayer/lambdaj/LambdaJ$ConsCell.cdr:Ljava/lang/Object;
      80: aload         8
      82: astore        6
      84: aload         7
      86: invokestatic  #5                  // Method cdr:(Ljava/lang/Object;)Ljava/lang/Object;
      89: astore        7
      91: goto          20
      94: aload_0
      95: ldc           #96                 // String evlis
      97: aload_1
      98: iload_3
      99: iload         4
     101: invokespecial #59                 // Method dbgEvalDone:(Ljava/lang/String;Ljava/lang/Object;II)V
     104: aload         5
     106: areturn

  private java.lang.Object evlabels(com.robertmayer.lambdaj.LambdaJ$ConsCell, com.robertmayer.lambdaj.LambdaJ$ConsCell, com.robertmayer.lambdaj.LambdaJ$ConsCell, int, int);
    Code:
       0: aload_0
       1: ldc           #98                 // String evlabels 1
       3: aload_1
       4: aload_3
       5: iload         4
       7: iload         5
       9: invokespecial #58                 // Method dbgEvalStart:(Ljava/lang/String;Ljava/lang/Object;Lcom/robertmayer/lambdaj/LambdaJ$ConsCell;II)V
      12: aload_3
      13: astore        6
      15: aload_1
      16: astore        7
      18: aload_2
      19: astore        8
      21: aload         7
      23: ifnull        109
      26: aload         7
      28: invokestatic  #4                  // Method car:(Ljava/lang/Object;)Ljava/lang/Object;
      31: checkcast     #77                 // class com/robertmayer/lambdaj/LambdaJ$ConsCell
      34: astore        9
      36: aload         9
      38: invokestatic  #4                  // Method car:(Ljava/lang/Object;)Ljava/lang/Object;
      41: checkcast     #99                 // class java/lang/String
      44: astore        10
      46: aload         9
      48: invokestatic  #5                  // Method cdr:(Ljava/lang/Object;)Ljava/lang/Object;
      51: checkcast     #77                 // class com/robertmayer/lambdaj/LambdaJ$ConsCell
      54: astore        11
      56: aload_0
      57: getfield      #45                 // Field sLambda:Ljava/util/function/Supplier;
      60: invokeinterface #69,  1           // InterfaceMethod java/util/function/Supplier.get:()Ljava/lang/Object;
      65: aload         11
      67: invokestatic  #3                  // Method cons:(Ljava/lang/Object;Ljava/lang/Object;)Lcom/robertmayer/lambdaj/LambdaJ$ConsCell;
      70: aconst_null
      71: invokestatic  #3                  // Method cons:(Ljava/lang/Object;Ljava/lang/Object;)Lcom/robertmayer/lambdaj/LambdaJ$ConsCell;
      74: astore        12
      76: aload_0
      77: getfield      #35                 // Field symtab:Lcom/robertmayer/lambdaj/LambdaJ$SymbolTable;
      80: aload         10
      82: invokeinterface #51,  2           // InterfaceMethod com/robertmayer/lambdaj/LambdaJ$SymbolTable.intern:(Ljava/lang/String;)Ljava/lang/Object;
      87: aload         12
      89: invokestatic  #3                  // Method cons:(Ljava/lang/Object;Ljava/lang/Object;)Lcom/robertmayer/lambdaj/LambdaJ$ConsCell;
      92: aload         6
      94: invokestatic  #3                  // Method cons:(Ljava/lang/Object;Ljava/lang/Object;)Lcom/robertmayer/lambdaj/LambdaJ$ConsCell;
      97: astore        6
      99: aload         7
     101: invokestatic  #5                  // Method cdr:(Ljava/lang/Object;)Ljava/lang/Object;
     104: astore        7
     106: goto          21
     109: aload_0
     110: ldc           #98                 // String evlabels 1
     112: aload_1
     113: iload         4
     115: iload         5
     117: invokespecial #59                 // Method dbgEvalDone:(Ljava/lang/String;Ljava/lang/Object;II)V
     120: aload_0
     121: ldc           #100                // String evlabels 2
     123: aload_2
     124: aload         6
     126: iload         4
     128: iload         5
     130: invokespecial #58                 // Method dbgEvalStart:(Ljava/lang/String;Ljava/lang/Object;Lcom/robertmayer/lambdaj/LambdaJ$ConsCell;II)V
     133: aconst_null
     134: astore        9
     136: aload         8
     138: ifnull        172
     141: aload_0
     142: aload         8
     144: invokestatic  #4                  // Method car:(Ljava/lang/Object;)Ljava/lang/Object;
     147: aload         6
     149: iload         4
     151: iconst_1
     152: iadd
     153: iload         5
     155: iconst_1
     156: iadd
     157: invokespecial #73                 // Method eval:(Ljava/lang/Object;Lcom/robertmayer/lambdaj/LambdaJ$ConsCell;II)Ljava/lang/Object;
     160: astore        9
     162: aload         8
     164: invokestatic  #5                  // Method cdr:(Ljava/lang/Object;)Ljava/lang/Object;
     167: astore        8
     169: goto          136
     172: aload_0
     173: ldc           #100                // String evlabels 2
     175: aload_2
     176: iload         4
     178: iload         5
     180: invokespecial #59                 // Method dbgEvalDone:(Ljava/lang/String;Ljava/lang/Object;II)V
     183: aload         9
     185: areturn

  private void dbgEvalStart(java.lang.String, java.lang.Object, com.robertmayer.lambdaj.LambdaJ$ConsCell, int, int);
    Code:
       0: aload_0
       1: getfield      #15                 // Field trace:I
       4: iconst_1
       5: if_icmplt     243
       8: aload_1
       9: invokestatic  #101                // Method fmtEvFunc:(Ljava/lang/String;)Ljava/lang/String;
      12: astore_1
      13: aload_0
      14: getfield      #102                // Field maxEvalStack:I
      17: iload         4
      19: if_icmpge     28
      22: aload_0
      23: iload         4
      25: putfield      #102                // Field maxEvalStack:I
      28: aload_0
      29: getfield      #103                // Field maxEvalLevel:I
      32: iload         5
      34: if_icmpge     43
      37: aload_0
      38: iload         5
      40: putfield      #103                // Field maxEvalLevel:I
      43: iload         4
      45: iconst_2
      46: imul
      47: newarray       char
      49: astore        6
      51: aload         6
      53: bipush        32
      55: invokestatic  #104                // Method java/util/Arrays.fill:([CC)V
      58: new           #99                 // class java/lang/String
      61: dup
      62: aload         6
      64: invokespecial #105                // Method java/lang/String."<init>":([C)V
      67: astore        7
      69: iconst_3
      70: iload         5
      72: iload         4
      74: isub
      75: iconst_2
      76: imul
      77: iadd
      78: newarray       char
      80: astore        8
      82: aload         8
      84: bipush        42
      86: invokestatic  #104                // Method java/util/Arrays.fill:([CC)V
      89: new           #99                 // class java/lang/String
      92: dup
      93: aload         8
      95: invokespecial #105                // Method java/lang/String."<init>":([C)V
      98: astore        9
     100: aload_0
     101: getfield      #6                  // Field tracer:Lcom/robertmayer/lambdaj/LambdaJ$Tracer;
     104: new           #61                 // class java/lang/StringBuilder
     107: dup
     108: invokespecial #62                 // Method java/lang/StringBuilder."<init>":()V
     111: aload         7
     113: invokevirtual #64                 // Method java/lang/StringBuilder.append:(Ljava/lang/String;)Ljava/lang/StringBuilder;
     116: ldc           #106                // String ***
     118: invokevirtual #64                 // Method java/lang/StringBuilder.append:(Ljava/lang/String;)Ljava/lang/StringBuilder;
     121: aload_1
     122: invokevirtual #64                 // Method java/lang/StringBuilder.append:(Ljava/lang/String;)Ljava/lang/StringBuilder;
     125: ldc           #107                // String  (
     127: invokevirtual #64                 // Method java/lang/StringBuilder.append:(Ljava/lang/String;)Ljava/lang/StringBuilder;
     130: iload         4
     132: invokevirtual #108                // Method java/lang/StringBuilder.append:(I)Ljava/lang/StringBuilder;
     135: bipush        47
     137: invokevirtual #94                 // Method java/lang/StringBuilder.append:(C)Ljava/lang/StringBuilder;
     140: iload         5
     142: invokevirtual #108                // Method java/lang/StringBuilder.append:(I)Ljava/lang/StringBuilder;
     145: ldc           #109                // String )
     147: invokevirtual #64                 // Method java/lang/StringBuilder.append:(Ljava/lang/String;)Ljava/lang/StringBuilder;
     150: aload         9
     152: invokevirtual #64                 // Method java/lang/StringBuilder.append:(Ljava/lang/String;)Ljava/lang/StringBuilder;
     155: invokevirtual #67                 // Method java/lang/StringBuilder.toString:()Ljava/lang/String;
     158: invokeinterface #110,  2          // InterfaceMethod com/robertmayer/lambdaj/LambdaJ$Tracer.println:(Ljava/lang/String;)V
     163: aload_0
     164: getfield      #15                 // Field trace:I
     167: iconst_2
     168: if_icmplt     207
     171: aload_0
     172: getfield      #6                  // Field tracer:Lcom/robertmayer/lambdaj/LambdaJ$Tracer;
     175: new           #61                 // class java/lang/StringBuilder
     178: dup
     179: invokespecial #62                 // Method java/lang/StringBuilder."<init>":()V
     182: aload         7
     184: invokevirtual #64                 // Method java/lang/StringBuilder.append:(Ljava/lang/String;)Ljava/lang/StringBuilder;
     187: ldc           #111                // String *** -> env:
     189: invokevirtual #64                 // Method java/lang/StringBuilder.append:(Ljava/lang/String;)Ljava/lang/StringBuilder;
     192: aload_3
     193: invokestatic  #11                 // Method printSEx:(Ljava/lang/Object;)Ljava/lang/String;
     196: invokevirtual #64                 // Method java/lang/StringBuilder.append:(Ljava/lang/String;)Ljava/lang/StringBuilder;
     199: invokevirtual #67                 // Method java/lang/StringBuilder.toString:()Ljava/lang/String;
     202: invokeinterface #110,  2          // InterfaceMethod com/robertmayer/lambdaj/LambdaJ$Tracer.println:(Ljava/lang/String;)V
     207: aload_0
     208: getfield      #6                  // Field tracer:Lcom/robertmayer/lambdaj/LambdaJ$Tracer;
     211: new           #61                 // class java/lang/StringBuilder
     214: dup
     215: invokespecial #62                 // Method java/lang/StringBuilder."<init>":()V
     218: aload         7
     220: invokevirtual #64                 // Method java/lang/StringBuilder.append:(Ljava/lang/String;)Ljava/lang/StringBuilder;
     223: ldc           #112                // String *** -> exp:
     225: invokevirtual #64                 // Method java/lang/StringBuilder.append:(Ljava/lang/String;)Ljava/lang/StringBuilder;
     228: aload_2
     229: invokestatic  #11                 // Method printSEx:(Ljava/lang/Object;)Ljava/lang/String;
     232: invokevirtual #64                 // Method java/lang/StringBuilder.append:(Ljava/lang/String;)Ljava/lang/StringBuilder;
     235: invokevirtual #67                 // Method java/lang/StringBuilder.toString:()Ljava/lang/String;
     238: invokeinterface #110,  2          // InterfaceMethod com/robertmayer/lambdaj/LambdaJ$Tracer.println:(Ljava/lang/String;)V
     243: return

  private void dbgEvalDone(java.lang.String, java.lang.Object, int, int);
    Code:
       0: aload_0
       1: getfield      #15                 // Field trace:I
       4: iconst_1
       5: if_icmplt     166
       8: aload_1
       9: invokestatic  #101                // Method fmtEvFunc:(Ljava/lang/String;)Ljava/lang/String;
      12: astore_1
      13: iload_3
      14: iconst_2
      15: imul
      16: newarray       char
      18: astore        5
      20: aload         5
      22: bipush        32
      24: invokestatic  #104                // Method java/util/Arrays.fill:([CC)V
      27: new           #99                 // class java/lang/String
      30: dup
      31: aload         5
      33: invokespecial #105                // Method java/lang/String."<init>":([C)V
      36: astore        6
      38: iconst_3
      39: iload         4
      41: iload_3
      42: isub
      43: iconst_2
      44: imul
      45: iadd
      46: newarray       char
      48: astore        7
      50: aload         7
      52: bipush        42
      54: invokestatic  #104                // Method java/util/Arrays.fill:([CC)V
      57: new           #99                 // class java/lang/String
      60: dup
      61: aload         7
      63: invokespecial #105                // Method java/lang/String."<init>":([C)V
      66: astore        8
      68: aload_0
      69: getfield      #6                  // Field tracer:Lcom/robertmayer/lambdaj/LambdaJ$Tracer;
      72: new           #61                 // class java/lang/StringBuilder
      75: dup
      76: invokespecial #62                 // Method java/lang/StringBuilder."<init>":()V
      79: aload         6
      81: invokevirtual #64                 // Method java/lang/StringBuilder.append:(Ljava/lang/String;)Ljava/lang/StringBuilder;
      84: ldc           #106                // String ***
      86: invokevirtual #64                 // Method java/lang/StringBuilder.append:(Ljava/lang/String;)Ljava/lang/StringBuilder;
      89: aload_1
      90: invokevirtual #64                 // Method java/lang/StringBuilder.append:(Ljava/lang/String;)Ljava/lang/StringBuilder;
      93: ldc           #107                // String  (
      95: invokevirtual #64                 // Method java/lang/StringBuilder.append:(Ljava/lang/String;)Ljava/lang/StringBuilder;
      98: iload_3
      99: invokevirtual #108                // Method java/lang/StringBuilder.append:(I)Ljava/lang/StringBuilder;
     102: bipush        47
     104: invokevirtual #94                 // Method java/lang/StringBuilder.append:(C)Ljava/lang/StringBuilder;
     107: iload         4
     109: invokevirtual #108                // Method java/lang/StringBuilder.append:(I)Ljava/lang/StringBuilder;
     112: ldc           #113                // String ) done
     114: invokevirtual #64                 // Method java/lang/StringBuilder.append:(Ljava/lang/String;)Ljava/lang/StringBuilder;
     117: aload         8
     119: invokevirtual #64                 // Method java/lang/StringBuilder.append:(Ljava/lang/String;)Ljava/lang/StringBuilder;
     122: invokevirtual #67                 // Method java/lang/StringBuilder.toString:()Ljava/lang/String;
     125: invokeinterface #110,  2          // InterfaceMethod com/robertmayer/lambdaj/LambdaJ$Tracer.println:(Ljava/lang/String;)V
     130: aload_0
     131: getfield      #6                  // Field tracer:Lcom/robertmayer/lambdaj/LambdaJ$Tracer;
     134: new           #61                 // class java/lang/StringBuilder
     137: dup
     138: invokespecial #62                 // Method java/lang/StringBuilder."<init>":()V
     141: aload         6
     143: invokevirtual #64                 // Method java/lang/StringBuilder.append:(Ljava/lang/String;)Ljava/lang/StringBuilder;
     146: ldc           #114                // String *** -> exp was:
     148: invokevirtual #64                 // Method java/lang/StringBuilder.append:(Ljava/lang/String;)Ljava/lang/StringBuilder;
     151: aload_2
     152: invokestatic  #11                 // Method printSEx:(Ljava/lang/Object;)Ljava/lang/String;
     155: invokevirtual #64                 // Method java/lang/StringBuilder.append:(Ljava/lang/String;)Ljava/lang/StringBuilder;
     158: invokevirtual #67                 // Method java/lang/StringBuilder.toString:()Ljava/lang/String;
     161: invokeinterface #110,  2          // InterfaceMethod com/robertmayer/lambdaj/LambdaJ$Tracer.println:(Ljava/lang/String;)V
     166: return

  private static java.lang.String fmtEvFunc(java.lang.String);
    Code:
       0: new           #61                 // class java/lang/StringBuilder
       3: dup
       4: invokespecial #62                 // Method java/lang/StringBuilder."<init>":()V
       7: aload_0
       8: invokevirtual #64                 // Method java/lang/StringBuilder.append:(Ljava/lang/String;)Ljava/lang/StringBuilder;
      11: ldc           #115                // String
      13: invokevirtual #64                 // Method java/lang/StringBuilder.append:(Ljava/lang/String;)Ljava/lang/StringBuilder;
      16: invokevirtual #67                 // Method java/lang/StringBuilder.toString:()Ljava/lang/String;
      19: iconst_0
      20: bipush        10
      22: invokevirtual #116                // Method java/lang/String.substring:(II)Ljava/lang/String;
      25: areturn

  private static com.robertmayer.lambdaj.LambdaJ$ConsCell cons(java.lang.Object, java.lang.Object);
    Code:
       0: new           #77                 // class com/robertmayer/lambdaj/LambdaJ$ConsCell
       3: dup
       4: aload_0
       5: aload_1
       6: invokespecial #117                // Method com/robertmayer/lambdaj/LambdaJ$ConsCell."<init>":(Ljava/lang/Object;Ljava/lang/Object;)V
       9: areturn

  private static java.lang.Object car(java.lang.Object);
    Code:
       0: aload_0
       1: checkcast     #77                 // class com/robertmayer/lambdaj/LambdaJ$ConsCell
       4: getfield      #118                // Field com/robertmayer/lambdaj/LambdaJ$ConsCell.car:Ljava/lang/Object;
       7: areturn

  private static java.lang.Object cdr(java.lang.Object);
    Code:
       0: aload_0
       1: checkcast     #77                 // class com/robertmayer/lambdaj/LambdaJ$ConsCell
       4: getfield      #97                 // Field com/robertmayer/lambdaj/LambdaJ$ConsCell.cdr:Ljava/lang/Object;
       7: areturn

  private static boolean consp(java.lang.Object);
    Code:
       0: aload_0
       1: instanceof    #77                 // class com/robertmayer/lambdaj/LambdaJ$ConsCell
       4: ireturn

  private static boolean atom(java.lang.Object);
    Code:
       0: aload_0
       1: ifnull        11
       4: aload_0
       5: instanceof    #77                 // class com/robertmayer/lambdaj/LambdaJ$ConsCell
       8: ifne          15
      11: iconst_1
      12: goto          16
      15: iconst_0
      16: ireturn

  private static boolean symbolp(java.lang.Object);
    Code:
       0: aload_0
       1: ifnull        11
       4: aload_0
       5: instanceof    #99                 // class java/lang/String
       8: ifeq          15
      11: iconst_1
      12: goto          16
      15: iconst_0
      16: ireturn

  private static boolean listp(java.lang.Object);
    Code:
       0: aload_0
       1: ifnull        11
       4: aload_0
       5: instanceof    #77                 // class com/robertmayer/lambdaj/LambdaJ$ConsCell
       8: ifeq          15
      11: iconst_1
      12: goto          16
      15: iconst_0
      16: ireturn

  private static boolean isPrim(java.lang.Object);
    Code:
       0: aload_0
       1: instanceof    #85                 // class com/robertmayer/lambdaj/LambdaJ$Primitive
       4: ireturn

  private static boolean numberp(java.lang.Object);
    Code:
       0: aload_0
       1: instanceof    #119                // class java/lang/Number
       4: ireturn

  private static boolean stringp(java.lang.Object);
    Code:
       0: aload_0
       1: instanceof    #120                // class com/robertmayer/lambdaj/LambdaJ$LambdaJString
       4: ireturn

  private static int length(java.lang.Object);
    Code:
       0: aload_0
       1: ifnonnull     6
       4: iconst_0
       5: ireturn
       6: iconst_0
       7: istore_1
       8: aload_0
       9: astore_2
      10: aload_2
      11: ifnull        25
      14: iinc          1, 1
      17: aload_2
      18: invokestatic  #5                  // Method cdr:(Ljava/lang/Object;)Ljava/lang/Object;
      21: astore_2
      22: goto          10
      25: iload_1
      26: ireturn

  private static java.lang.Object nthcdr(int, java.lang.Object);
    Code:
       0: aload_1
       1: ifnonnull     6
       4: aconst_null
       5: areturn
       6: aload_1
       7: ifnull        25
      10: iload_0
      11: iinc          0, -1
      14: ifle          25
      17: aload_1
      18: invokestatic  #5                  // Method cdr:(Ljava/lang/Object;)Ljava/lang/Object;
      21: astore_1
      22: goto          6
      25: aload_1
      26: areturn

  private static java.lang.Object assoc(java.lang.Object, java.lang.Object);
    Code:
       0: aload_0
       1: ifnonnull     6
       4: aconst_null
       5: areturn
       6: aload_1
       7: ifnonnull     12
      10: aconst_null
      11: areturn
      12: aload_1
      13: invokestatic  #121                // Method listp:(Ljava/lang/Object;)Z
      16: ifne          49
      19: new           #53                 // class com/robertmayer/lambdaj/LambdaJ$LambdaJError
      22: dup
      23: new           #61                 // class java/lang/StringBuilder
      26: dup
      27: invokespecial #62                 // Method java/lang/StringBuilder."<init>":()V
      30: ldc           #122                // String assoc: expected second argument to be a List but got
      32: invokevirtual #64                 // Method java/lang/StringBuilder.append:(Ljava/lang/String;)Ljava/lang/StringBuilder;
      35: aload_1
      36: invokestatic  #11                 // Method printSEx:(Ljava/lang/Object;)Ljava/lang/String;
      39: invokevirtual #64                 // Method java/lang/StringBuilder.append:(Ljava/lang/String;)Ljava/lang/StringBuilder;
      42: invokevirtual #67                 // Method java/lang/StringBuilder.toString:()Ljava/lang/String;
      45: invokespecial #55                 // Method com/robertmayer/lambdaj/LambdaJ$LambdaJError."<init>":(Ljava/lang/String;)V
      48: athrow
      49: aload_1
      50: checkcast     #77                 // class com/robertmayer/lambdaj/LambdaJ$ConsCell
      53: astore_2
      54: aload_2
      55: ifnull        93
      58: aload_1
      59: aload_2
      60: invokestatic  #5                  // Method cdr:(Ljava/lang/Object;)Ljava/lang/Object;
      63: if_acmpeq     93
      66: aload_0
      67: aload_2
      68: invokestatic  #4                  // Method car:(Ljava/lang/Object;)Ljava/lang/Object;
      71: invokestatic  #4                  // Method car:(Ljava/lang/Object;)Ljava/lang/Object;
      74: if_acmpne     82
      77: aload_2
      78: invokestatic  #4                  // Method car:(Ljava/lang/Object;)Ljava/lang/Object;
      81: areturn
      82: aload_2
      83: invokestatic  #5                  // Method cdr:(Ljava/lang/Object;)Ljava/lang/Object;
      86: checkcast     #77                 // class com/robertmayer/lambdaj/LambdaJ$ConsCell
      89: astore_2
      90: goto          54
      93: aconst_null
      94: areturn

  private static java.lang.Object[] listToArray(java.lang.Object);
    Code:
       0: aload_0
       1: ifnonnull     6
       4: aconst_null
       5: areturn
       6: aload_0
       7: invokestatic  #121                // Method listp:(Ljava/lang/Object;)Z
      10: ifne          43
      13: new           #53                 // class com/robertmayer/lambdaj/LambdaJ$LambdaJError
      16: dup
      17: new           #61                 // class java/lang/StringBuilder
      20: dup
      21: invokespecial #62                 // Method java/lang/StringBuilder."<init>":()V
      24: ldc           #123                // String listToArray: expected second argument to be a List but got
      26: invokevirtual #64                 // Method java/lang/StringBuilder.append:(Ljava/lang/String;)Ljava/lang/StringBuilder;
      29: aload_0
      30: invokestatic  #11                 // Method printSEx:(Ljava/lang/Object;)Ljava/lang/String;
      33: invokevirtual #64                 // Method java/lang/StringBuilder.append:(Ljava/lang/String;)Ljava/lang/StringBuilder;
      36: invokevirtual #67                 // Method java/lang/StringBuilder.toString:()Ljava/lang/String;
      39: invokespecial #55                 // Method com/robertmayer/lambdaj/LambdaJ$LambdaJError."<init>":(Ljava/lang/String;)V
      42: athrow
      43: new           #124                // class java/util/ArrayList
      46: dup
      47: invokespecial #125                // Method java/util/ArrayList."<init>":()V
      50: astore_1
      51: aload_0
      52: checkcast     #77                 // class com/robertmayer/lambdaj/LambdaJ$ConsCell
      55: astore_2
      56: aload_2
      57: ifnull        90
      60: aload_0
      61: aload_2
      62: invokestatic  #5                  // Method cdr:(Ljava/lang/Object;)Ljava/lang/Object;
      65: if_acmpeq     90
      68: aload_1
      69: aload_2
      70: invokestatic  #4                  // Method car:(Ljava/lang/Object;)Ljava/lang/Object;
      73: invokeinterface #126,  2          // InterfaceMethod java/util/List.add:(Ljava/lang/Object;)Z
      78: pop
      79: aload_2
      80: invokestatic  #5                  // Method cdr:(Ljava/lang/Object;)Ljava/lang/Object;
      83: checkcast     #77                 // class com/robertmayer/lambdaj/LambdaJ$ConsCell
      86: astore_2
      87: goto          56
      90: aload_1
      91: invokeinterface #127,  1          // InterfaceMethod java/util/List.toArray:()[Ljava/lang/Object;
      96: areturn

  private java.lang.Object applyPrimitive(com.robertmayer.lambdaj.LambdaJ$Primitive, com.robertmayer.lambdaj.LambdaJ$ConsCell, int);
    Code:
       0: aload_0
       1: getfield      #15                 // Field trace:I
       4: iconst_3
       5: if_icmplt     74
       8: iload_3
       9: iconst_2
      10: imul
      11: newarray       char
      13: astore        4
      15: aload         4
      17: bipush        32
      19: invokestatic  #104                // Method java/util/Arrays.fill:([CC)V
      22: new           #99                 // class java/lang/String
      25: dup
      26: aload         4
      28: invokespecial #105                // Method java/lang/String."<init>":([C)V
      31: astore        5
      33: aload_0
      34: getfield      #6                  // Field tracer:Lcom/robertmayer/lambdaj/LambdaJ$Tracer;
      37: new           #61                 // class java/lang/StringBuilder
      40: dup
      41: invokespecial #62                 // Method java/lang/StringBuilder."<init>":()V
      44: aload         5
      46: invokevirtual #64                 // Method java/lang/StringBuilder.append:(Ljava/lang/String;)Ljava/lang/StringBuilder;
      49: ldc           #128                // String (<primitive>
      51: invokevirtual #64                 // Method java/lang/StringBuilder.append:(Ljava/lang/String;)Ljava/lang/StringBuilder;
      54: aload_2
      55: invokestatic  #11                 // Method printSEx:(Ljava/lang/Object;)Ljava/lang/String;
      58: invokevirtual #64                 // Method java/lang/StringBuilder.append:(Ljava/lang/String;)Ljava/lang/StringBuilder;
      61: bipush        41
      63: invokevirtual #94                 // Method java/lang/StringBuilder.append:(C)Ljava/lang/StringBuilder;
      66: invokevirtual #67                 // Method java/lang/StringBuilder.toString:()Ljava/lang/String;
      69: invokeinterface #110,  2          // InterfaceMethod com/robertmayer/lambdaj/LambdaJ$Tracer.println:(Ljava/lang/String;)V
      74: aload_1
      75: aload_2
      76: invokeinterface #129,  2          // InterfaceMethod com/robertmayer/lambdaj/LambdaJ$Primitive.apply:(Lcom/robertmayer/lambdaj/LambdaJ$ConsCell;)Ljava/lang/Object;
      81: areturn

  private static java.lang.String printSEx(java.lang.Object);
    Code:
       0: aload_0
       1: ifnonnull     7
       4: ldc           #130                // String nil
       6: areturn
       7: new           #131                // class java/lang/StringBuffer
      10: dup
      11: sipush        200
      14: invokespecial #132                // Method java/lang/StringBuffer."<init>":(I)V
      17: astore_1
      18: aload_1
      19: aload_0
      20: aload_0
      21: iconst_1
      22: iconst_1
      23: invokestatic  #133                // Method _printSEx:(Ljava/lang/StringBuffer;Ljava/lang/Object;Ljava/lang/Object;ZZ)V
      26: aload_1
      27: invokevirtual #134                // Method java/lang/StringBuffer.toString:()Ljava/lang/String;
      30: areturn

  private static java.lang.String printObj(java.lang.Object);
    Code:
       0: aload_0
       1: ifnonnull     7
       4: ldc           #130                // String nil
       6: areturn
       7: new           #131                // class java/lang/StringBuffer
      10: dup
      11: sipush        200
      14: invokespecial #132                // Method java/lang/StringBuffer."<init>":(I)V
      17: astore_1
      18: aload_1
      19: aload_0
      20: aload_0
      21: iconst_1
      22: iconst_0
      23: invokestatic  #133                // Method _printSEx:(Ljava/lang/StringBuffer;Ljava/lang/Object;Ljava/lang/Object;ZZ)V
      26: aload_1
      27: invokevirtual #134                // Method java/lang/StringBuffer.toString:()Ljava/lang/String;
      30: areturn

  private static void _printSEx(java.lang.StringBuffer, java.lang.Object, java.lang.Object, boolean, boolean);
    Code:
       0: aload_2
       1: ifnonnull     12
       4: aload_0
       5: ldc           #130                // String nil
       7: invokevirtual #135                // Method java/lang/StringBuffer.append:(Ljava/lang/String;)Ljava/lang/StringBuffer;
      10: pop
      11: return
      12: aload_2
      13: invokestatic  #121                // Method listp:(Ljava/lang/Object;)Z
      16: ifeq          188
      19: iload_3
      20: ifeq          30
      23: aload_0
      24: bipush        40
      26: invokevirtual #136                // Method java/lang/StringBuffer.append:(C)Ljava/lang/StringBuffer;
      29: pop
      30: aload_2
      31: invokestatic  #4                  // Method car:(Ljava/lang/Object;)Ljava/lang/Object;
      34: aload_1
      35: if_acmpne     57
      38: aload_0
      39: iload_3
      40: ifeq          48
      43: ldc           #137                // String #<this cons>
      45: goto          50
      48: ldc           #138                // String #<this list>
      50: invokevirtual #135                // Method java/lang/StringBuffer.append:(Ljava/lang/String;)Ljava/lang/StringBuffer;
      53: pop
      54: goto          72
      57: aload_0
      58: aload_2
      59: invokestatic  #4                  // Method car:(Ljava/lang/Object;)Ljava/lang/Object;
      62: aload_2
      63: invokestatic  #4                  // Method car:(Ljava/lang/Object;)Ljava/lang/Object;
      66: iconst_1
      67: iload         4
      69: invokestatic  #133                // Method _printSEx:(Ljava/lang/StringBuffer;Ljava/lang/Object;Ljava/lang/Object;ZZ)V
      72: aload_2
      73: invokestatic  #5                  // Method cdr:(Ljava/lang/Object;)Ljava/lang/Object;
      76: ifnull        180
      79: aload_2
      80: invokestatic  #5                  // Method cdr:(Ljava/lang/Object;)Ljava/lang/Object;
      83: invokestatic  #121                // Method listp:(Ljava/lang/Object;)Z
      86: ifeq          122
      89: aload_0
      90: bipush        32
      92: invokevirtual #136                // Method java/lang/StringBuffer.append:(C)Ljava/lang/StringBuffer;
      95: pop
      96: aload_1
      97: aload_2
      98: invokestatic  #5                  // Method cdr:(Ljava/lang/Object;)Ljava/lang/Object;
     101: if_acmpne     112
     104: aload_0
     105: ldc           #139                // String #<circular list>)
     107: invokevirtual #135                // Method java/lang/StringBuffer.append:(Ljava/lang/String;)Ljava/lang/StringBuffer;
     110: pop
     111: return
     112: aload_2
     113: invokestatic  #5                  // Method cdr:(Ljava/lang/Object;)Ljava/lang/Object;
     116: astore_2
     117: iconst_0
     118: istore_3
     119: goto          0
     122: iload_3
     123: ifeq          153
     126: aload_0
     127: ldc           #140                // String  .
     129: invokevirtual #135                // Method java/lang/StringBuffer.append:(Ljava/lang/String;)Ljava/lang/StringBuffer;
     132: pop
     133: aload_0
     134: aload_1
     135: aload_2
     136: invokestatic  #5                  // Method cdr:(Ljava/lang/Object;)Ljava/lang/Object;
     139: iconst_0
     140: iload         4
     142: invokestatic  #133                // Method _printSEx:(Ljava/lang/StringBuffer;Ljava/lang/Object;Ljava/lang/Object;ZZ)V
     145: aload_0
     146: bipush        41
     148: invokevirtual #136                // Method java/lang/StringBuffer.append:(C)Ljava/lang/StringBuffer;
     151: pop
     152: return
     153: aload_0
     154: bipush        32
     156: invokevirtual #136                // Method java/lang/StringBuffer.append:(C)Ljava/lang/StringBuffer;
     159: pop
     160: aload_0
     161: aload_1
     162: aload_2
     163: invokestatic  #5                  // Method cdr:(Ljava/lang/Object;)Ljava/lang/Object;
     166: iconst_0
     167: iload         4
     169: invokestatic  #133                // Method _printSEx:(Ljava/lang/StringBuffer;Ljava/lang/Object;Ljava/lang/Object;ZZ)V
     172: aload_0
     173: bipush        41
     175: invokevirtual #136                // Method java/lang/StringBuffer.append:(C)Ljava/lang/StringBuffer;
     178: pop
     179: return
     180: aload_0
     181: bipush        41
     183: invokevirtual #136                // Method java/lang/StringBuffer.append:(C)Ljava/lang/StringBuffer;
     186: pop
     187: return
     188: iload         4
     190: ifeq          240
     193: aload_2
     194: invokestatic  #1                  // Method symbolp:(Ljava/lang/Object;)Z
     197: ifeq          240
     200: aload_2
     201: invokevirtual #141                // Method java/lang/Object.toString:()Ljava/lang/String;
     204: invokestatic  #142                // Method containsSExSyntaxOrBlank:(Ljava/lang/String;)Z
     207: ifeq          230
     210: aload_0
     211: bipush        124
     213: invokevirtual #136                // Method java/lang/StringBuffer.append:(C)Ljava/lang/StringBuffer;
     216: aload_2
     217: invokevirtual #141                // Method java/lang/Object.toString:()Ljava/lang/String;
     220: invokevirtual #135                // Method java/lang/StringBuffer.append:(Ljava/lang/String;)Ljava/lang/StringBuffer;
     223: bipush        124
     225: invokevirtual #136                // Method java/lang/StringBuffer.append:(C)Ljava/lang/StringBuffer;
     228: pop
     229: return
     230: aload_0
     231: aload_2
     232: invokevirtual #141                // Method java/lang/Object.toString:()Ljava/lang/String;
     235: invokevirtual #135                // Method java/lang/StringBuffer.append:(Ljava/lang/String;)Ljava/lang/StringBuffer;
     238: pop
     239: return
     240: aload_2
     241: invokestatic  #84                 // Method isPrim:(Ljava/lang/Object;)Z
     244: ifeq          255
     247: aload_0
     248: ldc           #143                // String #<primitive>
     250: invokevirtual #135                // Method java/lang/StringBuffer.append:(Ljava/lang/String;)Ljava/lang/StringBuffer;
     253: pop
     254: return
     255: iload         4
     257: ifeq          290
     260: aload_2
     261: invokestatic  #144                // Method stringp:(Ljava/lang/Object;)Z
     264: ifeq          290
     267: aload_0
     268: bipush        34
     270: invokevirtual #136                // Method java/lang/StringBuffer.append:(C)Ljava/lang/StringBuffer;
     273: aload_2
     274: invokevirtual #141                // Method java/lang/Object.toString:()Ljava/lang/String;
     277: invokestatic  #145                // Method escapeString:(Ljava/lang/String;)Ljava/lang/String;
     280: invokevirtual #135                // Method java/lang/StringBuffer.append:(Ljava/lang/String;)Ljava/lang/StringBuffer;
     283: bipush        34
     285: invokevirtual #136                // Method java/lang/StringBuffer.append:(C)Ljava/lang/StringBuffer;
     288: pop
     289: return
     290: aload_2
     291: invokestatic  #68                 // Method atom:(Ljava/lang/Object;)Z
     294: ifeq          307
     297: aload_0
     298: aload_2
     299: invokevirtual #141                // Method java/lang/Object.toString:()Ljava/lang/String;
     302: invokevirtual #135                // Method java/lang/StringBuffer.append:(Ljava/lang/String;)Ljava/lang/StringBuffer;
     305: pop
     306: return
     307: aload_0
     308: ldc           #146                // String <internal error>
     310: invokevirtual #135                // Method java/lang/StringBuffer.append:(Ljava/lang/String;)Ljava/lang/StringBuffer;
     313: pop
     314: return

  private static java.lang.String escapeString(java.lang.String);
    Code:
       0: getstatic     #147                // Field dQuotePattern:Ljava/util/regex/Pattern;
       3: aload_0
       4: invokevirtual #148                // Method java/util/regex/Pattern.matcher:(Ljava/lang/CharSequence;)Ljava/util/regex/Matcher;
       7: ldc           #149                // String \\\"
       9: invokevirtual #150                // Method java/util/regex/Matcher.replaceAll:(Ljava/lang/String;)Ljava/lang/String;
      12: astore_0
      13: getstatic     #151                // Field bSlashPattern:Ljava/util/regex/Pattern;
      16: aload_0
      17: invokevirtual #148                // Method java/util/regex/Pattern.matcher:(Ljava/lang/CharSequence;)Ljava/util/regex/Matcher;
      20: ldc           #152                // String \\\\$1
      22: invokevirtual #150                // Method java/util/regex/Matcher.replaceAll:(Ljava/lang/String;)Ljava/lang/String;
      25: astore_0
      26: aload_0
      27: areturn

  private java.lang.Object boolResult(boolean);
    Code:
       0: iload_1
       1: ifeq          16
       4: aload_0
       5: getfield      #49                 // Field expTrue:Ljava/util/function/Supplier;
       8: invokeinterface #69,  1           // InterfaceMethod java/util/function/Supplier.get:()Ljava/lang/Object;
      13: goto          17
      16: aconst_null
      17: areturn

  private static void noArgs(java.lang.String, com.robertmayer.lambdaj.LambdaJ$ConsCell);
    Code:
       0: aload_1
       1: ifnull        38
       4: new           #53                 // class com/robertmayer/lambdaj/LambdaJ$LambdaJError
       7: dup
       8: new           #61                 // class java/lang/StringBuilder
      11: dup
      12: invokespecial #62                 // Method java/lang/StringBuilder."<init>":()V
      15: aload_0
      16: invokevirtual #64                 // Method java/lang/StringBuilder.append:(Ljava/lang/String;)Ljava/lang/StringBuilder;
      19: ldc           #153                // String : expected no arguments but got
      21: invokevirtual #64                 // Method java/lang/StringBuilder.append:(Ljava/lang/String;)Ljava/lang/StringBuilder;
      24: aload_1
      25: invokestatic  #11                 // Method printSEx:(Ljava/lang/Object;)Ljava/lang/String;
      28: invokevirtual #64                 // Method java/lang/StringBuilder.append:(Ljava/lang/String;)Ljava/lang/StringBuilder;
      31: invokevirtual #67                 // Method java/lang/StringBuilder.toString:()Ljava/lang/String;
      34: invokespecial #55                 // Method com/robertmayer/lambdaj/LambdaJ$LambdaJError."<init>":(Ljava/lang/String;)V
      37: athrow
      38: return

  private static void oneArg(java.lang.String, java.lang.Object);
    Code:
       0: aload_1
       1: ifnonnull     31
       4: new           #53                 // class com/robertmayer/lambdaj/LambdaJ$LambdaJError
       7: dup
       8: new           #61                 // class java/lang/StringBuilder
      11: dup
      12: invokespecial #62                 // Method java/lang/StringBuilder."<init>":()V
      15: aload_0
      16: invokevirtual #64                 // Method java/lang/StringBuilder.append:(Ljava/lang/String;)Ljava/lang/StringBuilder;
      19: ldc           #154                // String : expected one argument but no argument was given
      21: invokevirtual #64                 // Method java/lang/StringBuilder.append:(Ljava/lang/String;)Ljava/lang/StringBuilder;
      24: invokevirtual #67                 // Method java/lang/StringBuilder.toString:()Ljava/lang/String;
      27: invokespecial #55                 // Method com/robertmayer/lambdaj/LambdaJ$LambdaJError."<init>":(Ljava/lang/String;)V
      30: athrow
      31: aload_1
      32: invokestatic  #5                  // Method cdr:(Ljava/lang/Object;)Ljava/lang/Object;
      35: ifnull        75
      38: new           #53                 // class com/robertmayer/lambdaj/LambdaJ$LambdaJError
      41: dup
      42: new           #61                 // class java/lang/StringBuilder
      45: dup
      46: invokespecial #62                 // Method java/lang/StringBuilder."<init>":()V
      49: aload_0
      50: invokevirtual #64                 // Method java/lang/StringBuilder.append:(Ljava/lang/String;)Ljava/lang/StringBuilder;
      53: ldc           #155                // String : expected one argument but got extra arg(s)
      55: invokevirtual #64                 // Method java/lang/StringBuilder.append:(Ljava/lang/String;)Ljava/lang/StringBuilder;
      58: aload_1
      59: invokestatic  #5                  // Method cdr:(Ljava/lang/Object;)Ljava/lang/Object;
      62: invokestatic  #11                 // Method printSEx:(Ljava/lang/Object;)Ljava/lang/String;
      65: invokevirtual #64                 // Method java/lang/StringBuilder.append:(Ljava/lang/String;)Ljava/lang/StringBuilder;
      68: invokevirtual #67                 // Method java/lang/StringBuilder.toString:()Ljava/lang/String;
      71: invokespecial #55                 // Method com/robertmayer/lambdaj/LambdaJ$LambdaJError."<init>":(Ljava/lang/String;)V
      74: athrow
      75: return

  private static void oneOrMoreArgs(java.lang.String, com.robertmayer.lambdaj.LambdaJ$ConsCell);
    Code:
       0: aload_1
       1: ifnonnull     31
       4: new           #53                 // class com/robertmayer/lambdaj/LambdaJ$LambdaJError
       7: dup
       8: new           #61                 // class java/lang/StringBuilder
      11: dup
      12: invokespecial #62                 // Method java/lang/StringBuilder."<init>":()V
      15: aload_0
      16: invokevirtual #64                 // Method java/lang/StringBuilder.append:(Ljava/lang/String;)Ljava/lang/StringBuilder;
      19: ldc           #156                // String : expected at least one argument but no argument was given
      21: invokevirtual #64                 // Method java/lang/StringBuilder.append:(Ljava/lang/String;)Ljava/lang/StringBuilder;
      24: invokevirtual #67                 // Method java/lang/StringBuilder.toString:()Ljava/lang/String;
      27: invokespecial #55                 // Method com/robertmayer/lambdaj/LambdaJ$LambdaJError."<init>":(Ljava/lang/String;)V
      30: athrow
      31: return

  private static void twoArgs(java.lang.String, java.lang.Object);
    Code:
       0: aload_0
       1: aload_1
       2: aconst_null
       3: invokestatic  #80                 // Method twoArgs:(Ljava/lang/String;Ljava/lang/Object;Ljava/lang/Object;)V
       6: return

  private static void twoArgs(java.lang.String, java.lang.Object, java.lang.Object);
    Code:
       0: aload_1
       1: ifnonnull     38
       4: new           #53                 // class com/robertmayer/lambdaj/LambdaJ$LambdaJError
       7: dup
       8: new           #61                 // class java/lang/StringBuilder
      11: dup
      12: invokespecial #62                 // Method java/lang/StringBuilder."<init>":()V
      15: aload_0
      16: invokevirtual #64                 // Method java/lang/StringBuilder.append:(Ljava/lang/String;)Ljava/lang/StringBuilder;
      19: ldc           #157                // String : expected two arguments but no argument was given
      21: invokevirtual #64                 // Method java/lang/StringBuilder.append:(Ljava/lang/String;)Ljava/lang/StringBuilder;
      24: aload_2
      25: invokestatic  #82                 // Method errorExp:(Ljava/lang/Object;)Ljava/lang/String;
      28: invokevirtual #64                 // Method java/lang/StringBuilder.append:(Ljava/lang/String;)Ljava/lang/StringBuilder;
      31: invokevirtual #67                 // Method java/lang/StringBuilder.toString:()Ljava/lang/String;
      34: invokespecial #55                 // Method com/robertmayer/lambdaj/LambdaJ$LambdaJError."<init>":(Ljava/lang/String;)V
      37: athrow
      38: aload_1
      39: invokestatic  #5                  // Method cdr:(Ljava/lang/Object;)Ljava/lang/Object;
      42: ifnonnull     79
      45: new           #53                 // class com/robertmayer/lambdaj/LambdaJ$LambdaJError
      48: dup
      49: new           #61                 // class java/lang/StringBuilder
      52: dup
      53: invokespecial #62                 // Method java/lang/StringBuilder."<init>":()V
      56: aload_0
      57: invokevirtual #64                 // Method java/lang/StringBuilder.append:(Ljava/lang/String;)Ljava/lang/StringBuilder;
      60: ldc           #158                // String : expected two arguments but only one argument was given
      62: invokevirtual #64                 // Method java/lang/StringBuilder.append:(Ljava/lang/String;)Ljava/lang/StringBuilder;
      65: aload_2
      66: invokestatic  #82                 // Method errorExp:(Ljava/lang/Object;)Ljava/lang/String;
      69: invokevirtual #64                 // Method java/lang/StringBuilder.append:(Ljava/lang/String;)Ljava/lang/StringBuilder;
      72: invokevirtual #67                 // Method java/lang/StringBuilder.toString:()Ljava/lang/String;
      75: invokespecial #55                 // Method com/robertmayer/lambdaj/LambdaJ$LambdaJError."<init>":(Ljava/lang/String;)V
      78: athrow
      79: aload_1
      80: invokestatic  #5                  // Method cdr:(Ljava/lang/Object;)Ljava/lang/Object;
      83: invokestatic  #5                  // Method cdr:(Ljava/lang/Object;)Ljava/lang/Object;
      86: ifnull        136
      89: new           #53                 // class com/robertmayer/lambdaj/LambdaJ$LambdaJError
      92: dup
      93: new           #61                 // class java/lang/StringBuilder
      96: dup
      97: invokespecial #62                 // Method java/lang/StringBuilder."<init>":()V
     100: aload_0
     101: invokevirtual #64                 // Method java/lang/StringBuilder.append:(Ljava/lang/String;)Ljava/lang/StringBuilder;
     104: ldc           #159                // String : expected two arguments but got extra arg(s)
     106: invokevirtual #64                 // Method java/lang/StringBuilder.append:(Ljava/lang/String;)Ljava/lang/StringBuilder;
     109: aload_1
     110: invokestatic  #5                  // Method cdr:(Ljava/lang/Object;)Ljava/lang/Object;
     113: invokestatic  #5                  // Method cdr:(Ljava/lang/Object;)Ljava/lang/Object;
     116: invokestatic  #11                 // Method printSEx:(Ljava/lang/Object;)Ljava/lang/String;
     119: invokevirtual #64                 // Method java/lang/StringBuilder.append:(Ljava/lang/String;)Ljava/lang/StringBuilder;
     122: aload_2
     123: invokestatic  #82                 // Method errorExp:(Ljava/lang/Object;)Ljava/lang/String;
     126: invokevirtual #64                 // Method java/lang/StringBuilder.append:(Ljava/lang/String;)Ljava/lang/StringBuilder;
     129: invokevirtual #67                 // Method java/lang/StringBuilder.toString:()Ljava/lang/String;
     132: invokespecial #55                 // Method com/robertmayer/lambdaj/LambdaJ$LambdaJError."<init>":(Ljava/lang/String;)V
     135: athrow
     136: return

  private static void nArgs(java.lang.String, java.lang.Object, int, java.lang.Object);
    Code:
       0: aload_1
       1: invokestatic  #160                // Method length:(Ljava/lang/Object;)I
       4: istore        4
       6: iload         4
       8: iload_2
       9: if_icmpge     60
      12: new           #53                 // class com/robertmayer/lambdaj/LambdaJ$LambdaJError
      15: dup
      16: new           #61                 // class java/lang/StringBuilder
      19: dup
      20: invokespecial #62                 // Method java/lang/StringBuilder."<init>":()V
      23: aload_0
      24: invokevirtual #64                 // Method java/lang/StringBuilder.append:(Ljava/lang/String;)Ljava/lang/StringBuilder;
      27: ldc           #161                // String : expected
      29: invokevirtual #64                 // Method java/lang/StringBuilder.append:(Ljava/lang/String;)Ljava/lang/StringBuilder;
      32: iload_2
      33: invokevirtual #108                // Method java/lang/StringBuilder.append:(I)Ljava/lang/StringBuilder;
      36: ldc           #162                // String  arguments or more but got only
      38: invokevirtual #64                 // Method java/lang/StringBuilder.append:(Ljava/lang/String;)Ljava/lang/StringBuilder;
      41: iload         4
      43: invokevirtual #108                // Method java/lang/StringBuilder.append:(I)Ljava/lang/StringBuilder;
      46: aload_3
      47: invokestatic  #82                 // Method errorExp:(Ljava/lang/Object;)Ljava/lang/String;
      50: invokevirtual #64                 // Method java/lang/StringBuilder.append:(Ljava/lang/String;)Ljava/lang/StringBuilder;
      53: invokevirtual #67                 // Method java/lang/StringBuilder.toString:()Ljava/lang/String;
      56: invokespecial #55                 // Method com/robertmayer/lambdaj/LambdaJ$LambdaJError."<init>":(Ljava/lang/String;)V
      59: athrow
      60: return

  private static void nArgs(java.lang.String, java.lang.Object, int, int, java.lang.Object);
    Code:
       0: aload_1
       1: invokestatic  #160                // Method length:(Ljava/lang/Object;)I
       4: istore        5
       6: iload         5
       8: iload_2
       9: if_icmpge     70
      12: new           #53                 // class com/robertmayer/lambdaj/LambdaJ$LambdaJError
      15: dup
      16: new           #61                 // class java/lang/StringBuilder
      19: dup
      20: invokespecial #62                 // Method java/lang/StringBuilder."<init>":()V
      23: aload_0
      24: invokevirtual #64                 // Method java/lang/StringBuilder.append:(Ljava/lang/String;)Ljava/lang/StringBuilder;
      27: ldc           #161                // String : expected
      29: invokevirtual #64                 // Method java/lang/StringBuilder.append:(Ljava/lang/String;)Ljava/lang/StringBuilder;
      32: iload_2
      33: invokevirtual #108                // Method java/lang/StringBuilder.append:(I)Ljava/lang/StringBuilder;
      36: ldc           #163                // String  to
      38: invokevirtual #64                 // Method java/lang/StringBuilder.append:(Ljava/lang/String;)Ljava/lang/StringBuilder;
      41: iload_3
      42: invokevirtual #108                // Method java/lang/StringBuilder.append:(I)Ljava/lang/StringBuilder;
      45: ldc           #164                // String  arguments but got only
      47: invokevirtual #64                 // Method java/lang/StringBuilder.append:(Ljava/lang/String;)Ljava/lang/StringBuilder;
      50: iload         5
      52: invokevirtual #108                // Method java/lang/StringBuilder.append:(I)Ljava/lang/StringBuilder;
      55: aload         4
      57: invokestatic  #82                 // Method errorExp:(Ljava/lang/Object;)Ljava/lang/String;
      60: invokevirtual #64                 // Method java/lang/StringBuilder.append:(Ljava/lang/String;)Ljava/lang/StringBuilder;
      63: invokevirtual #67                 // Method java/lang/StringBuilder.toString:()Ljava/lang/String;
      66: invokespecial #55                 // Method com/robertmayer/lambdaj/LambdaJ$LambdaJError."<init>":(Ljava/lang/String;)V
      69: athrow
      70: iload         5
      72: iload_3
      73: if_icmple     140
      76: new           #53                 // class com/robertmayer/lambdaj/LambdaJ$LambdaJError
      79: dup
      80: new           #61                 // class java/lang/StringBuilder
      83: dup
      84: invokespecial #62                 // Method java/lang/StringBuilder."<init>":()V
      87: aload_0
      88: invokevirtual #64                 // Method java/lang/StringBuilder.append:(Ljava/lang/String;)Ljava/lang/StringBuilder;
      91: ldc           #161                // String : expected
      93: invokevirtual #64                 // Method java/lang/StringBuilder.append:(Ljava/lang/String;)Ljava/lang/StringBuilder;
      96: iload_2
      97: invokevirtual #108                // Method java/lang/StringBuilder.append:(I)Ljava/lang/StringBuilder;
     100: ldc           #163                // String  to
     102: invokevirtual #64                 // Method java/lang/StringBuilder.append:(Ljava/lang/String;)Ljava/lang/StringBuilder;
     105: iload_3
     106: invokevirtual #108                // Method java/lang/StringBuilder.append:(I)Ljava/lang/StringBuilder;
     109: ldc           #165                // String  arguments but got extra arg(s)
     111: invokevirtual #64                 // Method java/lang/StringBuilder.append:(Ljava/lang/String;)Ljava/lang/StringBuilder;
     114: iload_3
     115: aload_1
     116: invokestatic  #166                // Method nthcdr:(ILjava/lang/Object;)Ljava/lang/Object;
     119: invokestatic  #11                 // Method printSEx:(Ljava/lang/Object;)Ljava/lang/String;
     122: invokevirtual #64                 // Method java/lang/StringBuilder.append:(Ljava/lang/String;)Ljava/lang/StringBuilder;
     125: aload         4
     127: invokestatic  #82                 // Method errorExp:(Ljava/lang/Object;)Ljava/lang/String;
     130: invokevirtual #64                 // Method java/lang/StringBuilder.append:(Ljava/lang/String;)Ljava/lang/StringBuilder;
     133: invokevirtual #67                 // Method java/lang/StringBuilder.toString:()Ljava/lang/String;
     136: invokespecial #55                 // Method com/robertmayer/lambdaj/LambdaJ$LambdaJError."<init>":(Ljava/lang/String;)V
     139: athrow
     140: return

  private static void onePair(java.lang.String, com.robertmayer.lambdaj.LambdaJ$ConsCell);
    Code:
       0: aload_1
       1: ifnonnull     31
       4: new           #53                 // class com/robertmayer/lambdaj/LambdaJ$LambdaJError
       7: dup
       8: new           #61                 // class java/lang/StringBuilder
      11: dup
      12: invokespecial #62                 // Method java/lang/StringBuilder."<init>":()V
      15: aload_0
      16: invokevirtual #64                 // Method java/lang/StringBuilder.append:(Ljava/lang/String;)Ljava/lang/StringBuilder;
      19: ldc           #167                // String : expected one Pair argument but no argument was given
      21: invokevirtual #64                 // Method java/lang/StringBuilder.append:(Ljava/lang/String;)Ljava/lang/StringBuilder;
      24: invokevirtual #67                 // Method java/lang/StringBuilder.toString:()Ljava/lang/String;
      27: invokespecial #55                 // Method com/robertmayer/lambdaj/LambdaJ$LambdaJError."<init>":(Ljava/lang/String;)V
      30: athrow
      31: aload_1
      32: invokestatic  #4                  // Method car:(Ljava/lang/Object;)Ljava/lang/Object;
      35: invokestatic  #121                // Method listp:(Ljava/lang/Object;)Z
      38: ifne          75
      41: new           #53                 // class com/robertmayer/lambdaj/LambdaJ$LambdaJError
      44: dup
      45: new           #61                 // class java/lang/StringBuilder
      48: dup
      49: invokespecial #62                 // Method java/lang/StringBuilder."<init>":()V
      52: aload_0
      53: invokevirtual #64                 // Method java/lang/StringBuilder.append:(Ljava/lang/String;)Ljava/lang/StringBuilder;
      56: ldc           #168                // String : expected one Pair argument but got
      58: invokevirtual #64                 // Method java/lang/StringBuilder.append:(Ljava/lang/String;)Ljava/lang/StringBuilder;
      61: aload_1
      62: invokestatic  #11                 // Method printSEx:(Ljava/lang/Object;)Ljava/lang/String;
      65: invokevirtual #64                 // Method java/lang/StringBuilder.append:(Ljava/lang/String;)Ljava/lang/StringBuilder;
      68: invokevirtual #67                 // Method java/lang/StringBuilder.toString:()Ljava/lang/String;
      71: invokespecial #55                 // Method com/robertmayer/lambdaj/LambdaJ$LambdaJError."<init>":(Ljava/lang/String;)V
      74: athrow
      75: aload_1
      76: invokestatic  #5                  // Method cdr:(Ljava/lang/Object;)Ljava/lang/Object;
      79: ifnull        119
      82: new           #53                 // class com/robertmayer/lambdaj/LambdaJ$LambdaJError
      85: dup
      86: new           #61                 // class java/lang/StringBuilder
      89: dup
      90: invokespecial #62                 // Method java/lang/StringBuilder."<init>":()V
      93: aload_0
      94: invokevirtual #64                 // Method java/lang/StringBuilder.append:(Ljava/lang/String;)Ljava/lang/StringBuilder;
      97: ldc           #169                // String : expected one Pair argument but got extra arg(s)
      99: invokevirtual #64                 // Method java/lang/StringBuilder.append:(Ljava/lang/String;)Ljava/lang/StringBuilder;
     102: aload_1
     103: invokestatic  #5                  // Method cdr:(Ljava/lang/Object;)Ljava/lang/Object;
     106: invokestatic  #11                 // Method printSEx:(Ljava/lang/Object;)Ljava/lang/String;
     109: invokevirtual #64                 // Method java/lang/StringBuilder.append:(Ljava/lang/String;)Ljava/lang/StringBuilder;
     112: invokevirtual #67                 // Method java/lang/StringBuilder.toString:()Ljava/lang/String;
     115: invokespecial #55                 // Method com/robertmayer/lambdaj/LambdaJ$LambdaJError."<init>":(Ljava/lang/String;)V
     118: athrow
     119: return

  private static void numberArgs(java.lang.String, com.robertmayer.lambdaj.LambdaJ$ConsCell);
    Code:
       0: aload_1
       1: ifnonnull     5
       4: return
       5: aload_1
       6: ifnull        81
       9: aload_1
      10: invokestatic  #4                  // Method car:(Ljava/lang/Object;)Ljava/lang/Object;
      13: invokestatic  #170                // Method numberp:(Ljava/lang/Object;)Z
      16: ifeq          36
      19: aload_1
      20: invokestatic  #5                  // Method cdr:(Ljava/lang/Object;)Ljava/lang/Object;
      23: ifnull        70
      26: aload_1
      27: invokestatic  #5                  // Method cdr:(Ljava/lang/Object;)Ljava/lang/Object;
      30: invokestatic  #83                 // Method consp:(Ljava/lang/Object;)Z
      33: ifne          70
      36: new           #53                 // class com/robertmayer/lambdaj/LambdaJ$LambdaJError
      39: dup
      40: new           #61                 // class java/lang/StringBuilder
      43: dup
      44: invokespecial #62                 // Method java/lang/StringBuilder."<init>":()V
      47: aload_0
      48: invokevirtual #64                 // Method java/lang/StringBuilder.append:(Ljava/lang/String;)Ljava/lang/StringBuilder;
      51: ldc           #171                // String : expected only number arguments but got
      53: invokevirtual #64                 // Method java/lang/StringBuilder.append:(Ljava/lang/String;)Ljava/lang/StringBuilder;
      56: aload_1
      57: invokestatic  #11                 // Method printSEx:(Ljava/lang/Object;)Ljava/lang/String;
      60: invokevirtual #64                 // Method java/lang/StringBuilder.append:(Ljava/lang/String;)Ljava/lang/StringBuilder;
      63: invokevirtual #67                 // Method java/lang/StringBuilder.toString:()Ljava/lang/String;
      66: invokespecial #55                 // Method com/robertmayer/lambdaj/LambdaJ$LambdaJError."<init>":(Ljava/lang/String;)V
      69: athrow
      70: aload_1
      71: invokestatic  #5                  // Method cdr:(Ljava/lang/Object;)Ljava/lang/Object;
      74: checkcast     #77                 // class com/robertmayer/lambdaj/LambdaJ$ConsCell
      77: astore_1
      78: goto          5
      81: return

  private static void oneOrMoreNumbers(java.lang.String, com.robertmayer.lambdaj.LambdaJ$ConsCell);
    Code:
       0: aload_0
       1: aload_1
       2: invokestatic  #172                // Method oneOrMoreArgs:(Ljava/lang/String;Lcom/robertmayer/lambdaj/LambdaJ$ConsCell;)V
       5: aload_0
       6: aload_1
       7: invokestatic  #173                // Method numberArgs:(Ljava/lang/String;Lcom/robertmayer/lambdaj/LambdaJ$ConsCell;)V
      10: return

  private void stringArg(java.lang.String, java.lang.String, java.lang.Object);
    Code:
       0: aload_3
       1: invokestatic  #4                  // Method car:(Ljava/lang/Object;)Ljava/lang/Object;
       4: instanceof    #120                // class com/robertmayer/lambdaj/LambdaJ$LambdaJString
       7: ifne          56
      10: new           #53                 // class com/robertmayer/lambdaj/LambdaJ$LambdaJError
      13: dup
      14: new           #61                 // class java/lang/StringBuilder
      17: dup
      18: invokespecial #62                 // Method java/lang/StringBuilder."<init>":()V
      21: aload_1
      22: invokevirtual #64                 // Method java/lang/StringBuilder.append:(Ljava/lang/String;)Ljava/lang/StringBuilder;
      25: ldc           #161                // String : expected
      27: invokevirtual #64                 // Method java/lang/StringBuilder.append:(Ljava/lang/String;)Ljava/lang/StringBuilder;
      30: aload_2
      31: invokevirtual #64                 // Method java/lang/StringBuilder.append:(Ljava/lang/String;)Ljava/lang/StringBuilder;
      34: ldc           #174                // String  to be a String but got
      36: invokevirtual #64                 // Method java/lang/StringBuilder.append:(Ljava/lang/String;)Ljava/lang/StringBuilder;
      39: aload_3
      40: invokestatic  #4                  // Method car:(Ljava/lang/Object;)Ljava/lang/Object;
      43: invokestatic  #11                 // Method printSEx:(Ljava/lang/Object;)Ljava/lang/String;
      46: invokevirtual #64                 // Method java/lang/StringBuilder.append:(Ljava/lang/String;)Ljava/lang/StringBuilder;
      49: invokevirtual #67                 // Method java/lang/StringBuilder.toString:()Ljava/lang/String;
      52: invokespecial #55                 // Method com/robertmayer/lambdaj/LambdaJ$LambdaJError."<init>":(Ljava/lang/String;)V
      55: athrow
      56: return

  private static java.lang.String errorExp(java.lang.Object);
    Code:
       0: aload_0
       1: ifnonnull     7
       4: ldc           #175                // String
       6: areturn
       7: new           #61                 // class java/lang/StringBuilder
      10: dup
      11: invokespecial #62                 // Method java/lang/StringBuilder."<init>":()V
      14: ldc           #176                // String \nerror occurred in expression
      16: invokevirtual #64                 // Method java/lang/StringBuilder.append:(Ljava/lang/String;)Ljava/lang/StringBuilder;
      19: aload_0
      20: invokestatic  #11                 // Method printSEx:(Ljava/lang/Object;)Ljava/lang/String;
      23: invokevirtual #64                 // Method java/lang/StringBuilder.append:(Ljava/lang/String;)Ljava/lang/StringBuilder;
      26: invokevirtual #67                 // Method java/lang/StringBuilder.toString:()Ljava/lang/String;
      29: areturn

  private java.lang.Object makeCompareOp(com.robertmayer.lambdaj.LambdaJ$ConsCell, java.lang.String, java.util.function.IntPredicate);
    Code:
       0: aload_2
       1: aload_1
       2: invokestatic  #177                // Method twoArgs:(Ljava/lang/String;Ljava/lang/Object;)V
       5: aload_2
       6: aload_1
       7: invokestatic  #173                // Method numberArgs:(Ljava/lang/String;Lcom/robertmayer/lambdaj/LambdaJ$ConsCell;)V
      10: aload_1
      11: invokestatic  #4                  // Method car:(Ljava/lang/Object;)Ljava/lang/Object;
      14: checkcast     #178                // class java/lang/Double
      17: invokevirtual #179                // Method java/lang/Double.doubleValue:()D
      20: dstore        4
      22: aload_1
      23: invokestatic  #5                  // Method cdr:(Ljava/lang/Object;)Ljava/lang/Object;
      26: invokestatic  #4                  // Method car:(Ljava/lang/Object;)Ljava/lang/Object;
      29: checkcast     #178                // class java/lang/Double
      32: invokevirtual #179                // Method java/lang/Double.doubleValue:()D
      35: dstore        6
      37: aload_0
      38: aload_3
      39: dload         4
      41: dload         6
      43: invokestatic  #180                // Method java/lang/Double.compare:(DD)I
      46: invokeinterface #181,  2          // InterfaceMethod java/util/function/IntPredicate.test:(I)Z
      51: invokespecial #182                // Method boolResult:(Z)Ljava/lang/Object;
      54: areturn

  private static java.lang.Object makeAddOp(com.robertmayer.lambdaj.LambdaJ$ConsCell, java.lang.String, double, java.util.function.DoubleBinaryOperator);
    Code:
       0: aload_1
       1: aload_0
       2: invokestatic  #173                // Method numberArgs:(Ljava/lang/String;Lcom/robertmayer/lambdaj/LambdaJ$ConsCell;)V
       5: aload_0
       6: ifnull        39
       9: aload         4
      11: dload_2
      12: aload_0
      13: invokestatic  #4                  // Method car:(Ljava/lang/Object;)Ljava/lang/Object;
      16: checkcast     #178                // class java/lang/Double
      19: invokevirtual #179                // Method java/lang/Double.doubleValue:()D
      22: invokeinterface #183,  5          // InterfaceMethod java/util/function/DoubleBinaryOperator.applyAsDouble:(DD)D
      27: dstore_2
      28: aload_0
      29: invokestatic  #5                  // Method cdr:(Ljava/lang/Object;)Ljava/lang/Object;
      32: checkcast     #77                 // class com/robertmayer/lambdaj/LambdaJ$ConsCell
      35: astore_0
      36: goto          5
      39: dload_2
      40: invokestatic  #184                // Method java/lang/Double.valueOf:(D)Ljava/lang/Double;
      43: areturn

  private static java.lang.Object makeSubOp(com.robertmayer.lambdaj.LambdaJ$ConsCell, java.lang.String, double, java.util.function.DoubleBinaryOperator);
    Code:
       0: ldc           #185                // String -
       2: aload_0
       3: invokestatic  #186                // Method oneOrMoreNumbers:(Ljava/lang/String;Lcom/robertmayer/lambdaj/LambdaJ$ConsCell;)V
       6: aload_0
       7: invokestatic  #4                  // Method car:(Ljava/lang/Object;)Ljava/lang/Object;
      10: checkcast     #178                // class java/lang/Double
      13: invokevirtual #179                // Method java/lang/Double.doubleValue:()D
      16: dstore        5
      18: aload_0
      19: invokestatic  #5                  // Method cdr:(Ljava/lang/Object;)Ljava/lang/Object;
      22: ifnonnull     39
      25: aload         4
      27: dload_2
      28: dload         5
      30: invokeinterface #183,  5          // InterfaceMethod java/util/function/DoubleBinaryOperator.applyAsDouble:(DD)D
      35: invokestatic  #184                // Method java/lang/Double.valueOf:(D)Ljava/lang/Double;
      38: areturn
      39: aload_0
      40: invokestatic  #5                  // Method cdr:(Ljava/lang/Object;)Ljava/lang/Object;
      43: checkcast     #77                 // class com/robertmayer/lambdaj/LambdaJ$ConsCell
      46: astore_0
      47: aload_0
      48: ifnull        83
      51: aload         4
      53: dload         5
      55: aload_0
      56: invokestatic  #4                  // Method car:(Ljava/lang/Object;)Ljava/lang/Object;
      59: checkcast     #178                // class java/lang/Double
      62: invokevirtual #179                // Method java/lang/Double.doubleValue:()D
      65: invokeinterface #183,  5          // InterfaceMethod java/util/function/DoubleBinaryOperator.applyAsDouble:(DD)D
      70: dstore        5
      72: aload_0
      73: invokestatic  #5                  // Method cdr:(Ljava/lang/Object;)Ljava/lang/Object;
      76: checkcast     #77                 // class com/robertmayer/lambdaj/LambdaJ$ConsCell
      79: astore_0
      80: goto          47
      83: dload         5
      85: invokestatic  #184                // Method java/lang/Double.valueOf:(D)Ljava/lang/Double;
      88: areturn

  private com.robertmayer.lambdaj.LambdaJ$ConsCell environment(com.robertmayer.lambdaj.LambdaJ$SymbolTable, com.robertmayer.lambdaj.LambdaJ$ConsCell, com.robertmayer.lambdaj.LambdaJ$ObjectReader, com.robertmayer.lambdaj.LambdaJ$ObjectWriter);
    Code:
       0: aload_2
       1: astore        5
       3: aload_0
       4: getfield      #29                 // Field HAVE_EQ:Z
       7: ifeq          42
      10: aload_0
      11: invokedynamic #187,  0            // InvokeDynamic #8:apply:(Lcom/robertmayer/lambdaj/LambdaJ;)Lcom/robertmayer/lambdaj/LambdaJ$Primitive;
      16: astore        6
      18: aload_1
      19: ldc           #188                // String eq
      21: invokeinterface #51,  2           // InterfaceMethod com/robertmayer/lambdaj/LambdaJ$SymbolTable.intern:(Ljava/lang/String;)Ljava/lang/Object;
      26: aload         6
      28: aconst_null
      29: invokestatic  #3                  // Method cons:(Ljava/lang/Object;Ljava/lang/Object;)Lcom/robertmayer/lambdaj/LambdaJ$ConsCell;
      32: invokestatic  #3                  // Method cons:(Ljava/lang/Object;Ljava/lang/Object;)Lcom/robertmayer/lambdaj/LambdaJ$ConsCell;
      35: aload         5
      37: invokestatic  #3                  // Method cons:(Ljava/lang/Object;Ljava/lang/Object;)Lcom/robertmayer/lambdaj/LambdaJ$ConsCell;
      40: astore        5
      42: aload_0
      43: getfield      #28                 // Field HAVE_ATOM:Z
      46: ifeq          81
      49: aload_0
      50: invokedynamic #189,  0            // InvokeDynamic #9:apply:(Lcom/robertmayer/lambdaj/LambdaJ;)Lcom/robertmayer/lambdaj/LambdaJ$Primitive;
      55: astore        6
      57: aload_1
      58: ldc           #190                // String atom
      60: invokeinterface #51,  2           // InterfaceMethod com/robertmayer/lambdaj/LambdaJ$SymbolTable.intern:(Ljava/lang/String;)Ljava/lang/Object;
      65: aload         6
      67: aconst_null
      68: invokestatic  #3                  // Method cons:(Ljava/lang/Object;Ljava/lang/Object;)Lcom/robertmayer/lambdaj/LambdaJ$ConsCell;
      71: invokestatic  #3                  // Method cons:(Ljava/lang/Object;Ljava/lang/Object;)Lcom/robertmayer/lambdaj/LambdaJ$ConsCell;
      74: aload         5
      76: invokestatic  #3                  // Method cons:(Ljava/lang/Object;Ljava/lang/Object;)Lcom/robertmayer/lambdaj/LambdaJ$ConsCell;
      79: astore        5
      81: aload_0
      82: getfield      #21                 // Field HAVE_T:Z
      85: ifeq          118
      88: aload_1
      89: ldc           #50                 // String t
      91: invokeinterface #51,  2           // InterfaceMethod com/robertmayer/lambdaj/LambdaJ$SymbolTable.intern:(Ljava/lang/String;)Ljava/lang/Object;
      96: aload_1
      97: ldc           #50                 // String t
      99: invokeinterface #51,  2           // InterfaceMethod com/robertmayer/lambdaj/LambdaJ$SymbolTable.intern:(Ljava/lang/String;)Ljava/lang/Object;
     104: aconst_null
     105: invokestatic  #3                  // Method cons:(Ljava/lang/Object;Ljava/lang/Object;)Lcom/robertmayer/lambdaj/LambdaJ$ConsCell;
     108: invokestatic  #3                  // Method cons:(Ljava/lang/Object;Ljava/lang/Object;)Lcom/robertmayer/lambdaj/LambdaJ$ConsCell;
     111: aload         5
     113: invokestatic  #3                  // Method cons:(Ljava/lang/Object;Ljava/lang/Object;)Lcom/robertmayer/lambdaj/LambdaJ$ConsCell;
     116: astore        5
     118: aload_0
     119: getfield      #20                 // Field HAVE_NIL:Z
     122: ifeq          148
     125: aload_1
     126: ldc           #130                // String nil
     128: invokeinterface #51,  2           // InterfaceMethod com/robertmayer/lambdaj/LambdaJ$SymbolTable.intern:(Ljava/lang/String;)Ljava/lang/Object;
     133: aconst_null
     134: aconst_null
     135: invokestatic  #3                  // Method cons:(Ljava/lang/Object;Ljava/lang/Object;)Lcom/robertmayer/lambdaj/LambdaJ$ConsCell;
     138: invokestatic  #3                  // Method cons:(Ljava/lang/Object;Ljava/lang/Object;)Lcom/robertmayer/lambdaj/LambdaJ$ConsCell;
     141: aload         5
     143: invokestatic  #3                  // Method cons:(Ljava/lang/Object;Ljava/lang/Object;)Lcom/robertmayer/lambdaj/LambdaJ$ConsCell;
     146: astore        5
     148: aload_0
     149: getfield      #23                 // Field HAVE_IO:Z
     152: ifeq          247
     155: aload_3
     156: invokedynamic #191,  0            // InvokeDynamic #10:apply:(Lcom/robertmayer/lambdaj/LambdaJ$ObjectReader;)Lcom/robertmayer/lambdaj/LambdaJ$Primitive;
     161: astore        6
     163: aload_0
     164: aload         4
     166: invokedynamic #192,  0            // InvokeDynamic #11:apply:(Lcom/robertmayer/lambdaj/LambdaJ;Lcom/robertmayer/lambdaj/LambdaJ$ObjectWriter;)Lcom/robertmayer/lambdaj/LambdaJ$Primitive;
     171: astore        7
     173: aload_0
     174: aload         4
     176: invokedynamic #193,  0            // InvokeDynamic #12:apply:(Lcom/robertmayer/lambdaj/LambdaJ;Lcom/robertmayer/lambdaj/LambdaJ$ObjectWriter;)Lcom/robertmayer/lambdaj/LambdaJ$Primitive;
     181: astore        8
     183: aload_1
     184: ldc           #194                // String read
     186: invokeinterface #51,  2           // InterfaceMethod com/robertmayer/lambdaj/LambdaJ$SymbolTable.intern:(Ljava/lang/String;)Ljava/lang/Object;
     191: aload         6
     193: aconst_null
     194: invokestatic  #3                  // Method cons:(Ljava/lang/Object;Ljava/lang/Object;)Lcom/robertmayer/lambdaj/LambdaJ$ConsCell;
     197: invokestatic  #3                  // Method cons:(Ljava/lang/Object;Ljava/lang/Object;)Lcom/robertmayer/lambdaj/LambdaJ$ConsCell;
     200: aload_1
     201: ldc           #195                // String write
     203: invokeinterface #51,  2           // InterfaceMethod com/robertmayer/lambdaj/LambdaJ$SymbolTable.intern:(Ljava/lang/String;)Ljava/lang/Object;
     208: aload         7
     210: aconst_null
     211: invokestatic  #3                  // Method cons:(Ljava/lang/Object;Ljava/lang/Object;)Lcom/robertmayer/lambdaj/LambdaJ$ConsCell;
     214: invokestatic  #3                  // Method cons:(Ljava/lang/Object;Ljava/lang/Object;)Lcom/robertmayer/lambdaj/LambdaJ$ConsCell;
     217: aload_1
     218: ldc           #196                // String writeln
     220: invokeinterface #51,  2           // InterfaceMethod com/robertmayer/lambdaj/LambdaJ$SymbolTable.intern:(Ljava/lang/String;)Ljava/lang/Object;
     225: aload         8
     227: aconst_null
     228: invokestatic  #3                  // Method cons:(Ljava/lang/Object;Ljava/lang/Object;)Lcom/robertmayer/lambdaj/LambdaJ$ConsCell;
     231: invokestatic  #3                  // Method cons:(Ljava/lang/Object;Ljava/lang/Object;)Lcom/robertmayer/lambdaj/LambdaJ$ConsCell;
     234: aload         5
     236: invokestatic  #3                  // Method cons:(Ljava/lang/Object;Ljava/lang/Object;)Lcom/robertmayer/lambdaj/LambdaJ$ConsCell;
     239: invokestatic  #3                  // Method cons:(Ljava/lang/Object;Ljava/lang/Object;)Lcom/robertmayer/lambdaj/LambdaJ$ConsCell;
     242: invokestatic  #3                  // Method cons:(Ljava/lang/Object;Ljava/lang/Object;)Lcom/robertmayer/lambdaj/LambdaJ$ConsCell;
     245: astore        5
     247: aload_0
     248: getfield      #24                 // Field HAVE_UTIL:Z
     251: ifeq          397
     254: aload_0
     255: invokedynamic #197,  0            // InvokeDynamic #13:apply:(Lcom/robertmayer/lambdaj/LambdaJ;)Lcom/robertmayer/lambdaj/LambdaJ$Primitive;
     260: astore        6
     262: aload_0
     263: invokedynamic #198,  0            // InvokeDynamic #14:apply:(Lcom/robertmayer/lambdaj/LambdaJ;)Lcom/robertmayer/lambdaj/LambdaJ$Primitive;
     268: astore        7
     270: aload_0
     271: invokedynamic #199,  0            // InvokeDynamic #15:apply:(Lcom/robertmayer/lambdaj/LambdaJ;)Lcom/robertmayer/lambdaj/LambdaJ$Primitive;
     276: astore        8
     278: aload_0
     279: invokedynamic #200,  0            // InvokeDynamic #16:apply:(Lcom/robertmayer/lambdaj/LambdaJ;)Lcom/robertmayer/lambdaj/LambdaJ$Primitive;
     284: astore        9
     286: invokedynamic #201,  0            // InvokeDynamic #17:apply:()Lcom/robertmayer/lambdaj/LambdaJ$Primitive;
     291: astore        10
     293: aload_1
     294: ldc           #202                // String consp
     296: invokeinterface #51,  2           // InterfaceMethod com/robertmayer/lambdaj/LambdaJ$SymbolTable.intern:(Ljava/lang/String;)Ljava/lang/Object;
     301: aload         7
     303: aconst_null
     304: invokestatic  #3                  // Method cons:(Ljava/lang/Object;Ljava/lang/Object;)Lcom/robertmayer/lambdaj/LambdaJ$ConsCell;
     307: invokestatic  #3                  // Method cons:(Ljava/lang/Object;Ljava/lang/Object;)Lcom/robertmayer/lambdaj/LambdaJ$ConsCell;
     310: aload_1
     311: ldc           #203                // String symbolp
     313: invokeinterface #51,  2           // InterfaceMethod com/robertmayer/lambdaj/LambdaJ$SymbolTable.intern:(Ljava/lang/String;)Ljava/lang/Object;
     318: aload         8
     320: aconst_null
     321: invokestatic  #3                  // Method cons:(Ljava/lang/Object;Ljava/lang/Object;)Lcom/robertmayer/lambdaj/LambdaJ$ConsCell;
     324: invokestatic  #3                  // Method cons:(Ljava/lang/Object;Ljava/lang/Object;)Lcom/robertmayer/lambdaj/LambdaJ$ConsCell;
     327: aload_1
     328: ldc           #204                // String listp
     330: invokeinterface #51,  2           // InterfaceMethod com/robertmayer/lambdaj/LambdaJ$SymbolTable.intern:(Ljava/lang/String;)Ljava/lang/Object;
     335: aload         9
     337: aconst_null
     338: invokestatic  #3                  // Method cons:(Ljava/lang/Object;Ljava/lang/Object;)Lcom/robertmayer/lambdaj/LambdaJ$ConsCell;
     341: invokestatic  #3                  // Method cons:(Ljava/lang/Object;Ljava/lang/Object;)Lcom/robertmayer/lambdaj/LambdaJ$ConsCell;
     344: aload_1
     345: ldc           #205                // String null?
     347: invokeinterface #51,  2           // InterfaceMethod com/robertmayer/lambdaj/LambdaJ$SymbolTable.intern:(Ljava/lang/String;)Ljava/lang/Object;
     352: aload         6
     354: aconst_null
     355: invokestatic  #3                  // Method cons:(Ljava/lang/Object;Ljava/lang/Object;)Lcom/robertmayer/lambdaj/LambdaJ$ConsCell;
     358: invokestatic  #3                  // Method cons:(Ljava/lang/Object;Ljava/lang/Object;)Lcom/robertmayer/lambdaj/LambdaJ$ConsCell;
     361: aload_1
     362: ldc           #206                // String assoc
     364: invokeinterface #51,  2           // InterfaceMethod com/robertmayer/lambdaj/LambdaJ$SymbolTable.intern:(Ljava/lang/String;)Ljava/lang/Object;
     369: aload         10
     371: aconst_null
     372: invokestatic  #3                  // Method cons:(Ljava/lang/Object;Ljava/lang/Object;)Lcom/robertmayer/lambdaj/LambdaJ$ConsCell;
     375: invokestatic  #3                  // Method cons:(Ljava/lang/Object;Ljava/lang/Object;)Lcom/robertmayer/lambdaj/LambdaJ$ConsCell;
     378: aload         5
     380: invokestatic  #3                  // Method cons:(Ljava/lang/Object;Ljava/lang/Object;)Lcom/robertmayer/lambdaj/LambdaJ$ConsCell;
     383: invokestatic  #3                  // Method cons:(Ljava/lang/Object;Ljava/lang/Object;)Lcom/robertmayer/lambdaj/LambdaJ$ConsCell;
     386: invokestatic  #3                  // Method cons:(Ljava/lang/Object;Ljava/lang/Object;)Lcom/robertmayer/lambdaj/LambdaJ$ConsCell;
     389: invokestatic  #3                  // Method cons:(Ljava/lang/Object;Ljava/lang/Object;)Lcom/robertmayer/lambdaj/LambdaJ$ConsCell;
     392: invokestatic  #3                  // Method cons:(Ljava/lang/Object;Ljava/lang/Object;)Lcom/robertmayer/lambdaj/LambdaJ$ConsCell;
     395: astore        5
     397: aload_0
     398: getfield      #26                 // Field HAVE_CONS:Z
     401: ifeq          489
     404: invokedynamic #207,  0            // InvokeDynamic #18:apply:()Lcom/robertmayer/lambdaj/LambdaJ$Primitive;
     409: astore        6
     411: invokedynamic #208,  0            // InvokeDynamic #19:apply:()Lcom/robertmayer/lambdaj/LambdaJ$Primitive;
     416: astore        7
     418: invokedynamic #209,  0            // InvokeDynamic #20:apply:()Lcom/robertmayer/lambdaj/LambdaJ$Primitive;
     423: astore        8
     425: aload_1
     426: ldc           #210                // String car
     428: invokeinterface #51,  2           // InterfaceMethod com/robertmayer/lambdaj/LambdaJ$SymbolTable.intern:(Ljava/lang/String;)Ljava/lang/Object;
     433: aload         7
     435: aconst_null
     436: invokestatic  #3                  // Method cons:(Ljava/lang/Object;Ljava/lang/Object;)Lcom/robertmayer/lambdaj/LambdaJ$ConsCell;
     439: invokestatic  #3                  // Method cons:(Ljava/lang/Object;Ljava/lang/Object;)Lcom/robertmayer/lambdaj/LambdaJ$ConsCell;
     442: aload_1
     443: ldc           #211                // String cdr
     445: invokeinterface #51,  2           // InterfaceMethod com/robertmayer/lambdaj/LambdaJ$SymbolTable.intern:(Ljava/lang/String;)Ljava/lang/Object;
     450: aload         8
     452: aconst_null
     453: invokestatic  #3                  // Method cons:(Ljava/lang/Object;Ljava/lang/Object;)Lcom/robertmayer/lambdaj/LambdaJ$ConsCell;
     456: invokestatic  #3                  // Method cons:(Ljava/lang/Object;Ljava/lang/Object;)Lcom/robertmayer/lambdaj/LambdaJ$ConsCell;
     459: aload_1
     460: ldc           #212                // String cons
     462: invokeinterface #51,  2           // InterfaceMethod com/robertmayer/lambdaj/LambdaJ$SymbolTable.intern:(Ljava/lang/String;)Ljava/lang/Object;
     467: aload         6
     469: aconst_null
     470: invokestatic  #3                  // Method cons:(Ljava/lang/Object;Ljava/lang/Object;)Lcom/robertmayer/lambdaj/LambdaJ$ConsCell;
     473: invokestatic  #3                  // Method cons:(Ljava/lang/Object;Ljava/lang/Object;)Lcom/robertmayer/lambdaj/LambdaJ$ConsCell;
     476: aload         5
     478: invokestatic  #3                  // Method cons:(Ljava/lang/Object;Ljava/lang/Object;)Lcom/robertmayer/lambdaj/LambdaJ$ConsCell;
     481: invokestatic  #3                  // Method cons:(Ljava/lang/Object;Ljava/lang/Object;)Lcom/robertmayer/lambdaj/LambdaJ$ConsCell;
     484: invokestatic  #3                  // Method cons:(Ljava/lang/Object;Ljava/lang/Object;)Lcom/robertmayer/lambdaj/LambdaJ$ConsCell;
     487: astore        5
     489: aload_0
     490: getfield      #8                  // Field HAVE_STRING:Z
     493: ifeq          584
     496: aload_0
     497: invokedynamic #213,  0            // InvokeDynamic #21:apply:(Lcom/robertmayer/lambdaj/LambdaJ;)Lcom/robertmayer/lambdaj/LambdaJ$Primitive;
     502: astore        6
     504: aload_0
     505: invokedynamic #214,  0            // InvokeDynamic #22:apply:(Lcom/robertmayer/lambdaj/LambdaJ;)Lcom/robertmayer/lambdaj/LambdaJ$Primitive;
     510: astore        7
     512: aload_0
     513: invokedynamic #215,  0            // InvokeDynamic #23:apply:(Lcom/robertmayer/lambdaj/LambdaJ;)Lcom/robertmayer/lambdaj/LambdaJ$Primitive;
     518: astore        8
     520: aload_1
     521: ldc           #216                // String stringp
     523: invokeinterface #51,  2           // InterfaceMethod com/robertmayer/lambdaj/LambdaJ$SymbolTable.intern:(Ljava/lang/String;)Ljava/lang/Object;
     528: aload         6
     530: aconst_null
     531: invokestatic  #3                  // Method cons:(Ljava/lang/Object;Ljava/lang/Object;)Lcom/robertmayer/lambdaj/LambdaJ$ConsCell;
     534: invokestatic  #3                  // Method cons:(Ljava/lang/Object;Ljava/lang/Object;)Lcom/robertmayer/lambdaj/LambdaJ$ConsCell;
     537: aload_1
     538: ldc           #217                // String string-format
     540: invokeinterface #51,  2           // InterfaceMethod com/robertmayer/lambdaj/LambdaJ$SymbolTable.intern:(Ljava/lang/String;)Ljava/lang/Object;
     545: aload         7
     547: aconst_null
     548: invokestatic  #3                  // Method cons:(Ljava/lang/Object;Ljava/lang/Object;)Lcom/robertmayer/lambdaj/LambdaJ$ConsCell;
     551: invokestatic  #3                  // Method cons:(Ljava/lang/Object;Ljava/lang/Object;)Lcom/robertmayer/lambdaj/LambdaJ$ConsCell;
     554: aload_1
     555: ldc           #218                // String string-format-locale
     557: invokeinterface #51,  2           // InterfaceMethod com/robertmayer/lambdaj/LambdaJ$SymbolTable.intern:(Ljava/lang/String;)Ljava/lang/Object;
     562: aload         8
     564: aconst_null
     565: invokestatic  #3                  // Method cons:(Ljava/lang/Object;Ljava/lang/Object;)Lcom/robertmayer/lambdaj/LambdaJ$ConsCell;
     568: invokestatic  #3                  // Method cons:(Ljava/lang/Object;Ljava/lang/Object;)Lcom/robertmayer/lambdaj/LambdaJ$ConsCell;
     571: aload         5
     573: invokestatic  #3                  // Method cons:(Ljava/lang/Object;Ljava/lang/Object;)Lcom/robertmayer/lambdaj/LambdaJ$ConsCell;
     576: invokestatic  #3                  // Method cons:(Ljava/lang/Object;Ljava/lang/Object;)Lcom/robertmayer/lambdaj/LambdaJ$ConsCell;
     579: invokestatic  #3                  // Method cons:(Ljava/lang/Object;Ljava/lang/Object;)Lcom/robertmayer/lambdaj/LambdaJ$ConsCell;
     582: astore        5
     584: aload_0
     585: getfield      #7                  // Field HAVE_DOUBLE:Z
     588: ifeq          898
     591: aload_0
     592: invokedynamic #219,  0            // InvokeDynamic #24:apply:(Lcom/robertmayer/lambdaj/LambdaJ;)Lcom/robertmayer/lambdaj/LambdaJ$Primitive;
     597: astore        6
     599: aload_0
     600: invokedynamic #220,  0            // InvokeDynamic #25:apply:(Lcom/robertmayer/lambdaj/LambdaJ;)Lcom/robertmayer/lambdaj/LambdaJ$Primitive;
     605: astore        7
     607: aload_0
     608: invokedynamic #221,  0            // InvokeDynamic #26:apply:(Lcom/robertmayer/lambdaj/LambdaJ;)Lcom/robertmayer/lambdaj/LambdaJ$Primitive;
     613: astore        8
     615: aload_0
     616: invokedynamic #222,  0            // InvokeDynamic #27:apply:(Lcom/robertmayer/lambdaj/LambdaJ;)Lcom/robertmayer/lambdaj/LambdaJ$Primitive;
     621: astore        9
     623: aload_0
     624: invokedynamic #223,  0            // InvokeDynamic #28:apply:(Lcom/robertmayer/lambdaj/LambdaJ;)Lcom/robertmayer/lambdaj/LambdaJ$Primitive;
     629: astore        10
     631: aload_0
     632: invokedynamic #224,  0            // InvokeDynamic #29:apply:(Lcom/robertmayer/lambdaj/LambdaJ;)Lcom/robertmayer/lambdaj/LambdaJ$Primitive;
     637: astore        11
     639: invokedynamic #225,  0            // InvokeDynamic #30:apply:()Lcom/robertmayer/lambdaj/LambdaJ$Primitive;
     644: astore        12
     646: invokedynamic #226,  0            // InvokeDynamic #31:apply:()Lcom/robertmayer/lambdaj/LambdaJ$Primitive;
     651: astore        13
     653: invokedynamic #227,  0            // InvokeDynamic #32:apply:()Lcom/robertmayer/lambdaj/LambdaJ$Primitive;
     658: astore        14
     660: invokedynamic #228,  0            // InvokeDynamic #33:apply:()Lcom/robertmayer/lambdaj/LambdaJ$Primitive;
     665: astore        15
     667: invokedynamic #229,  0            // InvokeDynamic #34:apply:()Lcom/robertmayer/lambdaj/LambdaJ$Primitive;
     672: astore        16
     674: aload_1
     675: ldc           #230                // String numberp
     677: invokeinterface #51,  2           // InterfaceMethod com/robertmayer/lambdaj/LambdaJ$SymbolTable.intern:(Ljava/lang/String;)Ljava/lang/Object;
     682: aload         6
     684: aconst_null
     685: invokestatic  #3                  // Method cons:(Ljava/lang/Object;Ljava/lang/Object;)Lcom/robertmayer/lambdaj/LambdaJ$ConsCell;
     688: invokestatic  #3                  // Method cons:(Ljava/lang/Object;Ljava/lang/Object;)Lcom/robertmayer/lambdaj/LambdaJ$ConsCell;
     691: aload_1
     692: ldc           #231                // String =
     694: invokeinterface #51,  2           // InterfaceMethod com/robertmayer/lambdaj/LambdaJ$SymbolTable.intern:(Ljava/lang/String;)Ljava/lang/Object;
     699: aload         7
     701: aconst_null
     702: invokestatic  #3                  // Method cons:(Ljava/lang/Object;Ljava/lang/Object;)Lcom/robertmayer/lambdaj/LambdaJ$ConsCell;
     705: invokestatic  #3                  // Method cons:(Ljava/lang/Object;Ljava/lang/Object;)Lcom/robertmayer/lambdaj/LambdaJ$ConsCell;
     708: aload_1
     709: ldc           #232                // String >
     711: invokeinterface #51,  2           // InterfaceMethod com/robertmayer/lambdaj/LambdaJ$SymbolTable.intern:(Ljava/lang/String;)Ljava/lang/Object;
     716: aload         10
     718: aconst_null
     719: invokestatic  #3                  // Method cons:(Ljava/lang/Object;Ljava/lang/Object;)Lcom/robertmayer/lambdaj/LambdaJ$ConsCell;
     722: invokestatic  #3                  // Method cons:(Ljava/lang/Object;Ljava/lang/Object;)Lcom/robertmayer/lambdaj/LambdaJ$ConsCell;
     725: aload_1
     726: ldc           #233                // String >=
     728: invokeinterface #51,  2           // InterfaceMethod com/robertmayer/lambdaj/LambdaJ$SymbolTable.intern:(Ljava/lang/String;)Ljava/lang/Object;
     733: aload         11
     735: aconst_null
     736: invokestatic  #3                  // Method cons:(Ljava/lang/Object;Ljava/lang/Object;)Lcom/robertmayer/lambdaj/LambdaJ$ConsCell;
     739: invokestatic  #3                  // Method cons:(Ljava/lang/Object;Ljava/lang/Object;)Lcom/robertmayer/lambdaj/LambdaJ$ConsCell;
     742: aload_1
     743: ldc           #234                // String <
     745: invokeinterface #51,  2           // InterfaceMethod com/robertmayer/lambdaj/LambdaJ$SymbolTable.intern:(Ljava/lang/String;)Ljava/lang/Object;
     750: aload         8
     752: aconst_null
     753: invokestatic  #3                  // Method cons:(Ljava/lang/Object;Ljava/lang/Object;)Lcom/robertmayer/lambdaj/LambdaJ$ConsCell;
     756: invokestatic  #3                  // Method cons:(Ljava/lang/Object;Ljava/lang/Object;)Lcom/robertmayer/lambdaj/LambdaJ$ConsCell;
     759: aload_1
     760: ldc           #235                // String <=
     762: invokeinterface #51,  2           // InterfaceMethod com/robertmayer/lambdaj/LambdaJ$SymbolTable.intern:(Ljava/lang/String;)Ljava/lang/Object;
     767: aload         9
     769: aconst_null
     770: invokestatic  #3                  // Method cons:(Ljava/lang/Object;Ljava/lang/Object;)Lcom/robertmayer/lambdaj/LambdaJ$ConsCell;
     773: invokestatic  #3                  // Method cons:(Ljava/lang/Object;Ljava/lang/Object;)Lcom/robertmayer/lambdaj/LambdaJ$ConsCell;
     776: aload_1
     777: ldc           #236                // String +
     779: invokeinterface #51,  2           // InterfaceMethod com/robertmayer/lambdaj/LambdaJ$SymbolTable.intern:(Ljava/lang/String;)Ljava/lang/Object;
     784: aload         12
     786: aconst_null
     787: invokestatic  #3                  // Method cons:(Ljava/lang/Object;Ljava/lang/Object;)Lcom/robertmayer/lambdaj/LambdaJ$ConsCell;
     790: invokestatic  #3                  // Method cons:(Ljava/lang/Object;Ljava/lang/Object;)Lcom/robertmayer/lambdaj/LambdaJ$ConsCell;
     793: aload_1
     794: ldc           #185                // String -
     796: invokeinterface #51,  2           // InterfaceMethod com/robertmayer/lambdaj/LambdaJ$SymbolTable.intern:(Ljava/lang/String;)Ljava/lang/Object;
     801: aload         14
     803: aconst_null
     804: invokestatic  #3                  // Method cons:(Ljava/lang/Object;Ljava/lang/Object;)Lcom/robertmayer/lambdaj/LambdaJ$ConsCell;
     807: invokestatic  #3                  // Method cons:(Ljava/lang/Object;Ljava/lang/Object;)Lcom/robertmayer/lambdaj/LambdaJ$ConsCell;
     810: aload_1
     811: ldc           #237                // String *
     813: invokeinterface #51,  2           // InterfaceMethod com/robertmayer/lambdaj/LambdaJ$SymbolTable.intern:(Ljava/lang/String;)Ljava/lang/Object;
     818: aload         13
     820: aconst_null
     821: invokestatic  #3                  // Method cons:(Ljava/lang/Object;Ljava/lang/Object;)Lcom/robertmayer/lambdaj/LambdaJ$ConsCell;
     824: invokestatic  #3                  // Method cons:(Ljava/lang/Object;Ljava/lang/Object;)Lcom/robertmayer/lambdaj/LambdaJ$ConsCell;
     827: aload_1
     828: ldc           #238                // String /
     830: invokeinterface #51,  2           // InterfaceMethod com/robertmayer/lambdaj/LambdaJ$SymbolTable.intern:(Ljava/lang/String;)Ljava/lang/Object;
     835: aload         15
     837: aconst_null
     838: invokestatic  #3                  // Method cons:(Ljava/lang/Object;Ljava/lang/Object;)Lcom/robertmayer/lambdaj/LambdaJ$ConsCell;
     841: invokestatic  #3                  // Method cons:(Ljava/lang/Object;Ljava/lang/Object;)Lcom/robertmayer/lambdaj/LambdaJ$ConsCell;
     844: aload_1
     845: ldc           #239                // String mod
     847: invokeinterface #51,  2           // InterfaceMethod com/robertmayer/lambdaj/LambdaJ$SymbolTable.intern:(Ljava/lang/String;)Ljava/lang/Object;
     852: aload         16
     854: aconst_null
     855: invokestatic  #3                  // Method cons:(Ljava/lang/Object;Ljava/lang/Object;)Lcom/robertmayer/lambdaj/LambdaJ$ConsCell;
     858: invokestatic  #3                  // Method cons:(Ljava/lang/Object;Ljava/lang/Object;)Lcom/robertmayer/lambdaj/LambdaJ$ConsCell;
     861: aload         5
     863: invokestatic  #3                  // Method cons:(Ljava/lang/Object;Ljava/lang/Object;)Lcom/robertmayer/lambdaj/LambdaJ$ConsCell;
     866: invokestatic  #3                  // Method cons:(Ljava/lang/Object;Ljava/lang/Object;)Lcom/robertmayer/lambdaj/LambdaJ$ConsCell;
     869: invokestatic  #3                  // Method cons:(Ljava/lang/Object;Ljava/lang/Object;)Lcom/robertmayer/lambdaj/LambdaJ$ConsCell;
     872: invokestatic  #3                  // Method cons:(Ljava/lang/Object;Ljava/lang/Object;)Lcom/robertmayer/lambdaj/LambdaJ$ConsCell;
     875: invokestatic  #3                  // Method cons:(Ljava/lang/Object;Ljava/lang/Object;)Lcom/robertmayer/lambdaj/LambdaJ$ConsCell;
     878: invokestatic  #3                  // Method cons:(Ljava/lang/Object;Ljava/lang/Object;)Lcom/robertmayer/lambdaj/LambdaJ$ConsCell;
     881: invokestatic  #3                  // Method cons:(Ljava/lang/Object;Ljava/lang/Object;)Lcom/robertmayer/lambdaj/LambdaJ$ConsCell;
     884: invokestatic  #3                  // Method cons:(Ljava/lang/Object;Ljava/lang/Object;)Lcom/robertmayer/lambdaj/LambdaJ$ConsCell;
     887: invokestatic  #3                  // Method cons:(Ljava/lang/Object;Ljava/lang/Object;)Lcom/robertmayer/lambdaj/LambdaJ$ConsCell;
     890: invokestatic  #3                  // Method cons:(Ljava/lang/Object;Ljava/lang/Object;)Lcom/robertmayer/lambdaj/LambdaJ$ConsCell;
     893: invokestatic  #3                  // Method cons:(Ljava/lang/Object;Ljava/lang/Object;)Lcom/robertmayer/lambdaj/LambdaJ$ConsCell;
     896: astore        5
     898: aload         5
     900: areturn

  public java.lang.Object interpretExpression(com.robertmayer.lambdaj.LambdaJ$ReadSupplier, com.robertmayer.lambdaj.LambdaJ$WriteConsumer);
    Code:
       0: new           #240                // class com/robertmayer/lambdaj/LambdaJ$SExpressionParser
       3: dup
       4: aload_0
       5: aload_1
       6: invokespecial #241                // Method com/robertmayer/lambdaj/LambdaJ$SExpressionParser."<init>":(Lcom/robertmayer/lambdaj/LambdaJ;Lcom/robertmayer/lambdaj/LambdaJ$ReadSupplier;)V
       9: astore_3
      10: aload_0
      11: aload_3
      12: invokespecial #242                // Method setSymtab:(Lcom/robertmayer/lambdaj/LambdaJ$SymbolTable;)V
      15: new           #243                // class com/robertmayer/lambdaj/LambdaJ$SExpressionWriter
      18: dup
      19: aload_2
      20: invokespecial #244                // Method com/robertmayer/lambdaj/LambdaJ$SExpressionWriter."<init>":(Lcom/robertmayer/lambdaj/LambdaJ$WriteConsumer;)V
      23: astore        4
      25: aload_0
      26: aload_0
      27: getfield      #35                 // Field symtab:Lcom/robertmayer/lambdaj/LambdaJ$SymbolTable;
      30: aconst_null
      31: aload_3
      32: aload         4
      34: invokespecial #245                // Method environment:(Lcom/robertmayer/lambdaj/LambdaJ$SymbolTable;Lcom/robertmayer/lambdaj/LambdaJ$ConsCell;Lcom/robertmayer/lambdaj/LambdaJ$ObjectReader;Lcom/robertmayer/lambdaj/LambdaJ$ObjectWriter;)Lcom/robertmayer/lambdaj/LambdaJ$ConsCell;
      37: astore        5
      39: aload_3
      40: invokeinterface #246,  1          // InterfaceMethod com/robertmayer/lambdaj/LambdaJ$Parser.readObj:()Ljava/lang/Object;
      45: astore        6
      47: aload_0
      48: aload         6
      50: aload         5
      52: iconst_0
      53: iconst_0
      54: invokespecial #73                 // Method eval:(Ljava/lang/Object;Lcom/robertmayer/lambdaj/LambdaJ$ConsCell;II)Ljava/lang/Object;
      57: astore        7
      59: aload_0
      60: getfield      #15                 // Field trace:I
      63: iconst_1
      64: if_icmplt     139
      67: aload_0
      68: getfield      #6                  // Field tracer:Lcom/robertmayer/lambdaj/LambdaJ$Tracer;
      71: new           #61                 // class java/lang/StringBuilder
      74: dup
      75: invokespecial #62                 // Method java/lang/StringBuilder."<init>":()V
      78: ldc           #247                // String *** max eval nesting:
      80: invokevirtual #64                 // Method java/lang/StringBuilder.append:(Ljava/lang/String;)Ljava/lang/StringBuilder;
      83: aload_0
      84: getfield      #103                // Field maxEvalLevel:I
      87: invokevirtual #108                // Method java/lang/StringBuilder.append:(I)Ljava/lang/StringBuilder;
      90: ldc           #248                // String  ***
      92: invokevirtual #64                 // Method java/lang/StringBuilder.append:(Ljava/lang/String;)Ljava/lang/StringBuilder;
      95: invokevirtual #67                 // Method java/lang/StringBuilder.toString:()Ljava/lang/String;
      98: invokeinterface #110,  2          // InterfaceMethod com/robertmayer/lambdaj/LambdaJ$Tracer.println:(Ljava/lang/String;)V
     103: aload_0
     104: getfield      #6                  // Field tracer:Lcom/robertmayer/lambdaj/LambdaJ$Tracer;
     107: new           #61                 // class java/lang/StringBuilder
     110: dup
     111: invokespecial #62                 // Method java/lang/StringBuilder."<init>":()V
     114: ldc           #249                // String *** max stack used:
     116: invokevirtual #64                 // Method java/lang/StringBuilder.append:(Ljava/lang/String;)Ljava/lang/StringBuilder;
     119: aload_0
     120: getfield      #102                // Field maxEvalStack:I
     123: invokevirtual #108                // Method java/lang/StringBuilder.append:(I)Ljava/lang/StringBuilder;
     126: ldc           #248                // String  ***
     128: invokevirtual #64                 // Method java/lang/StringBuilder.append:(Ljava/lang/String;)Ljava/lang/StringBuilder;
     131: invokevirtual #67                 // Method java/lang/StringBuilder.toString:()Ljava/lang/String;
     134: invokeinterface #110,  2          // InterfaceMethod com/robertmayer/lambdaj/LambdaJ$Tracer.println:(Ljava/lang/String;)V
     139: aload         7
     141: areturn

  public java.lang.Object interpretExpressions(com.robertmayer.lambdaj.LambdaJ$ReadSupplier, com.robertmayer.lambdaj.LambdaJ$ReadSupplier, com.robertmayer.lambdaj.LambdaJ$WriteConsumer);
    Code:
       0: new           #240                // class com/robertmayer/lambdaj/LambdaJ$SExpressionParser
       3: dup
       4: aload_0
       5: aload_1
       6: invokespecial #241                // Method com/robertmayer/lambdaj/LambdaJ$SExpressionParser."<init>":(Lcom/robertmayer/lambdaj/LambdaJ;Lcom/robertmayer/lambdaj/LambdaJ$ReadSupplier;)V
       9: astore        4
      11: new           #240                // class com/robertmayer/lambdaj/LambdaJ$SExpressionParser
      14: dup
      15: aload_0
      16: aload_2
      17: invokespecial #241                // Method com/robertmayer/lambdaj/LambdaJ$SExpressionParser."<init>":(Lcom/robertmayer/lambdaj/LambdaJ;Lcom/robertmayer/lambdaj/LambdaJ$ReadSupplier;)V
      20: astore        5
      22: new           #243                // class com/robertmayer/lambdaj/LambdaJ$SExpressionWriter
      25: dup
      26: aload_3
      27: invokespecial #244                // Method com/robertmayer/lambdaj/LambdaJ$SExpressionWriter."<init>":(Lcom/robertmayer/lambdaj/LambdaJ$WriteConsumer;)V
      30: astore        6
      32: aload_0
      33: aload         4
      35: aload         5
      37: aload         6
      39: invokedynamic #250,  0            // InvokeDynamic #35:customEnvironment:()Lcom/robertmayer/lambdaj/LambdaJ$CustomBuiltinsSupplier;
      44: invokevirtual #251                // Method interpretExpressions:(Lcom/robertmayer/lambdaj/LambdaJ$Parser;Lcom/robertmayer/lambdaj/LambdaJ$ObjectReader;Lcom/robertmayer/lambdaj/LambdaJ$ObjectWriter;Lcom/robertmayer/lambdaj/LambdaJ$CustomBuiltinsSupplier;)Ljava/lang/Object;
      47: areturn

  public java.lang.Object interpretExpressions(com.robertmayer.lambdaj.LambdaJ$Parser, com.robertmayer.lambdaj.LambdaJ$ObjectReader, com.robertmayer.lambdaj.LambdaJ$ObjectWriter, com.robertmayer.lambdaj.LambdaJ$CustomBuiltinsSupplier);
    Code:
       0: aload_0
       1: aload_1
       2: invokespecial #242                // Method setSymtab:(Lcom/robertmayer/lambdaj/LambdaJ$SymbolTable;)V
       5: aload_0
       6: aload_0
       7: getfield      #35                 // Field symtab:Lcom/robertmayer/lambdaj/LambdaJ$SymbolTable;
      10: aload         4
      12: aload_1
      13: aload_2
      14: aload_3
      15: invokeinterface #252,  4          // InterfaceMethod com/robertmayer/lambdaj/LambdaJ$CustomBuiltinsSupplier.customEnvironment:(Lcom/robertmayer/lambdaj/LambdaJ$SymbolTable;Lcom/robertmayer/lambdaj/LambdaJ$ObjectReader;Lcom/robertmayer/lambdaj/LambdaJ$ObjectWriter;)Lcom/robertmayer/lambdaj/LambdaJ$ConsCell;
      20: aload_2
      21: aload_3
      22: invokespecial #245                // Method environment:(Lcom/robertmayer/lambdaj/LambdaJ$SymbolTable;Lcom/robertmayer/lambdaj/LambdaJ$ConsCell;Lcom/robertmayer/lambdaj/LambdaJ$ObjectReader;Lcom/robertmayer/lambdaj/LambdaJ$ObjectWriter;)Lcom/robertmayer/lambdaj/LambdaJ$ConsCell;
      25: astore        5
      27: aload_1
      28: invokeinterface #246,  1          // InterfaceMethod com/robertmayer/lambdaj/LambdaJ$Parser.readObj:()Ljava/lang/Object;
      33: astore        6
      35: aload_0
      36: aload         6
      38: aload         5
      40: iconst_0
      41: iconst_0
      42: invokespecial #73                 // Method eval:(Ljava/lang/Object;Lcom/robertmayer/lambdaj/LambdaJ$ConsCell;II)Ljava/lang/Object;
      45: astore        7
      47: aload_0
      48: getfield      #15                 // Field trace:I
      51: iconst_1
      52: if_icmplt     127
      55: aload_0
      56: getfield      #6                  // Field tracer:Lcom/robertmayer/lambdaj/LambdaJ$Tracer;
      59: new           #61                 // class java/lang/StringBuilder
      62: dup
      63: invokespecial #62                 // Method java/lang/StringBuilder."<init>":()V
      66: ldc           #247                // String *** max eval nesting:
      68: invokevirtual #64                 // Method java/lang/StringBuilder.append:(Ljava/lang/String;)Ljava/lang/StringBuilder;
      71: aload_0
      72: getfield      #103                // Field maxEvalLevel:I
      75: invokevirtual #108                // Method java/lang/StringBuilder.append:(I)Ljava/lang/StringBuilder;
      78: ldc           #248                // String  ***
      80: invokevirtual #64                 // Method java/lang/StringBuilder.append:(Ljava/lang/String;)Ljava/lang/StringBuilder;
      83: invokevirtual #67                 // Method java/lang/StringBuilder.toString:()Ljava/lang/String;
      86: invokeinterface #110,  2          // InterfaceMethod com/robertmayer/lambdaj/LambdaJ$Tracer.println:(Ljava/lang/String;)V
      91: aload_0
      92: getfield      #6                  // Field tracer:Lcom/robertmayer/lambdaj/LambdaJ$Tracer;
      95: new           #61                 // class java/lang/StringBuilder
      98: dup
      99: invokespecial #62                 // Method java/lang/StringBuilder."<init>":()V
     102: ldc           #249                // String *** max stack used:
     104: invokevirtual #64                 // Method java/lang/StringBuilder.append:(Ljava/lang/String;)Ljava/lang/StringBuilder;
     107: aload_0
     108: getfield      #102                // Field maxEvalStack:I
     111: invokevirtual #108                // Method java/lang/StringBuilder.append:(I)Ljava/lang/StringBuilder;
     114: ldc           #248                // String  ***
     116: invokevirtual #64                 // Method java/lang/StringBuilder.append:(Ljava/lang/String;)Ljava/lang/StringBuilder;
     119: invokevirtual #67                 // Method java/lang/StringBuilder.toString:()Ljava/lang/String;
     122: invokeinterface #110,  2          // InterfaceMethod com/robertmayer/lambdaj/LambdaJ$Tracer.println:(Ljava/lang/String;)V
     127: aload_1
     128: invokeinterface #246,  1          // InterfaceMethod com/robertmayer/lambdaj/LambdaJ$Parser.readObj:()Ljava/lang/Object;
     133: astore        6
     135: aload         6
     137: ifnonnull     143
     140: aload         7
     142: areturn
     143: goto          35

  public static void main(java.lang.String[]);
    Code:
       0: ldc           #253                // String --version
       2: aload_0
       3: invokestatic  #254                // Method hasFlag:(Ljava/lang/String;[Ljava/lang/String;)Z
       6: ifeq          13
       9: invokestatic  #255                // Method showVersion:()V
      12: return
      13: ldc_w         #256                // String --help
      16: aload_0
      17: invokestatic  #254                // Method hasFlag:(Ljava/lang/String;[Ljava/lang/String;)Z
      20: ifne          33
      23: ldc_w         #257                // String --usage
      26: aload_0
      27: invokestatic  #254                // Method hasFlag:(Ljava/lang/String;[Ljava/lang/String;)Z
      30: ifeq          46
      33: invokestatic  #255                // Method showVersion:()V
      36: getstatic     #258                // Field java/lang/System.out:Ljava/io/PrintStream;
      39: invokevirtual #259                // Method java/io/PrintStream.println:()V
      42: invokestatic  #260                // Method showUsage:()V
      45: return
      46: new           #14                 // class com/robertmayer/lambdaj/LambdaJ
      49: dup
      50: invokespecial #261                // Method "<init>":()V
      53: astore_1
      54: ldc_w         #262                // String --trace
      57: aload_0
      58: invokestatic  #254                // Method hasFlag:(Ljava/lang/String;[Ljava/lang/String;)Z
      61: ifeq          70
      64: aload_1
      65: bipush        6
      67: putfield      #15                 // Field trace:I
      70: ldc_w         #263                // String --no-nil
      73: aload_0
      74: invokestatic  #254                // Method hasFlag:(Ljava/lang/String;[Ljava/lang/String;)Z
      77: ifeq          85
      80: aload_1
      81: iconst_0
      82: putfield      #20                 // Field HAVE_NIL:Z
      85: ldc_w         #264                // String --no-t
      88: aload_0
      89: invokestatic  #254                // Method hasFlag:(Ljava/lang/String;[Ljava/lang/String;)Z
      92: ifeq          100
      95: aload_1
      96: iconst_0
      97: putfield      #21                 // Field HAVE_T:Z
     100: ldc_w         #265                // String --no-extra
     103: aload_0
     104: invokestatic  #254                // Method hasFlag:(Ljava/lang/String;[Ljava/lang/String;)Z
     107: ifeq          115
     110: aload_1
     111: iconst_0
     112: putfield      #22                 // Field HAVE_XTRA:Z
     115: ldc_w         #266                // String --no-double
     118: aload_0
     119: invokestatic  #254                // Method hasFlag:(Ljava/lang/String;[Ljava/lang/String;)Z
     122: ifeq          130
     125: aload_1
     126: iconst_0
     127: putfield      #7                  // Field HAVE_DOUBLE:Z
     130: ldc_w         #267                // String --no-string
     133: aload_0
     134: invokestatic  #254                // Method hasFlag:(Ljava/lang/String;[Ljava/lang/String;)Z
     137: ifeq          145
     140: aload_1
     141: iconst_0
     142: putfield      #8                  // Field HAVE_STRING:Z
     145: ldc_w         #268                // String --no-io
     148: aload_0
     149: invokestatic  #254                // Method hasFlag:(Ljava/lang/String;[Ljava/lang/String;)Z
     152: ifeq          160
     155: aload_1
     156: iconst_0
     157: putfield      #23                 // Field HAVE_IO:Z
     160: ldc_w         #269                // String --no-util
     163: aload_0
     164: invokestatic  #254                // Method hasFlag:(Ljava/lang/String;[Ljava/lang/String;)Z
     167: ifeq          175
     170: aload_1
     171: iconst_0
     172: putfield      #24                 // Field HAVE_UTIL:Z
     175: ldc_w         #270                // String --no-labels
     178: aload_0
     179: invokestatic  #254                // Method hasFlag:(Ljava/lang/String;[Ljava/lang/String;)Z
     182: ifeq          190
     185: aload_1
     186: iconst_0
     187: putfield      #19                 // Field HAVE_LABELS:Z
     190: ldc_w         #271                // String --no-cons
     193: aload_0
     194: invokestatic  #254                // Method hasFlag:(Ljava/lang/String;[Ljava/lang/String;)Z
     197: ifeq          205
     200: aload_1
     201: iconst_0
     202: putfield      #26                 // Field HAVE_CONS:Z
     205: ldc_w         #272                // String --no-cond
     208: aload_0
     209: invokestatic  #254                // Method hasFlag:(Ljava/lang/String;[Ljava/lang/String;)Z
     212: ifeq          220
     215: aload_1
     216: iconst_0
     217: putfield      #27                 // Field HAVE_COND:Z
     220: ldc_w         #273                // String --no-apply
     223: aload_0
     224: invokestatic  #254                // Method hasFlag:(Ljava/lang/String;[Ljava/lang/String;)Z
     227: ifeq          235
     230: aload_1
     231: iconst_0
     232: putfield      #25                 // Field HAVE_APPLY:Z
     235: ldc_w         #274                // String --no-atom
     238: aload_0
     239: invokestatic  #254                // Method hasFlag:(Ljava/lang/String;[Ljava/lang/String;)Z
     242: ifeq          250
     245: aload_1
     246: iconst_0
     247: putfield      #28                 // Field HAVE_ATOM:Z
     250: ldc_w         #275                // String --no-eq
     253: aload_0
     254: invokestatic  #254                // Method hasFlag:(Ljava/lang/String;[Ljava/lang/String;)Z
     257: ifeq          265
     260: aload_1
     261: iconst_0
     262: putfield      #29                 // Field HAVE_EQ:Z
     265: ldc_w         #276                // String --no-quote
     268: aload_0
     269: invokestatic  #254                // Method hasFlag:(Ljava/lang/String;[Ljava/lang/String;)Z
     272: ifeq          280
     275: aload_1
     276: iconst_0
     277: putfield      #2                  // Field HAVE_QUOTE:Z
     280: ldc_w         #277                // String --min+
     283: aload_0
     284: invokestatic  #254                // Method hasFlag:(Ljava/lang/String;[Ljava/lang/String;)Z
     287: ifeq          294
     290: aload_1
     291: invokevirtual #30                 // Method haveMinPlus:()V
     294: ldc_w         #278                // String --min
     297: aload_0
     298: invokestatic  #254                // Method hasFlag:(Ljava/lang/String;[Ljava/lang/String;)Z
     301: ifeq          308
     304: aload_1
     305: invokevirtual #31                 // Method haveMin:()V
     308: ldc_w         #279                // String --lambda+
     311: aload_0
     312: invokestatic  #254                // Method hasFlag:(Ljava/lang/String;[Ljava/lang/String;)Z
     315: ifeq          322
     318: aload_1
     319: invokevirtual #32                 // Method haveLambdaPlus:()V
     322: ldc_w         #280                // String --lambda
     325: aload_0
     326: invokestatic  #254                // Method hasFlag:(Ljava/lang/String;[Ljava/lang/String;)Z
     329: ifeq          336
     332: aload_1
     333: invokevirtual #281                // Method haveLambda:()V
     336: ldc_w         #282                // String --result
     339: aload_0
     340: invokestatic  #254                // Method hasFlag:(Ljava/lang/String;[Ljava/lang/String;)Z
     343: istore_2
     344: aload_0
     345: invokestatic  #283                // Method argError:([Ljava/lang/String;)Z
     348: ifeq          361
     351: getstatic     #16                 // Field java/lang/System.err:Ljava/io/PrintStream;
     354: ldc_w         #284                // String LambdaJ: exiting because of previous errors.
     357: invokevirtual #285                // Method java/io/PrintStream.println:(Ljava/lang/String;)V
     360: return
     361: aconst_null
     362: invokestatic  #286                // Method java/lang/System.console:()Ljava/io/Console;
     365: if_acmpeq     372
     368: iconst_1
     369: goto          373
     372: iconst_0
     373: istore_3
     374: iload_3
     375: ifeq          534
     378: getstatic     #258                // Field java/lang/System.out:Ljava/io/PrintStream;
     381: ldc_w         #287                // String Enter a Lisp expression (or enter 'q or <EOF> to exit):
     384: invokevirtual #285                // Method java/io/PrintStream.println:(Ljava/lang/String;)V
     387: getstatic     #258                // Field java/lang/System.out:Ljava/io/PrintStream;
     390: invokevirtual #259                // Method java/io/PrintStream.println:()V
     393: aconst_null
     394: astore        4
     396: getstatic     #258                // Field java/lang/System.out:Ljava/io/PrintStream;
     399: ldc_w         #288                // String LambdaJ>
     402: invokevirtual #289                // Method java/io/PrintStream.print:(Ljava/lang/String;)V
     405: getstatic     #258                // Field java/lang/System.out:Ljava/io/PrintStream;
     408: invokevirtual #290                // Method java/io/PrintStream.flush:()V
     411: aload_1
     412: getstatic     #291                // Field java/lang/System.in:Ljava/io/InputStream;
     415: dup
     416: invokevirtual #17                 // Method java/lang/Object.getClass:()Ljava/lang/Class;
     419: pop
     420: invokedynamic #292,  0            // InvokeDynamic #36:read:(Ljava/io/InputStream;)Lcom/robertmayer/lambdaj/LambdaJ$ReadSupplier;
     425: getstatic     #258                // Field java/lang/System.out:Ljava/io/PrintStream;
     428: dup
     429: invokevirtual #17                 // Method java/lang/Object.getClass:()Ljava/lang/Class;
     432: pop
     433: invokedynamic #293,  0            // InvokeDynamic #37:print:(Ljava/io/PrintStream;)Lcom/robertmayer/lambdaj/LambdaJ$WriteConsumer;
     438: invokevirtual #294                // Method interpretExpression:(Lcom/robertmayer/lambdaj/LambdaJ$ReadSupplier;Lcom/robertmayer/lambdaj/LambdaJ$WriteConsumer;)Ljava/lang/Object;
     441: invokestatic  #11                 // Method printSEx:(Ljava/lang/Object;)Ljava/lang/String;
     444: astore        4
     446: getstatic     #258                // Field java/lang/System.out:Ljava/io/PrintStream;
     449: invokevirtual #259                // Method java/io/PrintStream.println:()V
     452: getstatic     #258                // Field java/lang/System.out:Ljava/io/PrintStream;
     455: new           #61                 // class java/lang/StringBuilder
     458: dup
     459: invokespecial #62                 // Method java/lang/StringBuilder."<init>":()V
     462: ldc_w         #295                // String result:
     465: invokevirtual #64                 // Method java/lang/StringBuilder.append:(Ljava/lang/String;)Ljava/lang/StringBuilder;
     468: aload         4
     470: invokevirtual #64                 // Method java/lang/StringBuilder.append:(Ljava/lang/String;)Ljava/lang/StringBuilder;
     473: invokevirtual #67                 // Method java/lang/StringBuilder.toString:()Ljava/lang/String;
     476: invokevirtual #285                // Method java/io/PrintStream.println:(Ljava/lang/String;)V
     479: getstatic     #258                // Field java/lang/System.out:Ljava/io/PrintStream;
     482: invokevirtual #259                // Method java/io/PrintStream.println:()V
     485: goto          513
     488: astore        5
     490: getstatic     #258                // Field java/lang/System.out:Ljava/io/PrintStream;
     493: invokevirtual #259                // Method java/io/PrintStream.println:()V
     496: getstatic     #258                // Field java/lang/System.out:Ljava/io/PrintStream;
     499: aload         5
     501: invokevirtual #296                // Method com/robertmayer/lambdaj/LambdaJ$LambdaJError.toString:()Ljava/lang/String;
     504: invokevirtual #285                // Method java/io/PrintStream.println:(Ljava/lang/String;)V
     507: getstatic     #258                // Field java/lang/System.out:Ljava/io/PrintStream;
     510: invokevirtual #259                // Method java/io/PrintStream.println:()V
     513: ldc_w         #297                // String q
     516: aload         4
     518: invokevirtual #298                // Method java/lang/String.equals:(Ljava/lang/Object;)Z
     521: ifeq          396
     524: getstatic     #258                // Field java/lang/System.out:Ljava/io/PrintStream;
     527: ldc_w         #299                // String bye.
     530: invokevirtual #285                // Method java/io/PrintStream.println:(Ljava/lang/String;)V
     533: return
     534: aload_1
     535: getstatic     #291                // Field java/lang/System.in:Ljava/io/InputStream;
     538: dup
     539: invokevirtual #17                 // Method java/lang/Object.getClass:()Ljava/lang/Class;
     542: pop
     543: invokedynamic #292,  0            // InvokeDynamic #36:read:(Ljava/io/InputStream;)Lcom/robertmayer/lambdaj/LambdaJ$ReadSupplier;
     548: getstatic     #291                // Field java/lang/System.in:Ljava/io/InputStream;
     551: dup
     552: invokevirtual #17                 // Method java/lang/Object.getClass:()Ljava/lang/Class;
     555: pop
     556: invokedynamic #292,  0            // InvokeDynamic #36:read:(Ljava/io/InputStream;)Lcom/robertmayer/lambdaj/LambdaJ$ReadSupplier;
     561: getstatic     #258                // Field java/lang/System.out:Ljava/io/PrintStream;
     564: dup
     565: invokevirtual #17                 // Method java/lang/Object.getClass:()Ljava/lang/Class;
     568: pop
     569: invokedynamic #293,  0            // InvokeDynamic #37:print:(Ljava/io/PrintStream;)Lcom/robertmayer/lambdaj/LambdaJ$WriteConsumer;
     574: invokevirtual #300                // Method interpretExpressions:(Lcom/robertmayer/lambdaj/LambdaJ$ReadSupplier;Lcom/robertmayer/lambdaj/LambdaJ$ReadSupplier;Lcom/robertmayer/lambdaj/LambdaJ$WriteConsumer;)Ljava/lang/Object;
     577: invokestatic  #11                 // Method printSEx:(Ljava/lang/Object;)Ljava/lang/String;
     580: astore        4
     582: iload_2
     583: ifeq          594
     586: getstatic     #258                // Field java/lang/System.out:Ljava/io/PrintStream;
     589: aload         4
     591: invokevirtual #285                // Method java/io/PrintStream.println:(Ljava/lang/String;)V
     594: goto          620
     597: astore        4
     599: getstatic     #16                 // Field java/lang/System.err:Ljava/io/PrintStream;
     602: invokevirtual #259                // Method java/io/PrintStream.println:()V
     605: getstatic     #16                 // Field java/lang/System.err:Ljava/io/PrintStream;
     608: aload         4
     610: invokevirtual #296                // Method com/robertmayer/lambdaj/LambdaJ$LambdaJError.toString:()Ljava/lang/String;
     613: invokevirtual #285                // Method java/io/PrintStream.println:(Ljava/lang/String;)V
     616: iconst_1
     617: invokestatic  #301                // Method java/lang/System.exit:(I)V
     620: return
    Exception table:
       from    to  target type
         411   485   488   Class com/robertmayer/lambdaj/LambdaJ$LambdaJError
         534   594   597   Class com/robertmayer/lambdaj/LambdaJ$LambdaJError

  private static boolean hasFlag(java.lang.String, java.lang.String[]);
    Code:
       0: iconst_0
       1: istore_2
       2: iload_2
       3: aload_1
       4: arraylength
       5: if_icmpge     32
       8: aload_1
       9: iload_2
      10: aaload
      11: astore_3
      12: aload_0
      13: aload_3
      14: invokevirtual #298                // Method java/lang/String.equals:(Ljava/lang/Object;)Z
      17: ifeq          26
      20: aload_1
      21: iload_2
      22: aconst_null
      23: aastore
      24: iconst_1
      25: ireturn
      26: iinc          2, 1
      29: goto          2
      32: iconst_0
      33: ireturn

  private static boolean argError(java.lang.String[]);
    Code:
       0: iconst_0
       1: istore_1
       2: aload_0
       3: astore_2
       4: aload_2
       5: arraylength
       6: istore_3
       7: iconst_0
       8: istore        4
      10: iload         4
      12: iload_3
      13: if_icmpge     81
      16: aload_2
      17: iload         4
      19: aaload
      20: astore        5
      22: aload         5
      24: ifnull        75
      27: aload         5
      29: ldc           #185                // String -
      31: invokevirtual #302                // Method java/lang/String.startsWith:(Ljava/lang/String;)Z
      34: ifeq          75
      37: getstatic     #16                 // Field java/lang/System.err:Ljava/io/PrintStream;
      40: new           #61                 // class java/lang/StringBuilder
      43: dup
      44: invokespecial #62                 // Method java/lang/StringBuilder."<init>":()V
      47: ldc_w         #303                // String LambdaJ: unknown commandline argument
      50: invokevirtual #64                 // Method java/lang/StringBuilder.append:(Ljava/lang/String;)Ljava/lang/StringBuilder;
      53: aload         5
      55: invokevirtual #64                 // Method java/lang/StringBuilder.append:(Ljava/lang/String;)Ljava/lang/StringBuilder;
      58: invokevirtual #67                 // Method java/lang/StringBuilder.toString:()Ljava/lang/String;
      61: invokevirtual #285                // Method java/io/PrintStream.println:(Ljava/lang/String;)V
      64: getstatic     #16                 // Field java/lang/System.err:Ljava/io/PrintStream;
      67: ldc_w         #304                // String use '--help' to show available commandline arguments
      70: invokevirtual #285                // Method java/io/PrintStream.println:(Ljava/lang/String;)V
      73: iconst_1
      74: istore_1
      75: iinc          4, 1
      78: goto          10
      81: iload_1
      82: ireturn

  private static void showVersion();
    Code:
       0: getstatic     #258                // Field java/lang/System.out:Ljava/io/PrintStream;
       3: ldc_w         #305                // String LambdaJ $Id: LambdaJ.java,v 1.70 2020/10/13 17:46:06 Robert Exp $
       6: invokevirtual #285                // Method java/io/PrintStream.println:(Ljava/lang/String;)V
       9: return

  private static void showUsage();
    Code:
       0: getstatic     #258                // Field java/lang/System.out:Ljava/io/PrintStream;
       3: ldc_w         #306                // String Usage:\n\ninteractive:\njava -jar lambda.jar [commandline-flags]*\n\nnon-interactive:\njava -jar lambda.jar [commandline-flags]* < lisp-source.lisp\n\nCommandline-flags are:\n\nMisc:\n--version .....  show version and exit\n--help ........  show this message and exit\n--trace .......  print internal interpreter info during\n                 reading/ parsing/ executing programs\n\nFeature flags:\n\n--no-nil ......  don't predefine symbol nil (hint: use '()' instead)\n--no-t ........  don't predefine symbol t (hint: use '(quote t)' instead)\n--no-extra ....  no special form 'if'\n--no-double ...  no number support\n--no-string ...  no string support\n--no-io .......  no primitive functions read/ write/ writeln\n--no-util .....  no primitive functions consp/ symbolp/ listp/ null?/ assoc\n\n--min+ ........  turn off all above features, leaving a Lisp with 10 primitives:\n                   S-expressions\n                   symbols and cons-cells (i.e. lists)\n                   function application\n                   the special form quote\n                   atom, eq, cons, car, cdr, lambda, apply, cond, labels\n\n--no-apply ....  no special form 'apply'\n--no-labels ...  no special form 'labels' (hint: use Y-combinator instead)\n\n--min .........  turn off all above features, leaving a Lisp with 8 primitives:\n                   S-expressions\n                   symbols and cons-cells (i.e. lists)\n                   function application\n                   the special form quote\n                   atom, eq, cons, car, cdr, lambda, cond\n\n--no-cons .....  no primitive functions cons/ car/ cdr\n--no-cond .....  no special form 'cond'\n\n--lambda+ .....  turn off pretty much everything except Lambda calculus,\n                 leaving a Lisp with 4 primitives:\n                   S-expressions\n                   symbols and cons-cells (i.e. lists)\n                   function application\n                   the special form quote\n                   atom, eq, lambda\n\n--no-atom .....  no primitive function 'atom'\n--no-eq .......  no primitive function 'eq'\n--no-quote ....  no special form quote\n\n--lambda ......  turns off yet even more stuff, leaving I guess bare bones Lambda calculus:\n                   S-expressions\n                   symbols and cons-cells (i.e. lists)\n                   function application\n                   lambda
       6: invokevirtual #285                // Method java/io/PrintStream.println:(Ljava/lang/String;)V
       9: return

  private static com.robertmayer.lambdaj.LambdaJ$ConsCell lambda$interpretExpressions$50(com.robertmayer.lambdaj.LambdaJ$SymbolTable, com.robertmayer.lambdaj.LambdaJ$ObjectReader, com.robertmayer.lambdaj.LambdaJ$ObjectWriter);
    Code:
       0: aconst_null
       1: areturn

  private static java.lang.Object lambda$environment$49(com.robertmayer.lambdaj.LambdaJ$ConsCell);
    Code:
       0: ldc           #239                // String mod
       2: aload_0
       3: invokestatic  #177                // Method twoArgs:(Ljava/lang/String;Ljava/lang/Object;)V
       6: ldc           #239                // String mod
       8: aload_0
       9: invokestatic  #173                // Method numberArgs:(Ljava/lang/String;Lcom/robertmayer/lambdaj/LambdaJ$ConsCell;)V
      12: aload_0
      13: invokestatic  #4                  // Method car:(Ljava/lang/Object;)Ljava/lang/Object;
      16: checkcast     #178                // class java/lang/Double
      19: invokevirtual #179                // Method java/lang/Double.doubleValue:()D
      22: aload_0
      23: invokestatic  #5                  // Method cdr:(Ljava/lang/Object;)Ljava/lang/Object;
      26: invokestatic  #4                  // Method car:(Ljava/lang/Object;)Ljava/lang/Object;
      29: checkcast     #178                // class java/lang/Double
      32: invokevirtual #179                // Method java/lang/Double.doubleValue:()D
      35: drem
      36: invokestatic  #184                // Method java/lang/Double.valueOf:(D)Ljava/lang/Double;
      39: areturn

  private static java.lang.Object lambda$environment$48(com.robertmayer.lambdaj.LambdaJ$ConsCell);
    Code:
       0: aload_0
       1: ldc           #238                // String /
       3: dconst_1
       4: invokedynamic #307,  0            // InvokeDynamic #38:applyAsDouble:()Ljava/util/function/DoubleBinaryOperator;
       9: invokestatic  #308                // Method makeSubOp:(Lcom/robertmayer/lambdaj/LambdaJ$ConsCell;Ljava/lang/String;DLjava/util/function/DoubleBinaryOperator;)Ljava/lang/Object;
      12: areturn

  private static double lambda$null$47(double, double);
    Code:
       0: dload_0
       1: dload_2
       2: ddiv
       3: dreturn

  private static java.lang.Object lambda$environment$46(com.robertmayer.lambdaj.LambdaJ$ConsCell);
    Code:
       0: aload_0
       1: ldc           #185                // String -
       3: dconst_0
       4: invokedynamic #309,  0            // InvokeDynamic #39:applyAsDouble:()Ljava/util/function/DoubleBinaryOperator;
       9: invokestatic  #308                // Method makeSubOp:(Lcom/robertmayer/lambdaj/LambdaJ$ConsCell;Ljava/lang/String;DLjava/util/function/DoubleBinaryOperator;)Ljava/lang/Object;
      12: areturn

  private static double lambda$null$45(double, double);
    Code:
       0: dload_0
       1: dload_2
       2: dsub
       3: dreturn

  private static java.lang.Object lambda$environment$44(com.robertmayer.lambdaj.LambdaJ$ConsCell);
    Code:
       0: aload_0
       1: ldc           #237                // String *
       3: dconst_1
       4: invokedynamic #310,  0            // InvokeDynamic #40:applyAsDouble:()Ljava/util/function/DoubleBinaryOperator;
       9: invokestatic  #311                // Method makeAddOp:(Lcom/robertmayer/lambdaj/LambdaJ$ConsCell;Ljava/lang/String;DLjava/util/function/DoubleBinaryOperator;)Ljava/lang/Object;
      12: areturn

  private static double lambda$null$43(double, double);
    Code:
       0: dload_0
       1: dload_2
       2: dmul
       3: dreturn

  private static java.lang.Object lambda$environment$42(com.robertmayer.lambdaj.LambdaJ$ConsCell);
    Code:
       0: aload_0
       1: ldc           #236                // String +
       3: dconst_0
       4: invokedynamic #312,  0            // InvokeDynamic #41:applyAsDouble:()Ljava/util/function/DoubleBinaryOperator;
       9: invokestatic  #311                // Method makeAddOp:(Lcom/robertmayer/lambdaj/LambdaJ$ConsCell;Ljava/lang/String;DLjava/util/function/DoubleBinaryOperator;)Ljava/lang/Object;
      12: areturn

  private static double lambda$null$41(double, double);
    Code:
       0: dload_0
       1: dload_2
       2: dadd
       3: dreturn

  private java.lang.Object lambda$environment$40(com.robertmayer.lambdaj.LambdaJ$ConsCell);
    Code:
       0: aload_0
       1: aload_1
       2: ldc           #233                // String >=
       4: invokedynamic #313,  0            // InvokeDynamic #42:test:()Ljava/util/function/IntPredicate;
       9: invokespecial #314                // Method makeCompareOp:(Lcom/robertmayer/lambdaj/LambdaJ$ConsCell;Ljava/lang/String;Ljava/util/function/IntPredicate;)Ljava/lang/Object;
      12: areturn

  private static boolean lambda$null$39(int);
    Code:
       0: iload_0
       1: iflt          8
       4: iconst_1
       5: goto          9
       8: iconst_0
       9: ireturn

  private java.lang.Object lambda$environment$38(com.robertmayer.lambdaj.LambdaJ$ConsCell);
    Code:
       0: aload_0
       1: aload_1
       2: ldc           #232                // String >
       4: invokedynamic #315,  0            // InvokeDynamic #43:test:()Ljava/util/function/IntPredicate;
       9: invokespecial #314                // Method makeCompareOp:(Lcom/robertmayer/lambdaj/LambdaJ$ConsCell;Ljava/lang/String;Ljava/util/function/IntPredicate;)Ljava/lang/Object;
      12: areturn

  private static boolean lambda$null$37(int);
    Code:
       0: iload_0
       1: ifle          8
       4: iconst_1
       5: goto          9
       8: iconst_0
       9: ireturn

  private java.lang.Object lambda$environment$36(com.robertmayer.lambdaj.LambdaJ$ConsCell);
    Code:
       0: aload_0
       1: aload_1
       2: ldc           #235                // String <=
       4: invokedynamic #316,  0            // InvokeDynamic #44:test:()Ljava/util/function/IntPredicate;
       9: invokespecial #314                // Method makeCompareOp:(Lcom/robertmayer/lambdaj/LambdaJ$ConsCell;Ljava/lang/String;Ljava/util/function/IntPredicate;)Ljava/lang/Object;
      12: areturn

  private static boolean lambda$null$35(int);
    Code:
       0: iload_0
       1: ifgt          8
       4: iconst_1
       5: goto          9
       8: iconst_0
       9: ireturn

  private java.lang.Object lambda$environment$34(com.robertmayer.lambdaj.LambdaJ$ConsCell);
    Code:
       0: aload_0
       1: aload_1
       2: ldc           #234                // String <
       4: invokedynamic #317,  0            // InvokeDynamic #45:test:()Ljava/util/function/IntPredicate;
       9: invokespecial #314                // Method makeCompareOp:(Lcom/robertmayer/lambdaj/LambdaJ$ConsCell;Ljava/lang/String;Ljava/util/function/IntPredicate;)Ljava/lang/Object;
      12: areturn

  private static boolean lambda$null$33(int);
    Code:
       0: iload_0
       1: ifge          8
       4: iconst_1
       5: goto          9
       8: iconst_0
       9: ireturn

  private java.lang.Object lambda$environment$32(com.robertmayer.lambdaj.LambdaJ$ConsCell);
    Code:
       0: aload_0
       1: aload_1
       2: ldc           #231                // String =
       4: invokedynamic #318,  0            // InvokeDynamic #46:test:()Ljava/util/function/IntPredicate;
       9: invokespecial #314                // Method makeCompareOp:(Lcom/robertmayer/lambdaj/LambdaJ$ConsCell;Ljava/lang/String;Ljava/util/function/IntPredicate;)Ljava/lang/Object;
      12: areturn

  private static boolean lambda$null$31(int);
    Code:
       0: iload_0
       1: ifne          8
       4: iconst_1
       5: goto          9
       8: iconst_0
       9: ireturn

  private java.lang.Object lambda$environment$30(com.robertmayer.lambdaj.LambdaJ$ConsCell);
    Code:
       0: ldc           #230                // String numberp
       2: aload_1
       3: invokestatic  #70                 // Method oneArg:(Ljava/lang/String;Ljava/lang/Object;)V
       6: aload_0
       7: aload_1
       8: invokestatic  #4                  // Method car:(Ljava/lang/Object;)Ljava/lang/Object;
      11: invokestatic  #170                // Method numberp:(Ljava/lang/Object;)Z
      14: invokespecial #182                // Method boolResult:(Z)Ljava/lang/Object;
      17: areturn

  private java.lang.Object lambda$environment$29(com.robertmayer.lambdaj.LambdaJ$ConsCell);
    Code:
       0: ldc           #218                // String string-format-locale
       2: aload_1
       3: iconst_2
       4: aconst_null
       5: invokestatic  #75                 // Method nArgs:(Ljava/lang/String;Ljava/lang/Object;ILjava/lang/Object;)V
       8: aload_1
       9: invokestatic  #4                  // Method car:(Ljava/lang/Object;)Ljava/lang/Object;
      12: ifnull        39
      15: aload_0
      16: ldc           #218                // String string-format-locale
      18: ldc_w         #319                // String first argument
      21: aload_1
      22: invokespecial #320                // Method stringArg:(Ljava/lang/String;Ljava/lang/String;Ljava/lang/Object;)V
      25: aload_1
      26: invokestatic  #4                  // Method car:(Ljava/lang/Object;)Ljava/lang/Object;
      29: checkcast     #120                // class com/robertmayer/lambdaj/LambdaJ$LambdaJString
      32: invokestatic  #321                // Method com/robertmayer/lambdaj/LambdaJ$LambdaJString.access$1300:(Lcom/robertmayer/lambdaj/LambdaJ$LambdaJString;)Ljava/lang/String;
      35: astore_2
      36: goto          41
      39: aconst_null
      40: astore_2
      41: aload_0
      42: ldc           #218                // String string-format-locale
      44: ldc_w         #322                // String second argument
      47: aload_1
      48: invokestatic  #5                  // Method cdr:(Ljava/lang/Object;)Ljava/lang/Object;
      51: invokespecial #320                // Method stringArg:(Ljava/lang/String;Ljava/lang/String;Ljava/lang/Object;)V
      54: aload_1
      55: invokestatic  #5                  // Method cdr:(Ljava/lang/Object;)Ljava/lang/Object;
      58: invokestatic  #4                  // Method car:(Ljava/lang/Object;)Ljava/lang/Object;
      61: checkcast     #120                // class com/robertmayer/lambdaj/LambdaJ$LambdaJString
      64: invokestatic  #321                // Method com/robertmayer/lambdaj/LambdaJ$LambdaJString.access$1300:(Lcom/robertmayer/lambdaj/LambdaJ$LambdaJString;)Ljava/lang/String;
      67: astore_3
      68: aload_2
      69: ifnonnull     87
      72: aload_3
      73: aload_1
      74: invokestatic  #5                  // Method cdr:(Ljava/lang/Object;)Ljava/lang/Object;
      77: invokestatic  #5                  // Method cdr:(Ljava/lang/Object;)Ljava/lang/Object;
      80: invokestatic  #323                // Method listToArray:(Ljava/lang/Object;)[Ljava/lang/Object;
      83: invokestatic  #324                // Method java/lang/String.format:(Ljava/lang/String;[Ljava/lang/Object;)Ljava/lang/String;
      86: areturn
      87: aload_2
      88: invokestatic  #325                // Method java/util/Locale.forLanguageTag:(Ljava/lang/String;)Ljava/util/Locale;
      91: astore        4
      93: aload         4
      95: aload_3
      96: aload_1
      97: invokestatic  #5                  // Method cdr:(Ljava/lang/Object;)Ljava/lang/Object;
     100: invokestatic  #5                  // Method cdr:(Ljava/lang/Object;)Ljava/lang/Object;
     103: invokestatic  #323                // Method listToArray:(Ljava/lang/Object;)[Ljava/lang/Object;
     106: invokestatic  #326                // Method java/lang/String.format:(Ljava/util/Locale;Ljava/lang/String;[Ljava/lang/Object;)Ljava/lang/String;
     109: areturn
     110: astore        4
     112: new           #53                 // class com/robertmayer/lambdaj/LambdaJ$LambdaJError
     115: dup
     116: new           #61                 // class java/lang/StringBuilder
     119: dup
     120: invokespecial #62                 // Method java/lang/StringBuilder."<init>":()V
     123: ldc_w         #328                // String string-format-locale: illegal format string and/ or arguments:
     126: invokevirtual #64                 // Method java/lang/StringBuilder.append:(Ljava/lang/String;)Ljava/lang/StringBuilder;
     129: aload         4
     131: invokevirtual #329                // Method java/util/IllegalFormatException.getMessage:()Ljava/lang/String;
     134: invokevirtual #64                 // Method java/lang/StringBuilder.append:(Ljava/lang/String;)Ljava/lang/StringBuilder;
     137: ldc_w         #330                // String \nerror ocurred processing the argument(s)
     140: invokevirtual #64                 // Method java/lang/StringBuilder.append:(Ljava/lang/String;)Ljava/lang/StringBuilder;
     143: aload_1
     144: invokestatic  #11                 // Method printSEx:(Ljava/lang/Object;)Ljava/lang/String;
     147: invokevirtual #64                 // Method java/lang/StringBuilder.append:(Ljava/lang/String;)Ljava/lang/StringBuilder;
     150: invokevirtual #67                 // Method java/lang/StringBuilder.toString:()Ljava/lang/String;
     153: invokespecial #55                 // Method com/robertmayer/lambdaj/LambdaJ$LambdaJError."<init>":(Ljava/lang/String;)V
     156: athrow
    Exception table:
       from    to  target type
          68    86   110   Class java/util/IllegalFormatException
          87   109   110   Class java/util/IllegalFormatException

  private java.lang.Object lambda$environment$28(com.robertmayer.lambdaj.LambdaJ$ConsCell);
    Code:
       0: ldc           #217                // String string-format
       2: aload_1
       3: iconst_1
       4: aconst_null
       5: invokestatic  #75                 // Method nArgs:(Ljava/lang/String;Ljava/lang/Object;ILjava/lang/Object;)V
       8: aload_0
       9: ldc           #217                // String string-format
      11: ldc_w         #319                // String first argument
      14: aload_1
      15: invokespecial #320                // Method stringArg:(Ljava/lang/String;Ljava/lang/String;Ljava/lang/Object;)V
      18: aload_1
      19: invokestatic  #4                  // Method car:(Ljava/lang/Object;)Ljava/lang/Object;
      22: checkcast     #120                // class com/robertmayer/lambdaj/LambdaJ$LambdaJString
      25: invokestatic  #321                // Method com/robertmayer/lambdaj/LambdaJ$LambdaJString.access$1300:(Lcom/robertmayer/lambdaj/LambdaJ$LambdaJString;)Ljava/lang/String;
      28: astore_2
      29: aload_2
      30: aload_1
      31: invokestatic  #5                  // Method cdr:(Ljava/lang/Object;)Ljava/lang/Object;
      34: invokestatic  #323                // Method listToArray:(Ljava/lang/Object;)[Ljava/lang/Object;
      37: invokestatic  #324                // Method java/lang/String.format:(Ljava/lang/String;[Ljava/lang/Object;)Ljava/lang/String;
      40: areturn
      41: astore_3
      42: new           #53                 // class com/robertmayer/lambdaj/LambdaJ$LambdaJError
      45: dup
      46: new           #61                 // class java/lang/StringBuilder
      49: dup
      50: invokespecial #62                 // Method java/lang/StringBuilder."<init>":()V
      53: ldc_w         #331                // String string-format: illegal format string and/ or arguments:
      56: invokevirtual #64                 // Method java/lang/StringBuilder.append:(Ljava/lang/String;)Ljava/lang/StringBuilder;
      59: aload_3
      60: invokevirtual #329                // Method java/util/IllegalFormatException.getMessage:()Ljava/lang/String;
      63: invokevirtual #64                 // Method java/lang/StringBuilder.append:(Ljava/lang/String;)Ljava/lang/StringBuilder;
      66: ldc_w         #330                // String \nerror ocurred processing the argument(s)
      69: invokevirtual #64                 // Method java/lang/StringBuilder.append:(Ljava/lang/String;)Ljava/lang/StringBuilder;
      72: aload_1
      73: invokestatic  #11                 // Method printSEx:(Ljava/lang/Object;)Ljava/lang/String;
      76: invokevirtual #64                 // Method java/lang/StringBuilder.append:(Ljava/lang/String;)Ljava/lang/StringBuilder;
      79: invokevirtual #67                 // Method java/lang/StringBuilder.toString:()Ljava/lang/String;
      82: invokespecial #55                 // Method com/robertmayer/lambdaj/LambdaJ$LambdaJError."<init>":(Ljava/lang/String;)V
      85: athrow
    Exception table:
       from    to  target type
          29    40    41   Class java/util/IllegalFormatException

  private java.lang.Object lambda$environment$27(com.robertmayer.lambdaj.LambdaJ$ConsCell);
    Code:
       0: ldc           #216                // String stringp
       2: aload_1
       3: invokestatic  #70                 // Method oneArg:(Ljava/lang/String;Ljava/lang/Object;)V
       6: aload_0
       7: aload_1
       8: invokestatic  #4                  // Method car:(Ljava/lang/Object;)Ljava/lang/Object;
      11: invokestatic  #144                // Method stringp:(Ljava/lang/Object;)Z
      14: invokespecial #182                // Method boolResult:(Z)Ljava/lang/Object;
      17: areturn

  private static java.lang.Object lambda$environment$26(com.robertmayer.lambdaj.LambdaJ$ConsCell);
    Code:
       0: ldc           #211                // String cdr
       2: aload_0
       3: invokestatic  #332                // Method onePair:(Ljava/lang/String;Lcom/robertmayer/lambdaj/LambdaJ$ConsCell;)V
       6: aload_0
       7: invokestatic  #4                  // Method car:(Ljava/lang/Object;)Ljava/lang/Object;
      10: ifnonnull     15
      13: aconst_null
      14: areturn
      15: aload_0
      16: invokestatic  #4                  // Method car:(Ljava/lang/Object;)Ljava/lang/Object;
      19: invokestatic  #5                  // Method cdr:(Ljava/lang/Object;)Ljava/lang/Object;
      22: areturn

  private static java.lang.Object lambda$environment$25(com.robertmayer.lambdaj.LambdaJ$ConsCell);
    Code:
       0: ldc           #210                // String car
       2: aload_0
       3: invokestatic  #332                // Method onePair:(Ljava/lang/String;Lcom/robertmayer/lambdaj/LambdaJ$ConsCell;)V
       6: aload_0
       7: invokestatic  #4                  // Method car:(Ljava/lang/Object;)Ljava/lang/Object;
      10: ifnonnull     15
      13: aconst_null
      14: areturn
      15: aload_0
      16: invokestatic  #4                  // Method car:(Ljava/lang/Object;)Ljava/lang/Object;
      19: invokestatic  #4                  // Method car:(Ljava/lang/Object;)Ljava/lang/Object;
      22: areturn

  private static java.lang.Object lambda$environment$24(com.robertmayer.lambdaj.LambdaJ$ConsCell);
    Code:
       0: ldc           #212                // String cons
       2: aload_0
       3: invokestatic  #177                // Method twoArgs:(Ljava/lang/String;Ljava/lang/Object;)V
       6: aload_0
       7: invokestatic  #4                  // Method car:(Ljava/lang/Object;)Ljava/lang/Object;
      10: ifnonnull     25
      13: aload_0
      14: invokestatic  #5                  // Method cdr:(Ljava/lang/Object;)Ljava/lang/Object;
      17: invokestatic  #4                  // Method car:(Ljava/lang/Object;)Ljava/lang/Object;
      20: ifnonnull     25
      23: aconst_null
      24: areturn
      25: aload_0
      26: invokestatic  #4                  // Method car:(Ljava/lang/Object;)Ljava/lang/Object;
      29: aload_0
      30: invokestatic  #5                  // Method cdr:(Ljava/lang/Object;)Ljava/lang/Object;
      33: invokestatic  #4                  // Method car:(Ljava/lang/Object;)Ljava/lang/Object;
      36: invokestatic  #3                  // Method cons:(Ljava/lang/Object;Ljava/lang/Object;)Lcom/robertmayer/lambdaj/LambdaJ$ConsCell;
      39: areturn

  private static java.lang.Object lambda$environment$23(com.robertmayer.lambdaj.LambdaJ$ConsCell);
    Code:
       0: ldc           #206                // String assoc
       2: aload_0
       3: invokestatic  #177                // Method twoArgs:(Ljava/lang/String;Ljava/lang/Object;)V
       6: aload_0
       7: invokestatic  #4                  // Method car:(Ljava/lang/Object;)Ljava/lang/Object;
      10: aload_0
      11: invokestatic  #5                  // Method cdr:(Ljava/lang/Object;)Ljava/lang/Object;
      14: invokestatic  #4                  // Method car:(Ljava/lang/Object;)Ljava/lang/Object;
      17: invokestatic  #60                 // Method assoc:(Ljava/lang/Object;Ljava/lang/Object;)Ljava/lang/Object;
      20: areturn

  private java.lang.Object lambda$environment$22(com.robertmayer.lambdaj.LambdaJ$ConsCell);
    Code:
       0: ldc           #204                // String listp
       2: aload_1
       3: invokestatic  #70                 // Method oneArg:(Ljava/lang/String;Ljava/lang/Object;)V
       6: aload_0
       7: aload_1
       8: invokestatic  #4                  // Method car:(Ljava/lang/Object;)Ljava/lang/Object;
      11: invokestatic  #121                // Method listp:(Ljava/lang/Object;)Z
      14: invokespecial #182                // Method boolResult:(Z)Ljava/lang/Object;
      17: areturn

  private java.lang.Object lambda$environment$21(com.robertmayer.lambdaj.LambdaJ$ConsCell);
    Code:
       0: ldc           #203                // String symbolp
       2: aload_1
       3: invokestatic  #70                 // Method oneArg:(Ljava/lang/String;Ljava/lang/Object;)V
       6: aload_0
       7: aload_1
       8: invokestatic  #4                  // Method car:(Ljava/lang/Object;)Ljava/lang/Object;
      11: invokestatic  #1                  // Method symbolp:(Ljava/lang/Object;)Z
      14: invokespecial #182                // Method boolResult:(Z)Ljava/lang/Object;
      17: areturn

  private java.lang.Object lambda$environment$20(com.robertmayer.lambdaj.LambdaJ$ConsCell);
    Code:
       0: ldc           #202                // String consp
       2: aload_1
       3: invokestatic  #70                 // Method oneArg:(Ljava/lang/String;Ljava/lang/Object;)V
       6: aload_0
       7: aload_1
       8: invokestatic  #4                  // Method car:(Ljava/lang/Object;)Ljava/lang/Object;
      11: invokestatic  #83                 // Method consp:(Ljava/lang/Object;)Z
      14: invokespecial #182                // Method boolResult:(Z)Ljava/lang/Object;
      17: areturn

  private java.lang.Object lambda$environment$19(com.robertmayer.lambdaj.LambdaJ$ConsCell);
    Code:
       0: ldc           #205                // String null?
       2: aload_1
       3: invokestatic  #70                 // Method oneArg:(Ljava/lang/String;Ljava/lang/Object;)V
       6: aload_0
       7: aload_1
       8: invokestatic  #4                  // Method car:(Ljava/lang/Object;)Ljava/lang/Object;
      11: ifnonnull     18
      14: iconst_1
      15: goto          19
      18: iconst_0
      19: invokespecial #182                // Method boolResult:(Z)Ljava/lang/Object;
      22: areturn

  private java.lang.Object lambda$environment$18(com.robertmayer.lambdaj.LambdaJ$ObjectWriter, com.robertmayer.lambdaj.LambdaJ$ConsCell);
    Code:
       0: ldc           #196                // String writeln
       2: aload_2
       3: iconst_0
       4: iconst_1
       5: aconst_null
       6: invokestatic  #72                 // Method nArgs:(Ljava/lang/String;Ljava/lang/Object;IILjava/lang/Object;)V
       9: aload_2
      10: ifnonnull     29
      13: aload_1
      14: invokeinterface #333,  1          // InterfaceMethod com/robertmayer/lambdaj/LambdaJ$ObjectWriter.printEol:()V
      19: aload_0
      20: getfield      #49                 // Field expTrue:Ljava/util/function/Supplier;
      23: invokeinterface #69,  1           // InterfaceMethod java/util/function/Supplier.get:()Ljava/lang/Object;
      28: areturn
      29: aload_1
      30: aload_2
      31: invokestatic  #4                  // Method car:(Ljava/lang/Object;)Ljava/lang/Object;
      34: invokeinterface #334,  2          // InterfaceMethod com/robertmayer/lambdaj/LambdaJ$ObjectWriter.printObj:(Ljava/lang/Object;)V
      39: aload_1
      40: invokeinterface #333,  1          // InterfaceMethod com/robertmayer/lambdaj/LambdaJ$ObjectWriter.printEol:()V
      45: aload_0
      46: getfield      #49                 // Field expTrue:Ljava/util/function/Supplier;
      49: invokeinterface #69,  1           // InterfaceMethod java/util/function/Supplier.get:()Ljava/lang/Object;
      54: areturn

  private java.lang.Object lambda$environment$17(com.robertmayer.lambdaj.LambdaJ$ObjectWriter, com.robertmayer.lambdaj.LambdaJ$ConsCell);
    Code:
       0: ldc           #195                // String write
       2: aload_2
       3: invokestatic  #70                 // Method oneArg:(Ljava/lang/String;Ljava/lang/Object;)V
       6: aload_1
       7: aload_2
       8: invokestatic  #4                  // Method car:(Ljava/lang/Object;)Ljava/lang/Object;
      11: invokeinterface #334,  2          // InterfaceMethod com/robertmayer/lambdaj/LambdaJ$ObjectWriter.printObj:(Ljava/lang/Object;)V
      16: aload_0
      17: getfield      #49                 // Field expTrue:Ljava/util/function/Supplier;
      20: invokeinterface #69,  1           // InterfaceMethod java/util/function/Supplier.get:()Ljava/lang/Object;
      25: areturn

  private static java.lang.Object lambda$environment$16(com.robertmayer.lambdaj.LambdaJ$ObjectReader, com.robertmayer.lambdaj.LambdaJ$ConsCell);
    Code:
       0: ldc           #194                // String read
       2: aload_1
       3: invokestatic  #335                // Method noArgs:(Ljava/lang/String;Lcom/robertmayer/lambdaj/LambdaJ$ConsCell;)V
       6: aload_0
       7: invokeinterface #336,  1          // InterfaceMethod com/robertmayer/lambdaj/LambdaJ$ObjectReader.readObj:()Ljava/lang/Object;
      12: areturn

  private java.lang.Object lambda$environment$15(com.robertmayer.lambdaj.LambdaJ$ConsCell);
    Code:
       0: ldc           #190                // String atom
       2: aload_1
       3: invokestatic  #70                 // Method oneArg:(Ljava/lang/String;Ljava/lang/Object;)V
       6: aload_0
       7: aload_1
       8: invokestatic  #4                  // Method car:(Ljava/lang/Object;)Ljava/lang/Object;
      11: invokestatic  #68                 // Method atom:(Ljava/lang/Object;)Z
      14: invokespecial #182                // Method boolResult:(Z)Ljava/lang/Object;
      17: areturn

  private java.lang.Object lambda$environment$14(com.robertmayer.lambdaj.LambdaJ$ConsCell);
    Code:
       0: ldc           #188                // String eq
       2: aload_1
       3: invokestatic  #177                // Method twoArgs:(Ljava/lang/String;Ljava/lang/Object;)V
       6: aload_0
       7: aload_1
       8: invokestatic  #4                  // Method car:(Ljava/lang/Object;)Ljava/lang/Object;
      11: aload_1
      12: invokestatic  #5                  // Method cdr:(Ljava/lang/Object;)Ljava/lang/Object;
      15: invokestatic  #4                  // Method car:(Ljava/lang/Object;)Ljava/lang/Object;
      18: if_acmpne     25
      21: iconst_1
      22: goto          26
      25: iconst_0
      26: invokespecial #182                // Method boolResult:(Z)Ljava/lang/Object;
      29: areturn

  private java.lang.Object lambda$setSymtab$13();
    Code:
       0: aload_0
       1: invokespecial #337                // Method makeExpTrue:()Ljava/lang/Object;
       4: astore_1
       5: aload_0
       6: aload_1
       7: invokedynamic #338,  0            // InvokeDynamic #47:get:(Ljava/lang/Object;)Ljava/util/function/Supplier;
      12: putfield      #49                 // Field expTrue:Ljava/util/function/Supplier;
      15: aload_1
      16: areturn

  private static java.lang.Object lambda$null$12(java.lang.Object);
    Code:
       0: aload_0
       1: areturn

  private java.lang.Object lambda$setSymtab$11(com.robertmayer.lambdaj.LambdaJ$SymbolTable);
    Code:
       0: aload_1
       1: ldc           #52                 // String quote
       3: invokeinterface #51,  2           // InterfaceMethod com/robertmayer/lambdaj/LambdaJ$SymbolTable.intern:(Ljava/lang/String;)Ljava/lang/Object;
       8: astore_2
       9: aload_0
      10: aload_2
      11: invokedynamic #339,  0            // InvokeDynamic #48:get:(Ljava/lang/Object;)Ljava/util/function/Supplier;
      16: putfield      #47                 // Field sQuote:Ljava/util/function/Supplier;
      19: aload_2
      20: areturn

  private static java.lang.Object lambda$null$10(java.lang.Object);
    Code:
       0: aload_0
       1: areturn

  private java.lang.Object lambda$setSymtab$9(com.robertmayer.lambdaj.LambdaJ$SymbolTable);
    Code:
       0: aload_1
       1: ldc           #74                 // String lambda
       3: invokeinterface #51,  2           // InterfaceMethod com/robertmayer/lambdaj/LambdaJ$SymbolTable.intern:(Ljava/lang/String;)Ljava/lang/Object;
       8: astore_2
       9: aload_0
      10: aload_2
      11: invokedynamic #340,  0            // InvokeDynamic #49:get:(Ljava/lang/Object;)Ljava/util/function/Supplier;
      16: putfield      #45                 // Field sLambda:Ljava/util/function/Supplier;
      19: aload_2
      20: areturn

  private static java.lang.Object lambda$null$8(java.lang.Object);
    Code:
       0: aload_0
       1: areturn

  private java.lang.Object lambda$setSymtab$7(com.robertmayer.lambdaj.LambdaJ$SymbolTable);
    Code:
       0: aload_1
       1: ldc           #76                 // String labels
       3: invokeinterface #51,  2           // InterfaceMethod com/robertmayer/lambdaj/LambdaJ$SymbolTable.intern:(Ljava/lang/String;)Ljava/lang/Object;
       8: astore_2
       9: aload_0
      10: aload_2
      11: invokedynamic #341,  0            // InvokeDynamic #50:get:(Ljava/lang/Object;)Ljava/util/function/Supplier;
      16: putfield      #43                 // Field sLabels:Ljava/util/function/Supplier;
      19: aload_2
      20: areturn

  private static java.lang.Object lambda$null$6(java.lang.Object);
    Code:
       0: aload_0
       1: areturn

  private java.lang.Object lambda$setSymtab$5(com.robertmayer.lambdaj.LambdaJ$SymbolTable);
    Code:
       0: aload_1
       1: ldc           #71                 // String if
       3: invokeinterface #51,  2           // InterfaceMethod com/robertmayer/lambdaj/LambdaJ$SymbolTable.intern:(Ljava/lang/String;)Ljava/lang/Object;
       8: astore_2
       9: aload_0
      10: aload_2
      11: invokedynamic #342,  0            // InvokeDynamic #51:get:(Ljava/lang/Object;)Ljava/util/function/Supplier;
      16: putfield      #41                 // Field sIf:Ljava/util/function/Supplier;
      19: aload_2
      20: areturn

  private static java.lang.Object lambda$null$4(java.lang.Object);
    Code:
       0: aload_0
       1: areturn

  private java.lang.Object lambda$setSymtab$3(com.robertmayer.lambdaj.LambdaJ$SymbolTable);
    Code:
       0: aload_1
       1: ldc_w         #343                // String cond
       4: invokeinterface #51,  2           // InterfaceMethod com/robertmayer/lambdaj/LambdaJ$SymbolTable.intern:(Ljava/lang/String;)Ljava/lang/Object;
       9: astore_2
      10: aload_0
      11: aload_2
      12: invokedynamic #344,  0            // InvokeDynamic #52:get:(Ljava/lang/Object;)Ljava/util/function/Supplier;
      17: putfield      #39                 // Field sCond:Ljava/util/function/Supplier;
      20: aload_2
      21: areturn

  private static java.lang.Object lambda$null$2(java.lang.Object);
    Code:
       0: aload_0
       1: areturn

  private java.lang.Object lambda$setSymtab$1(com.robertmayer.lambdaj.LambdaJ$SymbolTable);
    Code:
       0: aload_1
       1: ldc           #79                 // String apply
       3: invokeinterface #51,  2           // InterfaceMethod com/robertmayer/lambdaj/LambdaJ$SymbolTable.intern:(Ljava/lang/String;)Ljava/lang/Object;
       8: astore_2
       9: aload_0
      10: aload_2
      11: invokedynamic #345,  0            // InvokeDynamic #53:get:(Ljava/lang/Object;)Ljava/util/function/Supplier;
      16: putfield      #37                 // Field sApply:Ljava/util/function/Supplier;
      19: aload_2
      20: areturn

  private static java.lang.Object lambda$null$0(java.lang.Object);
    Code:
       0: aload_0
       1: areturn

  static java.lang.String access$000(java.lang.Object);
    Code:
       0: aload_0
       1: invokestatic  #12                 // Method printObj:(Ljava/lang/Object;)Ljava/lang/String;
       4: areturn

  static java.lang.String access$200(java.lang.Object);
    Code:
       0: aload_0
       1: invokestatic  #11                 // Method printSEx:(Ljava/lang/Object;)Ljava/lang/String;
       4: areturn

  static boolean access$300(int);
    Code:
       0: iload_0
       1: invokestatic  #10                 // Method isWhiteSpace:(I)Z
       4: ireturn

  static boolean access$400(int);
    Code:
       0: iload_0
       1: invokestatic  #9                  // Method isSExSyntaxChar:(I)Z
       4: ireturn

  static boolean access$500(com.robertmayer.lambdaj.LambdaJ);
    Code:
       0: aload_0
       1: getfield      #8                  // Field HAVE_STRING:Z
       4: ireturn

  static boolean access$600(com.robertmayer.lambdaj.LambdaJ);
    Code:
       0: aload_0
       1: getfield      #7                  // Field HAVE_DOUBLE:Z
       4: ireturn

  static com.robertmayer.lambdaj.LambdaJ$Tracer access$700(com.robertmayer.lambdaj.LambdaJ);
    Code:
       0: aload_0
       1: getfield      #6                  // Field tracer:Lcom/robertmayer/lambdaj/LambdaJ$Tracer;
       4: areturn

  static java.lang.Object access$800(java.lang.Object);
    Code:
       0: aload_0
       1: invokestatic  #5                  // Method cdr:(Ljava/lang/Object;)Ljava/lang/Object;
       4: areturn

  static java.lang.Object access$900(java.lang.Object);
    Code:
       0: aload_0
       1: invokestatic  #4                  // Method car:(Ljava/lang/Object;)Ljava/lang/Object;
       4: areturn

  static com.robertmayer.lambdaj.LambdaJ$ConsCell access$1000(java.lang.Object, java.lang.Object);
    Code:
       0: aload_0
       1: aload_1
       2: invokestatic  #3                  // Method cons:(Ljava/lang/Object;Ljava/lang/Object;)Lcom/robertmayer/lambdaj/LambdaJ$ConsCell;
       5: areturn

  static boolean access$1100(com.robertmayer.lambdaj.LambdaJ);
    Code:
       0: aload_0
       1: getfield      #2                  // Field HAVE_QUOTE:Z
       4: ireturn

  static boolean access$1200(java.lang.Object);
    Code:
       0: aload_0
       1: invokestatic  #1                  // Method symbolp:(Ljava/lang/Object;)Z
       4: ireturn

  static {};
    Code:
       0: ldc_w         #346                // String [\"]
       3: invokestatic  #347                // Method java/util/regex/Pattern.compile:(Ljava/lang/String;)Ljava/util/regex/Pattern;
       6: putstatic     #147                // Field dQuotePattern:Ljava/util/regex/Pattern;
       9: ldc_w         #348                // String [\\]([^\"])
      12: invokestatic  #347                // Method java/util/regex/Pattern.compile:(Ljava/lang/String;)Ljava/util/regex/Pattern;
      15: putstatic     #151                // Field bSlashPattern:Ljava/util/regex/Pattern;
      18: return
}
